Workbook

Sheet README
A1: База мест Voyz — одна карточка на лист
A2: Выгружено 2026-10-21 · карточек: 112
A4: Как пользоваться
A5: «Оглавление» — список всех карточек со ссылками (клик по id открывает лист). Сводка справа.
A6: Лист карточки называется её id (kg-skazka). Разделы идут в порядке карточки в приложении: Основное → Плашки → Тексты → Медиа → Дорога → Сезон → Важно → Ночлег и еда → На месте → Сервисы → Бюджет → Отзывы → Рядом → Проверка → Перевод EN.
A7: Поля: подпись в колонке B, значение — в колонке C. Жёлтая подпись — обязательное поле. Выпадающие списки — у страны, публикации, статуса, категории, региона, плашек.
A8: Списки (фото, подъезды, ночлег, тропы…): зелёная строка с названием, под ней подписи колонок и записи. Новая запись — в пустую строку под таблицей; если нужно больше, вставьте строку (Ctrl+«+») внутри таблицы.
A9: Колонку A (серые служебные метки) не трогайте — по ним программа читает файл.
A11: Как добавить новое место
A12: 1. Правой кнопкой по листу «_шаблон» → «Переместить или скопировать» → «Создать копию».
A13: 2. Переименуйте копию в id нового места: kg-… или alt-…, латиница и дефисы (например kg-ala-kul). В поле id впишите то же самое.
A14: 3. Заполните жёлтые поля, добавьте фото (файлы — в папку assets/img проекта), подъезды, ночлег. Публикация = черновик, пока не готово.
... A27: Схема и проверки — tools/places_xlsx.py, чтение/запись этого формата — tools/places_cards.py, описание — docs/09_DATA_EXCEL.md.

Sheet Оглавление
A1: id | B1: name | C1: country | D1: publish | E1: status | F1: cat | G1: reg | H1: photos | I1: routes | J1: stays
A2: Карточка (ссылка) | B2: Название | C2: Страна | D2: Публикация | E2: Статус | F2: Категория | G2: Регион | H2: Фото | I2: Подъездов | J2: Ночлег | L2: Сводка
A3: kg-skazka | B3: ='kg-skazka'!C7 | C3: ='kg-skazka'!C4 | D3: ='kg-skazka'!C5 | E3: ='kg-skazka'!C6 | F3: ='kg-skazka'!C9 | G3: ='kg-skazka'!C10 | H3: 2 | I3: 3 | J3: 8 | L3: Карточек | M3: =COUNTA(A3:A114)
A4: kg-altyn-arashan | B4: ='kg-altyn-arashan'!C7 | C4: ='kg-altyn-arashan'!C4 | D4: ='kg-altyn-arashan'!C5 | E4: ='kg-altyn-arashan'!C6 | F4: ='kg-altyn-arashan'!C9 | G4: ='kg-altyn-arashan'!C10 | H4: 2 | I4: 2 | J4: 7 | L4: Кыргызстан | M4: =COUNTIF(C3:C114,"kg")
A5: kg-son-kul | B5: ='kg-son-kul'!C7 | C5: ='kg-son-kul'!C4 | D5: ='kg-son-kul'!C5 | E5: ='kg-son-kul'!C6 | F5: ='kg-son-kul'!C9 | G5: ='kg-son-kul'!C10 | H5: 2 | I5: 5 | J5: 8 | L5: Алтай | M5: =COUNTIF(C3:C114,"alt")
A6: kg-0002 | B6: ='kg-0002'!C7 | C6: ='kg-0002'!C4 | D6: ='kg-0002'!C5 | E6: ='kg-0002'!C6 | F6: ='kg-0002'!C9 | G6: ='kg-0002'!C10 | H6: 0 | I6: 2 | J6: 4 | L6: Опубликовано | M6: =COUNTIF(D3:D114,"опубликовано")
A7: kg-0003 | B7: ='kg-0003'!C7 | C7: ='kg-0003'!C4 | D7: ='kg-0003'!C5 | E7: ='kg-0003'!C6 | F7: ='kg-0003'!C9 | G7: ='kg-0003'!C10 | H7: 2 | I7: 1 | J7: 6 | L7: Черновиков | M7: =COUNTIF(D3:D114,"черновик")
A8: kg-0004 | B8: ='kg-0004'!C7 | C8: ='kg-0004'!C4 | D8: ='kg-0004'!C5 | E8: ='kg-0004'!C6 | F8: ='kg-0004'!C9 | G8: ='kg-0004'!C10 | H8: 2 | I8: 3 | J8: 5 | L8: Без фото | M8: =COUNTIF(H3:H114,0)
A9: kg-0007 | B9: ='kg-0007'!C7 | C9: ='kg-0007'!C4 | D9: ='kg-0007'!C5 | E9: ='kg-0007'!C6 | F9: ='kg-0007'!C9 | G9: ='kg-0007'!C10 | H9: 2 | I9: 2 | J9: 7 | L9: Открытых тикетов | M9: =COUNTIF('Тикеты'!F:F,"открыт")
A10: kg-0009 | B10: ='kg-0009'!C7 | C10: ='kg-0009'!C4 | D10: ='kg-0009'!C5 | E10: ='kg-0009'!C6 | F10: ='kg-0009'!C9 | G10: ='kg-0009'!C10 | H10: 2 | I10: 4 | J10: 8 | L10: В работе | M10: =COUNTIF('Тикеты'!F:F,"в работе")
A11: kg-0010 | B11: ='kg-0010'!C7 | C11: ='kg-0010'!C4 | D11: ='kg-0010'!C5 | E11: ='kg-0010'!C6 | F11: ='kg-0010'!C9 | G11: ='kg-0010'!C10 | H11: 2 | I11: 2 | J11: 5
A12: kg-0011 | B12: ='kg-0011'!C7 | C12: ='kg-0011'!C4 | D12: ='kg-0011'!C5 | E12: ='kg-0011'!C6 | F12: ='kg-0011'!C9 | G12: ='kg-0011'!C10 | H12: 2 | I12: 3 | J12: 6 | L12: Фото/подъезды/ночлег — на момент выгрузки
A13: kg-0012 | B13: ='kg-0012'!C7 | C13: ='kg-0012'!C4 | D13: ='kg-0012'!C5 | E13: ='kg-0012'!C6 | F13: ='kg-0012'!C9 | G13: ='kg-0012'!C10 | H13: 1 | I13: 1 | J13: 8
A14: kg-0013 | B14: ='kg-0013'!C7 | C14: ='kg-0013'!C4 | D14: ='kg-0013'!C5 | E14: ='kg-0013'!C6 | F14: ='kg-0013'!C9 | G14: ='kg-0013'!C10 | H14: 0 | I14: 2 | J14: 6
A15: kg-0014 | B15: ='kg-0014'!C7 | C15: ='kg-0014'!C4 | D15: ='kg-0014'!C5 | E15: ='kg-0014'!C6 | F15: ='kg-0014'!C9 | G15: ='kg-0014'!C10 | H15: 2 | I15: 1 | J15: 6
A16: kg-0016 | B16: ='kg-0016'!C7 | C16: ='kg-0016'!C4 | D16: ='kg-0016'!C5 | E16: ='kg-0016'!C6 | F16: ='kg-0016'!C9 | G16: ='kg-0016'!C10 | H16: 1 | I16: 1 | J16: 6
A17: kg-0017 | B17: ='kg-0017'!C7 | C17: ='kg-0017'!C4 | D17: ='kg-0017'!C5 | E17: ='kg-0017'!C6 | F17: ='kg-0017'!C9 | G17: ='kg-0017'!C10 | H17: 2 | I17: 2 | J17: 4
A18: kg-0018 | B18: ='kg-0018'!C7 | C18: ='kg-0018'!C4 | D18: ='kg-0018'!C5 | E18: ='kg-0018'!C6 | F18: ='kg-0018'!C9 | G18: ='kg-0018'!C10 | H18: 0 | I18: 2 | J18: 3
A19: kg-0019 | B19: ='kg-0019'!C7 | C19: ='kg-0019'!C4 | D19: ='kg-0019'!C5 | E19: ='kg-0019'!C6 | F19: ='kg-0019'!C9 | G19: ='kg-0019'!C10 | H19: 0 | I19: 2 | J19: 3
A20: kg-0020 | B20: ='kg-0020'!C7 | C20: ='kg-0020'!C4 | D20: ='kg-0020'!C5 | E20: ='kg-0020'!C6 | F20: ='kg-0020'!C9 | G20: ='kg-0020'!C10 | H20: 0 | I20: 1 | J20: 6
A21: kg-0021 | B21: ='kg-0021'!C7 | C21: ='kg-0021'!C4 | D21: ='kg-0021'!C5 | E21: ='kg-0021'!C6 | F21: ='kg-0021'!C9 | G21: ='kg-0021'!C10 | H21: 1 | I21: 2 | J21: 6
A22: kg-0022 | B22: ='kg-0022'!C7 | C22: ='kg-0022'!C4 | D22: ='kg-0022'!C5 | E22: ='kg-0022'!C6 | F22: ='kg-0022'!C9 | G22: ='kg-0022'!C10 | H22: 0 | I22: 1 | J22: 5
A23: kg-0023 | B23: ='kg-0023'!C7 | C23: ='kg-0023'!C4 | D23: ='kg-0023'!C5 | E23: ='kg-0023'!C6 | F23: ='kg-0023'!C9 | G23: ='kg-0023'!C10 | H23: 2 | I23: 1 | J23: 4
A24: kg-0027 | B24: ='kg-0027'!C7 | C24: ='kg-0027'!C4 | D24: ='kg-0027'!C5 | E24: ='kg-0027'!C6 | F24: ='kg-0027'!C9 | G24: ='kg-0027'!C10 | H24: 2 | I24: 2 | J24: 6
A25: kg-0028 | B25: ='kg-0028'!C7 | C25: ='kg-0028'!C4 | D25: ='kg-0028'!C5 | E25: ='kg-0028'!C6 | F25: ='kg-0028'!C9 | G25: ='kg-0028'!C10 | H25: 0 | I25: 1 | J25: 7
A26: kg-0029 | B26: ='kg-0029'!C7 | C26: ='kg-0029'!C4 | D26: ='kg-0029'!C5 | E26: ='kg-0029'!C6 | F26: ='kg-0029'!C9 | G26: ='kg-0029'!C10 | H26: 2 | I26: 2 | J26: 2
A27: kg-0030 | B27: ='kg-0030'!C7 | C27: ='kg-0030'!C4 | D27: ='kg-0030'!C5 | E27: ='kg-0030'!C6 | F27: ='kg-0030'!C9 | G27: ='kg-0030'!C10 | H27: 1 | I27: 1 | J27: 5
A28: kg-0031 | B28: ='kg-0031'!C7 | C28: ='kg-0031'!C4 | D28: ='kg-0031'!C5 | E28: ='kg-0031'!C6 | F28: ='kg-0031'!C9 | G28: ='kg-0031'!C10 | H28: 0 | I28: 3 | J28: 5
A29: kg-0032 | B29: ='kg-0032'!C7 | C29: ='kg-0032'!C4 | D29: ='kg-0032'!C5 | E29: ='kg-0032'!C6 | F29: ='kg-0032'!C9 | G29: ='kg-0032'!C10 | H29: 2 | I29: 2 | J29: 6
A30: kg-0033 | B30: ='kg-0033'!C7 | C30: ='kg-0033'!C4 | D30: ='kg-0033'!C5 | E30: ='kg-0033'!C6 | F30: ='kg-0033'!C9 | G30: ='kg-0033'!C10 | H30: 0 | I30: 2 | J30: 5
A31: kg-0034 | B31: ='kg-0034'!C7 | C31: ='kg-0034'!C4 | D31: ='kg-0034'!C5 | E31: ='kg-0034'!C6 | F31: ='kg-0034'!C9 | G31: ='kg-0034'!C10 | H31: 2 | I31: 1 | J31: 3
A32: kg-0036 | B32: ='kg-0036'!C7 | C32: ='kg-0036'!C4 | D32: ='kg-0036'!C5 | E32: ='kg-0036'!C6 | F32: ='kg-0036'!C9 | G32: ='kg-0036'!C10 | H32: 0 | I32: 2 | J32: 6
A33: kg-0038 | B33: ='kg-0038'!C7 | C33: ='kg-0038'!C4 | D33: ='kg-0038'!C5 | E33: ='kg-0038'!C6 | F33: ='kg-0038'!C9 | G33: ='kg-0038'!C10 | H33: 1 | I33: 3 | J33: 4
A34: kg-0039 | B34: ='kg-0039'!C7 | C34: ='kg-0039'!C4 | D34: ='kg-0039'!C5 | E34: ='kg-0039'!C6 | F34: ='kg-0039'!C9 | G34: ='kg-0039'!C10 | H34: 2 | I34: 4 | J34: 9
A35: kg-0040 | B35: ='kg-0040'!C7 | C35: ='kg-0040'!C4 | D35: ='kg-0040'!C5 | E35: ='kg-0040'!C6 | F35: ='kg-0040'!C9 | G35: ='kg-0040'!C10 | H35: 0 | I35: 2 | J35: 4
A36: kg-0041 | B36: ='kg-0041'!C7 | C36: ='kg-0041'!C4 | D36: ='kg-0041'!C5 | E36: ='kg-0041'!C6 | F36: ='kg-0041'!C9 | G36: ='kg-0041'!C10 | H36: 2 | I36: 2 | J36: 3
A37: kg-0042 | B37: ='kg-0042'!C7 | C37: ='kg-0042'!C4 | D37: ='kg-0042'!C5 | E37: ='kg-0042'!C6 | F37: ='kg-0042'!C9 | G37: ='kg-0042'!C10 | H37: 2 | I37: 2 | J37: 4
A38: kg-0043 | B38: ='kg-0043'!C7 | C38: ='kg-0043'!C4 | D38: ='kg-0043'!C5 | E38: ='kg-0043'!C6 | F38: ='kg-0043'!C9 | G38: ='kg-0043'!C10 | H38: 2 | I38: 2 | J38: 5
A39: kg-0044 | B39: ='kg-0044'!C7 | C39: ='kg-0044'!C4 | D39: ='kg-0044'!C5 | E39: ='kg-0044'!C6 | F39: ='kg-0044'!C9 | G39: ='kg-0044'!C10 | H39: 2 | I39: 2 | J39: 5
A40: kg-0045 | B40: ='kg-0045'!C7 | C40: ='kg-0045'!C4 | D40: ='kg-0045'!C5 | E40: ='kg-0045'!C6 | F40: ='kg-0045'!C9 | G40: ='kg-0045'!C10 | H40: 2 | I40: 2 | J40: 5
A41: kg-0047 | B41: ='kg-0047'!C7 | C41: ='kg-0047'!C4 | D41: ='kg-0047'!C5 | E41: ='kg-0047'!C6 | F41: ='kg-0047'!C9 | G41: ='kg-0047'!C10 | H41: 0 | I41: 3 | J41: 4
A42: kg-0048 | B42: ='kg-0048'!C7 | C42: ='kg-0048'!C4 | D42: ='kg-0048'!C5 | E42: ='kg-0048'!C6 | F42: ='kg-0048'!C9 | G42: ='kg-0048'!C10 | H42: 0 | I42: 3 | J42: 4
A43: kg-0049 | B43: ='kg-0049'!C7 | C43: ='kg-0049'!C4 | D43: ='kg-0049'!C5 | E43: ='kg-0049'!C6 | F43: ='kg-0049'!C9 | G43: ='kg-0049'!C10 | H43: 0 | I43: 2 | J43: 5
A44: kg-0050 | B44: ='kg-0050'!C7 | C44: ='kg-0050'!C4 | D44: ='kg-0050'!C5 | E44: ='kg-0050'!C6 | F44: ='kg-0050'!C9 | G44: ='kg-0050'!C10 | H44: 2 | I44: 2 | J44: 5
A45: kg-0051 | B45: ='kg-0051'!C7 | C45: ='kg-0051'!C4 | D45: ='kg-0051'!C5 | E45: ='kg-0051'!C6 | F45: ='kg-0051'!C9 | G45: ='kg-0051'!C10 | H45: 0 | I45: 3 | J45: 6
A46: kg-0052 | B46: ='kg-0052'!C7 | C46: ='kg-0052'!C4 | D46: ='kg-0052'!C5 | E46: ='kg-0052'!C6 | F46: ='kg-0052'!C9 | G46: ='kg-0052'!C10 | H46: 2 | I46: 1 | J46: 7
A47: kg-0053 | B47: ='kg-0053'!C7 | C47: ='kg-0053'!C4 | D47: ='kg-0053'!C5 | E47: ='kg-0053'!C6 | F47: ='kg-0053'!C9 | G47: ='kg-0053'!C10 | H47: 0 | I47: 4 | J47: 6
A48: kg-0054 | B48: ='kg-0054'!C7 | C48: ='kg-0054'!C4 | D48: ='kg-0054'!C5 | E48: ='kg-0054'!C6 | F48: ='kg-0054'!C9 | G48: ='kg-0054'!C10 | H48: 0 | I48: 2 | J48: 5
A49: kg-0056 | B49: ='kg-0056'!C7 | C49: ='kg-0056'!C4 | D49: ='kg-0056'!C5 | E49: ='kg-0056'!C6 | F49: ='kg-0056'!C9 | G49: ='kg-0056'!C10 | H49: 1 | I49: 2 | J49: 4
A50: kg-0057 | B50: ='kg-0057'!C7 | C50: ='kg-0057'!C4 | D50: ='kg-0057'!C5 | E50: ='kg-0057'!C6 | F50: ='kg-0057'!C9 | G50: ='kg-0057'!C10 | H50: 1 | I50: 2 | J50: 5
A51: kg-0058 | B51: ='kg-0058'!C7 | C51: ='kg-0058'!C4 | D51: ='kg-0058'!C5 | E51: ='kg-0058'!C6 | F51: ='kg-0058'!C9 | G51: ='kg-0058'!C10 | H51: 0 | I51: 2 | J51: 8
A52: kg-0059 | B52: ='kg-0059'!C7 | C52: ='kg-0059'!C4 | D52: ='kg-0059'!C5 | E52: ='kg-0059'!C6 | F52: ='kg-0059'!C9 | G52: ='kg-0059'!C10 | H52: 1 | I52: 2 | J52: 6
A53: kg-0060 | B53: ='kg-0060'!C7 | C53: ='kg-0060'!C4 | D53: ='kg-0060'!C5 | E53: ='kg-0060'!C6 | F53: ='kg-0060'!C9 | G53: ='kg-0060'!C10 | H53: 2 | I53: 2 | J53: 5
A54: kg-0061 | B54: ='kg-0061'!C7 | C54: ='kg-0061'!C4 | D54: ='kg-0061'!C5 | E54: ='kg-0061'!C6 | F54: ='kg-0061'!C9 | G54: ='kg-0061'!C10 | H54: 2 | I54: 3 | J54: 8
A55: kg-0062 | B55: ='kg-0062'!C7 | C55: ='kg-0062'!C4 | D55: ='kg-0062'!C5 | E55: ='kg-0062'!C6 | F55: ='kg-0062'!C9 | G55: ='kg-0062'!C10 | H55: 2 | I55: 3 | J55: 7
A56: kg-0063 | B56: ='kg-0063'!C7 | C56: ='kg-0063'!C4 | D56: ='kg-0063'!C5 | E56: ='kg-0063'!C6 | F56: ='kg-0063'!C9 | G56: ='kg-0063'!C10 | H56: 2 | I56: 1 | J56: 3
A57: kg-0064 | B57: ='kg-0064'!C7 | C57: ='kg-0064'!C4 | D57: ='kg-0064'!C5 | E57: ='kg-0064'!C6 | F57: ='kg-0064'!C9 | G57: ='kg-0064'!C10 | H57: 1 | I57: 3 | J57: 5
A58: kg-0065 | B58: ='kg-0065'!C7 | C58: ='kg-0065'!C4 | D58: ='kg-0065'!C5 | E58: ='kg-0065'!C6 | F58: ='kg-0065'!C9 | G58: ='kg-0065'!C10 | H58: 0 | I58: 3 | J58: 3
A59: kg-0066 | B59: ='kg-0066'!C7 | C59: ='kg-0066'!C4 | D59: ='kg-0066'!C5 | E59: ='kg-0066'!C6 | F59: ='kg-0066'!C9 | G59: ='kg-0066'!C10 | H59: 0 | I59: 1 | J59: 3
A60: kg-0067 | B60: ='kg-0067'!C7 | C60: ='kg-0067'!C4 | D60: ='kg-0067'!C5 | E60: ='kg-0067'!C6 | F60: ='kg-0067'!C9 | G60: ='kg-0067'!C10 | H60: 2 | I60: 2 | J60: 6
A61: kg-0069 | B61: ='kg-0069'!C7 | C61: ='kg-0069'!C4 | D61: ='kg-0069'!C5 | E61: ='kg-0069'!C6 | F61: ='kg-0069'!C9 | G61: ='kg-0069'!C10 | H61: 2 | I61: 2 | J61: 4
A62: kg-0071 | B62: ='kg-0071'!C7 | C62: ='kg-0071'!C4 | D62: ='kg-0071'!C5 | E62: ='kg-0071'!C6 | F62: ='kg-0071'!C9 | G62: ='kg-0071'!C10 | H62: 1 | I62: 1 | J62: 4
A63: kg-0072 | B63: ='kg-0072'!C7 | C63: ='kg-0072'!C4 | D63: ='kg-0072'!C5 | E63: ='kg-0072'!C6 | F63: ='kg-0072'!C9 | G63: ='kg-0072'!C10 | H63: 1 | I63: 3 | J63: 6
A64: kg-0073 | B64: ='kg-0073'!C7 | C64: ='kg-0073'!C4 | D64: ='kg-0073'!C5 | E64: ='kg-0073'!C6 | F64: ='kg-0073'!C9 | G64: ='kg-0073'!C10 | H64: 1 | I64: 2 | J64: 6
A65: kg-0077 | B65: ='kg-0077'!C7 | C65: ='kg-0077'!C4 | D65: ='kg-0077'!C5 | E65: ='kg-0077'!C6 | F65: ='kg-0077'!C9 | G65: ='kg-0077'!C10 | H65: 1 | I65: 2 | J65: 7
A66: kg-0078 | B66: ='kg-0078'!C7 | C66: ='kg-0078'!C4 | D66: ='kg-0078'!C5 | E66: ='kg-0078'!C6 | F66: ='kg-0078'!C9 | G66: ='kg-0078'!C10 | H66: 2 | I66: 2 | J66: 12
A67: kg-0079 | B67: ='kg-0079'!C7 | C67: ='kg-0079'!C4 | D67: ='kg-0079'!C5 | E67: ='kg-0079'!C6 | F67: ='kg-0079'!C9 | G67: ='kg-0079'!C10 | H67: 0 | I67: 2 | J67: 7
A68: kg-0080 | B68: ='kg-0080'!C7 | C68: ='kg-0080'!C4 | D68: ='kg-0080'!C5 | E68: ='kg-0080'!C6 | F68: ='kg-0080'!C9 | G68: ='kg-0080'!C10 | H68: 2 | I68: 3 | J68: 5
A69: kg-0081 | B69: ='kg-0081'!C7 | C69: ='kg-0081'!C4 | D69: ='kg-0081'!C5 | E69: ='kg-0081'!C6 | F69: ='kg-0081'!C9 | G69: ='kg-0081'!C10 | H69: 2 | I69: 2 | J69: 7
A70: kg-0082 | B70: ='kg-0082'!C7 | C70: ='kg-0082'!C4 | D70: ='kg-0082'!C5 | E70: ='kg-0082'!C6 | F70: ='kg-0082'!C9 | G70: ='kg-0082'!C10 | H70: 0 | I70: 3 | J70: 6
A71: kg-0083 | B71: ='kg-0083'!C7 | C71: ='kg-0083'!C4 | D71: ='kg-0083'!C5 | E71: ='kg-0083'!C6 | F71: ='kg-0083'!C9 | G71: ='kg-0083'!C10 | H71: 2 | I71: 1 | J71: 5
A72: kg-0084 | B72: ='kg-0084'!C7 | C72: ='kg-0084'!C4 | D72: ='kg-0084'!C5 | E72: ='kg-0084'!C6 | F72: ='kg-0084'!C9 | G72: ='kg-0084'!C10 | H72: 2 | I72: 2 | J72: 5
A73: kg-0086 | B73: ='kg-0086'!C7 | C73: ='kg-0086'!C4 | D73: ='kg-0086'!C5 | E73: ='kg-0086'!C6 | F73: ='kg-0086'!C9 | G73: ='kg-0086'!C10 | H73: 2 | I73: 1 | J73: 5
A74: kg-0087 | B74: ='kg-0087'!C7 | C74: ='kg-0087'!C4 | D74: ='kg-0087'!C5 | E74: ='kg-0087'!C6 | F74: ='kg-0087'!C9 | G74: ='kg-0087'!C10 | H74: 0 | I74: 2 | J74: 12
A75: kg-0088 | B75: ='kg-0088'!C7 | C75: ='kg-0088'!C4 | D75: ='kg-0088'!C5 | E75: ='kg-0088'!C6 | F75: ='kg-0088'!C9 | G75: ='kg-0088'!C10 | H75: 2 | I75: 1 | J75: 7
A76: kg-0089 | B76: ='kg-0089'!C7 | C76: ='kg-0089'!C4 | D76: ='kg-0089'!C5 | E76: ='kg-0089'!C6 | F76: ='kg-0089'!C9 | G76: ='kg-0089'!C10 | H76: 2 | I76: 1 | J76: 5
A77: kg-0090 | B77: ='kg-0090'!C7 | C77: ='kg-0090'!C4 | D77: ='kg-0090'!C5 | E77: ='kg-0090'!C6 | F77: ='kg-0090'!C9 | G77: ='kg-0090'!C10 | H77: 2 | I77: 4 | J77: 6
A78: kg-0091 | B78: ='kg-0091'!C7 | C78: ='kg-0091'!C4 | D78: ='kg-0091'!C5 | E78: ='kg-0091'!C6 | F78: ='kg-0091'!C9 | G78: ='kg-0091'!C10 | H78: 2 | I78: 1 | J78: 5
A79: kg-0092 | B79: ='kg-0092'!C7 | C79: ='kg-0092'!C4 | D79: ='kg-0092'!C5 | E79: ='kg-0092'!C6 | F79: ='kg-0092'!C9 | G79: ='kg-0092'!C10 | H79: 0 | I79: 2 | J79: 7
A80: kg-0093 | B80: ='kg-0093'!C7 | C80: ='kg-0093'!C4 | D80: ='kg-0093'!C5 | E80: ='kg-0093'!C6 | F80: ='kg-0093'!C9 | G80: ='kg-0093'!C10 | H80: 2 | I80: 2 | J80: 5
A81: kg-0094 | B81: ='kg-0094'!C7 | C81: ='kg-0094'!C4 | D81: ='kg-0094'!C5 | E81: ='kg-0094'!C6 | F81: ='kg-0094'!C9 | G81: ='kg-0094'!C10 | H81: 2 | I81: 3 | J81: 6
A82: kg-0095 | B82: ='kg-0095'!C7 | C82: ='kg-0095'!C4 | D82: ='kg-0095'!C5 | E82: ='kg-0095'!C6 | F82: ='kg-0095'!C9 | G82: ='kg-0095'!C10 | H82: 0 | I82: 2 | J82: 12
A83: kg-0096 | B83: ='kg-0096'!C7 | C83: ='kg-0096'!C4 | D83: ='kg-0096'!C5 | E83: ='kg-0096'!C6 | F83: ='kg-0096'!C9 | G83: ='kg-0096'!C10 | H83: 0 | I83: 1 | J83: 3
A84: kg-0097 | B84: ='kg-0097'!C7 | C84: ='kg-0097'!C4 | D84: ='kg-0097'!C5 | E84: ='kg-0097'!C6 | F84: ='kg-0097'!C9 | G84: ='kg-0097'!C10 | H84: 0 | I84: 1 | J84: 5
A85: kg-0099 | B85: ='kg-0099'!C7 | C85: ='kg-0099'!C4 | D85: ='kg-0099'!C5 | E85: ='kg-0099'!C6 | F85: ='kg-0099'!C9 | G85: ='kg-0099'!C10 | H85: 2 | I85: 2 | J85: 6
A86: alt-01 | B86: ='alt-01'!C7 | C86: ='alt-01'!C4 | D86: ='alt-01'!C5 | E86: ='alt-01'!C6 | F86: ='alt-01'!C9 | G86: ='alt-01'!C10 | H86: 6 | I86: 3 | J86: 9
A87: alt-02 | B87: ='alt-02'!C7 | C87: ='alt-02'!C4 | D87: ='alt-02'!C5 | E87: ='alt-02'!C6 | F87: ='alt-02'!C9 | G87: ='alt-02'!C10 | H87: 3 | I87: 2 | J87: 1
A88: alt-03 | B88: ='alt-03'!C7 | C88: ='alt-03'!C4 | D88: ='alt-03'!C5 | E88: ='alt-03'!C6 | F88: ='alt-03'!C9 | G88: ='alt-03'!C10 | H88: 5 | I88: 2 | J88: 6
A89: alt-04 | B89: ='alt-04'!C7 | C89: ='alt-04'!C4 | D89: ='alt-04'!C5 | E89: ='alt-04'!C6 | F89: ='alt-04'!C9 | G89: ='alt-04'!C10 | H89: 6 | I89: 2 | J89: 12
A90: alt-05 | B90: ='alt-05'!C7 | C90: ='alt-05'!C4 | D90: ='alt-05'!C5 | E90: ='alt-05'!C6 | F90: ='alt-05'!C9 | G90: ='alt-05'!C10 | H90: 4 | I90: 2 | J90: 5
A91: alt-06 | B91: ='alt-06'!C7 | C91: ='alt-06'!C4 | D91: ='alt-06'!C5 | E91: ='alt-06'!C6 | F91: ='alt-06'!C9 | G91: ='alt-06'!C10 | H91: 2 | I91: 2 | J91: 5
A92: alt-07 | B92: ='alt-07'!C7 | C92: ='alt-07'!C4 | D92: ='alt-07'!C5 | E92: ='alt-07'!C6 | F92: ='alt-07'!C9 | G92: ='alt-07'!C10 | H92: 3 | I92: 2 | J92: 6
A93: alt-08 | B93: ='alt-08'!C7 | C93: ='alt-08'!C4 | D93: ='alt-08'!C5 | E93: ='alt-08'!C6 | F93: ='alt-08'!C9 | G93: ='alt-08'!C10 | H93: 5 | I93: 2 | J93: 2
A94: alt-09 | B94: ='alt-09'!C7 | C94: ='alt-09'!C4 | D94: ='alt-09'!C5 | E94: ='alt-09'!C6 | F94: ='alt-09'!C9 | G94: ='alt-09'!C10 | H94: 2 | I94: 2 | J94: 8
A95: alt-10 | B95: ='alt-10'!C7 | C95: ='alt-10'!C4 | D95: ='alt-10'!C5 | E95: ='alt-10'!C6 | F95: ='alt-10'!C9 | G95: ='alt-10'!C10 | H95: 3 | I95: 2 | J95: 6
A96: alt-11 | B96: ='alt-11'!C7 | C96: ='alt-11'!C4 | D96: ='alt-11'!C5 | E96: ='alt-11'!C6 | F96: ='alt-11'!C9 | G96: ='alt-11'!C10 | H96: 4 | I96: 2 | J96: 9
A97: alt-12 | B97: ='alt-12'!C7 | C97: ='alt-12'!C4 | D97: ='alt-12'!C5 | E97: ='alt-12'!C6 | F97: ='alt-12'!C9 | G97: ='alt-12'!C10 | H97: 3 | I97: 2 | J97: 3
A98: alt-13 | B98: ='alt-13'!C7 | C98: ='alt-13'!C4 | D98: ='alt-13'!C5 | E98: ='alt-13'!C6 | F98: ='alt-13'!C9 | G98: ='alt-13'!C10 | H98: 5 | I98: 2 | J98: 5
A99: alt-14 | B99: ='alt-14'!C7 | C99: ='alt-14'!C4 | D99: ='alt-14'!C5 | E99: ='alt-14'!C6 | F99: ='alt-14'!C9 | G99: ='alt-14'!C10 | H99: 4 | I99: 1 | J99: 4
A100: alt-15 | B100: ='alt-15'!C7 | C100: ='alt-15'!C4 | D100: ='alt-15'!C5 | E100: ='alt-15'!C6 | F100: ='alt-15'!C9 | G100: ='alt-15'!C10 | H100: 4 | I100: 2 | J100: 5
...

Sheet Теги
A1: tag_id | B1: name_ru | C1: name_en | D1: group | E1: description
A2: ID тега (латиница, дефис) | B2: Название RU | C2: Название EN | D2: Группа | E2: Описание
A3: lakes | B3: Озёра | C3: Lakes | D3: категория | E3: Категория «Озёра» (по полю cat)
A4: waterfalls | B4: Водопады | C4: Waterfalls | D4: категория | E4: Категория «Водопады» (по полю cat)
A5: canyons | B5: Каньоны | C5: Canyons | D5: категория | E5: Категория «Каньоны» (по полю cat)
A6: gorges | B6: Ущелья | C6: Gorges | D6: категория | E6: Категория «Ущелья» (по полю cat)
A7: passes | B7: Перевалы и дороги | C7: Passes & roads | D7: категория | E7: Категория «Перевалы и дороги» (по полю cat)
A8: valleys | B8: Долины и панорамы | C8: Valleys & views | D8: категория | E8: Категория «Долины и панорамы» (по полю cat)
A9: mountains | B9: Горы и ледники | C9: Mountains & glaciers | D9: категория | E9: Категория «Горы и ледники» (по полю cat)
A10: parks | B10: Парки и заповедники | C10: Parks & reserves | D10: категория | E10: Категория «Парки и заповедники» (по полю cat)
A11: springs | B11: Источники и курорты | C11: Springs & resorts | D11: категория | E11: Категория «Источники и курорты» (по полю cat)
A12: culture | B12: История и культура | C12: History & culture | D12: категория | E12: Категория «История и культура» (по полю cat)
... A28: hard | B28: Сложное | C28: Hard | D28: сложность | E28: Сложность: высокая

Sheet Тикеты
A1: ticket_id | B1: type | C1: place_id | D1: title | E1: details | F1: status | G1: priority | H1: assignee | I1: created | J1: due | K1: source | L1: done_at
A2: № тикета | B2: Тип | C2: Карточка (id) | D2: Задача | E2: Подробности | F2: Статус | G2: Приоритет | H2: Исполнитель | I2: Создан | J2: Срок | K2: Откуда задача | L2: Закрыт
A3: T-0001 | B3: Фото | C3: kg-0002 | D3: Ущелье Кара-Булак: нет свободных фото | E3: Найти фото с лицензией CC/своё, добавить в assets/img и лист photos | F3: открыт | G3: средний | I3: 2026-10-21 | K3: photos пусто
A4: T-0002 | B4: Фото | C4: kg-0013 | D4: Культурный центр Рух-Ордо: нет свободных фото | E4: Найти фото с лицензией CC/своё, добавить в assets/img и лист photos | F4: открыт | G4: средний | I4: 2026-10-21 | K4: photos пусто
A5: T-0003 | B5: Фото | C5: kg-0018 | D5: Ущелье Чон-Ак-Суу: нет свободных фото | E5: Найти фото с лицензией CC/своё, добавить в assets/img и лист photos | F5: открыт | G5: средний | I5: 2026-10-21 | K5: photos пусто
A6: T-0004 | B6: Фото | C6: kg-0019 | D6: Перевал Кара-Кече: нет свободных фото | E6: Найти фото с лицензией CC/своё, добавить в assets/img и лист photos | F6: открыт | G6: средний | I6: 2026-10-21 | K6: photos пусто
A7: T-0005 | B7: Фото | C7: kg-0020 | D7: Каньоны Ак-Сай: нет свободных фото | E7: Найти фото с лицензией CC/своё, добавить в assets/img и лист photos | F7: открыт | G7: средний | I7: 2026-10-21 | K7: photos пусто
A8: T-0006 | B8: Фото | C8: kg-0022 | D8: Ущелье Шамси: нет свободных фото | E8: Найти фото с лицензией CC/своё, добавить в assets/img и лист photos | F8: открыт | G8: средний | I8: 2026-10-21 | K8: photos пусто
A9: T-0007 | B9: Фото | C9: kg-0028 | D9: Водопад Кегеты: нет свободных фото | E9: Найти фото с лицензией CC/своё, добавить в assets/img и лист photos | F9: открыт | G9: средний | I9: 2026-10-21 | K9: photos пусто
A10: T-0008 | B10: Фото | C10: kg-0031 | D10: Горячие источники Джууку: нет свободных фото | E10: Найти фото с лицензией CC/своё, добавить в assets/img и лист photos | F10: открыт | G10: средний | I10: 2026-10-21 | K10: photos пусто
A11: T-0009 | B11: Фото | C11: kg-0033 | D11: Панорама Шатылы: нет свободных фото | E11: Найти фото с лицензией CC/своё, добавить в assets/img и лист photos | F11: открыт | G11: средний | I11: 2026-10-21 | K11: photos пусто
A12: T-0010 | B12: Фото | C12: kg-0036 | D12: Семеновское ущелье: нет свободных фото | E12: Найти фото с лицензией CC/своё, добавить в assets/img и лист photos | F12: открыт | G12: средний | I12: 2026-10-21 | K12: photos пусто
A13: T-0011 | B13: Уточнить координаты | C13: kg-0038 | D13: Ущелье Каравшин: координаты уточняются | E13: Сверить точку с картой/треком, обновить lat/lon и подъезды | F13: открыт | G13: высокий | I13: 2026-10-21 | K13: status в данных
A14: T-0012 | B14: Фото | C14: kg-0040 | D14: Перевал Кызарт: нет свободных фото | E14: Найти фото с лицензией CC/своё, добавить в assets/img и лист photos | F14: открыт | G14: средний | I14: 2026-10-21 | K14: photos пусто
... A149: T-0147 | B149: Перевод EN | C149: alt-31 | D149: Гора Белуха и Аккемское озеро: вычитать EN-перевод | E149: Лист translations_en; после проверки поставить en_reviewed = да на листе places | F149: открыт | G149: низкий | I149: 2026-10-21 | K149: черновой перевод ИИ

Sheet Справочники
A1: country | B1: publish | C1: status | D1: cat | E1: reg | F1: s_acc | G1: s_diff | H1: s_when | I1: yes_no | J1: ticket_type | K1: ticket_status | L1: priority | M1: license
A2: country | B2: publish | C2: status | D2: cat | E2: reg | F2: s_acc | G2: s_diff | H2: s_when | I2: yes_no | J2: ticket_type | K2: ticket_status | L2: priority | M2: license
A3: kg | B3: опубликовано | C3: Координаты уточняются | D3: Автодорога | E3: Алтайский край (рядом) | F3: Кроссовер | G3: Высокая | H3: Апр – июн | I3: да | J3: Новое место | K3: открыт | L3: высокий | M3: CC (Wikimedia Commons, через tonkosti.ru) — точную версию лицензии сверить на Commons
A4: alt | B4: черновик | C4: Нужна проверка | D4: Альпинистский лагерь | E4: Баткенская область | F4: На любой машине | G4: Лёгкая | H4: Апр – ноя | I4: нет | J4: Дозаполнить данные | K4: в работе | L4: средний | M4: CC BY 2.0
B5: скрыто | C5: Проверено | D5: Археологический памятник | E5: Джалал-Абадская область | F5: Нужен 4×4 | G5: Лёгкая–средняя | H5: Апр – окт | J5: Проверить факты | K5: на проверке | L5: низкий | M5: CC BY 2.5
D6: Водопад | E6: Иссык-Кульская область | F6: По воде | G6: Очень лёгкая | H6: Апр – сен | J6: Уточнить координаты | K6: готово | M6: CC BY 3.0
D7: Водопад; памятник природы республиканского значения | E7: Нарынская область | F7: Только пешком | G7: Сложная | H7: Дек – июн | J7: Фото | K7: отклонён | M7: CC BY 4.0
D8: Водохранилище | E8: Ошская область | G8: См. описание | H8: Июл – сен | J8: Перевод EN | M8: CC BY-SA 2.0
D9: Высокогорное плато | E9: Республика Алтай | G9: Средняя | H9: Июн | J9: Отзыв/жалоба | M9: CC BY-SA 2.5
D10: Гора / озеро | E10: Таласская область | G10: Средняя–высокая | H10: Июн – авг | J10: Другое | M10: CC BY-SA 3.0
D11: Горная долина / Горячие источники | E11: Чуйская область | G11: Средняя–сложная | H11: Июн – окт | M11: CC BY-SA 3.0 de
D12: Горная хижина | H12: Июн – сен | M12: CC BY-SA 4.0
D13: Городище | H13: Круглый год | M13: CC0
D14: Горячие источники | H14: Май – авг | M14: Flickr — лицензию сверить (вероятно CC), права не проверены
D15: Долина | H15: Май – июн | M15: Pixabay Content License
D16: Долина / жайлоо | H16: Май – окт | M16: Public Domain (по данным altapress/kp для фото HiOr) — сверить
D17: Долина / панорама | H17: Май – сен | M17: Public domain
D18: Долина / перевал | H18: Мар – май | M18: Unsplash License
D19: Исторический / духовный объект | H19: Ноя – апр | M19: © Global Look Press
D20: Исторический комплекс | H20: Ноя – сен | M20: © Greenpeace / altapress.ru
D21: Каньон | H21: Сен – июл | M21: © Shutterstock (через Tripster)
D22: Караван-сарай | H22: Сен – окт | M22: © Shutterstock (через tonkosti.ru)
D23: Культурный центр | H23: Янв – апр | M23: © Shutterstock (через tonkosti.ru), права не проверены
D24: Курорт / озеро (всесезонный горнолыжный курорт; озеро — памятник природы) | M24: © Shutterstock / права не проверены
D25: Ледник | M25: © TURISTKA.RU
D26: Ледниковое озеро | M26: © Алтай-Фото
D27: Лес | M27: © Алтайский заповедник / altapress, права не проверены
D28: Мавзолей | M28: © ГАГУ, права не проверены
D29: Мечеть | M29: © КП, права не проверены
D30: Музей | M30: © Комсомольская правда
D31: Музей (краеведческий, археология, этнография, природа, искусство) | M31: © Правительство Алтайского края, права не проверены
D32: Национальный парк | M32: © автор / Т—Ж, права не проверены
D33: Озеро | M33: © автор, права не проверены
D34: Озеро (каскад горных озёр); памятник природы | M34: © администрация Улаганского р-на, права не проверены
D35: Озеро (каскад горных озёр); частично Катунский биосферный заповедник (ЮНЕСКО «Золотые горы Алтая»), Нижнее и Среднее — региональные памятники природы | M35: © парк «Уч Энмек», права не проверены
... D37: Перевал | M37: права не проверены
D38: Петроглифы
D39: Пещеры
D40: Природный памятник
D41: Природный парк
D42: Священная гора
D43: Священное место
D44: Солёное озеро
D45: Урочище
D46: Ущелье
D47: Храм

Sheet _шаблон
A1: #title | B1: Новое место | C1: · ← к оглавлению
A2: #section | B2: Основное
A3: id | B3: ID места (kg-…, alt-…)
A4: country | B4: Страна (kg / alt)
A5: publish | B5: Публикация | C5: черновик
A6: status | B6: Статус проверки | C6: Нужна проверка
A7: name | B7: Название
A8: full | B8: Полное название
A9: cat | B9: Категория
A10: reg | B10: Регион
A11: dist | B11: Район
A12: lat | B12: Широта
A13: lon | B13: Долгота
A14: elev | B14: Высота
A15: near | B15: Ближайший пункт
A16: tags | B16: Теги (через ;)
A17: top | B17: В топе (да/нет)
A18: rank | B18: Место в рейтинге
... A43: #table:photos | B43: Фото — 0
A44: #keys | C44: f | D44: t | E44: w | F44: h | G44: cap | H44: by | I44: lic | J44: page
A45: #labels | B45: № / строки ниже | C45: Файл (img/…) | D45: Миниатюра (img/t_…) | E45: Ширина | F45: Высота | G45: Подпись | H45: Автор | I45: Лицензия | J45: Страница-источник
A47: #table:videos | B47: Видео — 0
A48: #keys | C48: t | D48: u | E48: ch | F48: y
A49: #labels | B49: № / строки ниже | C49: Заголовок | D49: Ссылка | E49: Канал | F49: Год
A51: #table:photo_links | B51: Фото-ссылки (внешние) — 0
A52: #keys | C52: cap | D52: url | E52: by
A53: #labels | B53: № / строки ниже | C53: Подпись | D53: Ссылка | E53: Автор
A56: #section | B56: Дорога
A57: how | B57: Как добраться (кратко)
A58: needcar | B58: Нужна ли машина
A59: self | B59: Самостоятельно / с гидом
A60: roadtype | B60: Тип дороги
A61: traveltime | B61: Время в пути
A62: transfer | B62: Трансфер
A63: p_sum | B63: Дорога: сводка
A64: #table:routes | B64: Подъезды — 0
A65: #keys | C65: rec | D65: title | E65: from | F65: route | G65: km | H65: time | I65: surface | J65: vehicle | K65: season | L65: last | M65: parking_d | N65: parking_price | O65: trail_d | P65: haz | Q65: src | R65: hub | S65: hub_lat | T65: hub_lon | U65: rkm | V65: parking_lat | W65: parking_lon | X65: trail_lat | Y65: trail_lon | Z65: road | AA65: has_rt
A66: #labels | B66: № / строки ниже | C66: Рекомендован (да/нет) | D66: Название варианта | E66: Откуда | F66: Маршрут | G66: Км | H66: Время | I66: Покрытие | J66: Машина | K66: Сезон | L66: Последние АЗС/магазины | M66: Парковка | N66: Парковка: цена | O66: Тропа от парковки | P66: Опасности | Q66: Источник | R66: Город-старт | S66: Старт: широта | T66: Старт: долгота | U66: Км по графу дорог | V66: Парковка: широта | W66: Парковка: долгота | X66: Тропа: широта | Y66: Тропа: долгота | Z66: Геометрия дороги (JSON, генерируется) | AA66: Есть маршрут на карте (да/нет)
A68: #table:transport | B68: Транспорт и туры — 0
A69: #keys | C69: mode | D69: provider | E69: from | F69: details | G69: price | H69: year | I69: contact | J69: src
A70: #labels | B70: № / строки ниже | C70: Вид | D70: Перевозчик | E70: Откуда | F70: Подробно | G70: Цена | H70: Год цены | I70: Контакт | J70: Источник
A73: #section | B73: Сезон и что взять
A74: when | B74: Когда ехать (подробно)
A75: diff | B75: Сложность (подробно)
A76: hours | B76: Часы работы
A77: daytime | B77: Лучшее время суток
A78: p_season | B78: Сезон (подробно)
A79: bring | B79: Что взять
A81: #section | B81: Важно
A82: warn | B82: Важно / предупреждения
A83: entry | B83: Вход (подробно)
A84: net | B84: Связь (подробно)
A85: p_permits | B85: Разрешения
... A91: #table:stays | B91: Ночлег — 0
A92: #keys | C92: name | D92: type | E92: where | F92: season | G92: price | H92: year | I92: contact | J92: src
A93: #labels | B93: № / строки ниже | C93: Название | D93: Тип | E93: Где | F93: Сезон | G93: Цена | H93: Год цены | I93: Контакт | J93: Источник
A95: #table:food | B95: Еда — 0
A96: #keys | C96: name | D96: where | E96: details | F96: src
A97: #labels | B97: № / строки ниже | C97: Название | D97: Где | E97: Подробно | F97: Источник
A100: #section | B100: На месте
A101: camping | B101: Кемпинг
A102: photo_spots | B102: Точки для фото
A103: #table:hikes | B103: Тропы — 0
A104: #keys | C104: name | D104: route | E104: km | F104: gain_m | G104: time | H104: difficulty | I104: marked | J104: track | K104: src
A105: #labels | B105: № / строки ниже | C105: Название | D105: Маршрут | E105: Км | F105: Набор, м | G105: Время | H105: Сложность | I105: Маркировка | J105: Трек (ссылка) | K105: Источник
A107: #table:horses | B107: Конные прогулки — 0
A108: #keys | C108: where | D108: price | E108: guide | F108: notes | G108: src
A109: #labels | B109: № / строки ниже | C109: Где | D109: Цена | E109: Гид | F109: Заметки | G109: Источник
A111: #table:activities | B111: Активности на месте — 0
A112: #keys | C112: activity | D112: details | E112: price | F112: src
A113: #labels | B113: № / строки ниже | C113: Активность | D113: Подробно | E113: Цена | F113: Источник
A115: #table:rent | B115: Прокат — 0
A116: #keys | C116: what | D116: where | E116: price | F116: src
A117: #labels | B117: № / строки ниже | C117: Что | D117: Где | E117: Цена | F117: Источник
A119: #table:itinerary | B119: Готовые планы — 0
A120: #keys | C120: title | D120: plan
A121: #labels | B121: № / строки ниже | C121: Название плана | D121: План
A124: #section | B124: Сервисы рядом
A125: svc_toilets | B125: Сервис: туалеты
A126: svc_water | B126: Сервис: вода
A127: svc_shop | B127: Сервис: магазин
A128: svc_atm | B128: Сервис: банкомат
A129: svc_fuel | B129: Сервис: АЗС
A130: svc_mobile | B130: Сервис: связь
A131: svc_medical | B131: Сервис: медпомощь
A132: svc_rescue | B132: Сервис: спасатели
A134: #section | B134: Бюджет
A135: budget_economy | B135: Бюджет: эконом
A136: budget_comfort | B136: Бюджет: комфорт
... A143: #table:nearby | B143: Рядом — 0
A144: #keys | C144: id | D144: name | E144: km
A145: #labels | B145: № / строки ниже | C145: ID соседнего места | D145: Название | E145: Км
A148: #section | B148: Проверка и качество данных
A149: checked | B149: Как проверено
A150: note | B150: Заметка редакции
A151: gaps | B151: Чего не хватает в данных (каждое с новой строки)
A152: flags | B152: Противоречия источников (каждое с новой строки)
A153: idx | B153: Индекс полноты 0–100
A154: rich | B154: Насыщенность
A155: conf | B155: Достоверность
...

Sheet kg-skazka
A1: #title | B1: Каньон Сказка | C1: kg-skazka · ← к оглавлению
A2: #section | B2: Основное
A3: id | B3: ID места (kg-…, alt-…) | C3: kg-skazka
A4: country | B4: Страна (kg / alt) | C4: kg
A5: publish | B5: Публикация | C5: опубликовано
A6: status | B6: Статус проверки | C6: Проверено
A7: name | B7: Название | C7: Каньон Сказка
A8: full | B8: Полное название | C8: Каньон Сказка (Skazka / Fairy Tale Canyon)
A9: cat | B9: Категория | C9: Каньон
A10: reg | B10: Регион | C10: Иссык-Кульская область
A11: dist | B11: Район | C11: Джети-Огузский район
A12: lat | B12: Широта | C12: 42.1565
A13: lon | B13: Долгота | C13: 77.3543
A14: elev | B14: Высота | C14: ≈1650–1700 м (расчёт: уровень Иссык-Куля 1607 м, каньон на первой террасе над южным берегом; точная отметка входа источниками не опубликована)
A15: near | B15: Ближайший пункт | C15: Тосор (≈8 км на восток от поворота, 10–15 мин на машине). Поворот к каньону — примерно 4 км западнее Тосора на трассе Балыкчи — Каракол (южный берег), ≈120-й км от Балыкчи.
A16: tags | B16: Теги (через ;) | C16: canyons;any-car;easy;no-car;year-round;hiking;yurts
A17: top | B17: В топе (да/нет) | C17: нет
A18: rank | B18: Место в рейтинге | C18: 25
A19: updated_at | B19: Изменено (дата)
A20: updated_by | B20: Кто изменил
A22: #section | B22: Коротко на карточке (плашки)
A23: months | B23: Месяцы сезона (1;2;…12) | C23: 1;2;3;4;5;6;7;8;9;10;11;12
A24: month_scores | B24: Оценка месяцев (JSON: месяц → 2 лучшее, 1 подходит), напр. {"6":1,"7":2} | C24: {"1":1,"2":1,"3":1,"4":1,"5":2,"6":2,"7":1,"8":1,"9":2,"10":2,"11":1,"12":1}
A25: s_diff | B25: Сложность (коротко) | C25: Лёгкая
A26: s_when | B26: Когда (коротко) | C26: Круглый год
A27: s_acc | B27: Доступ (коротко) | C27: На любой машине
A28: s_onsite | B28: Время на месте (коротко) | C28: 40 мин
A29: s_entry | B29: Вход (коротко) | C29: 50 сомов с человека
A30: s_net | B30: Связь (коротко) | C30: У трассы и в…
A31: rating_v | B31: Рейтинг | C31: 4.8
A32: rating_n | B32: Кол-во оценок | C32: 1682
A33: rating_src | B33: Источник рейтинга | C33: Google
A35: #section | B35: Обзор — тексты
A36: short | B36: Коротко (1–2 предложения) | C36: Небольшой каньон из разноцветных глин и песчаников на южном берегу Иссык-Куля между Тосором и Каджи-Саем. Красные, оранжевые, жёлтые и серые гребни; осмотр занимает 1–2 часа, виды на озеро и хребет Терскей-Ала-Тоо с верхних точек.
A37: desc | B37: Описание | C37: Сказка — компактный эрозионный каньон на первой террасе над южным берегом Иссык-Куля, в ≈2 км от трассы Балыкчи — Каракол (поворот примерно на 120-м км от Балыкчи, большой указатель; рядом второй указатель «Jeti-Oguz», у шлагбаума берут плату). Ветер и дождь вырезали в красных и охристых глинах стены, башни, «печные трубы» в духе Каппадокии; самый известный гребень называют «Китайской стеной». По каньону расходится сеть тропинок: короткий круг — около часа, расширенный маршрут со смотровыми площадками — около двух; набор высоты небольшой. С гребней открывается вид на озеро. Снега здесь почти не бывает, поэтому каньон доступен круглый год, но летом в полдень очень жарко, а после дождя глина становится скользкой. Инфраструктуры минимум: будка кассира у шлагбаума, парковка, простой туалет.
A38: guide | B38: Почему стоит приехать / текст аудиогида | C38: Иди не по одной тропе, а поднимись на гребень: именно сверху «Китайская стена» превращается в зубчатую линию, а за ней раскрывается синяя полоса Иссык-Куля. Ищи фигуры сам — путешественники видят здесь дракона, пингвина, замки и спящего великана, и у каждого выходит своя сказка; официальных табличек нет. Лучший свет — рассвет и час перед закатом, когда красные слои загораются, а серые уходят в тень; в обед цвета выгорают, а тени нет совсем. Возьми обувь с протектором: сыпучий песчаник скользит даже в сухую погоду, а после дождя в каньон лучше не ходить. Если осталось время, спустись к берегу — пляж у Тосора считают одним из красивейших на южном берегу.
A39: see | B39: Что посмотреть | C39: Гребень «Китайская стена»; «расписные горы» с жёлто-оранжево-розовыми слоями; «печные трубы» и башни; смотровые точки на гребнях с видом на Иссык-Куль и Терскей-Ала-Тоо; «окна» в скалах. Фигуры дракона, пингвина, замков — условные туристические названия, табличек нет.
A40: skip | B40: Кому не стоит | C40: Если ты уже был в Чарынском каньоне или на «Марсе» у Каджи-Сая и ждёшь масштаба — Сказка заметно меньше. Если на улице ливень или гроза — глина скользкая, сухие русла опасны. Если едешь в полдень в июле без шляпы и воды — тени здесь нет вообще.
A42: #section | B42: Медиа
A43: #table:photos | B43: Фото — 2
A44: #keys | C44: f | D44: t | E44: w | F44: h | G44: cap | H44: by | I44: lic | J44: page
A45: #labels | B45: № / строки ниже | C45: Файл (img/…) | D45: Миниатюра (img/t_…) | E45: Ширина | F45: Высота | G45: Подпись | H45: Автор | I45: Лицензия | J45: Страница-источник
B46: 1 | C46: img/photo-8ad223affb782f97.jpg | D46: img/t_photo-8ad223affb782f97.jpg | E46: 600 | F46: 450 | G46: Fairy Tale Canyon (22-06-2026) (113) | H46: Incall | I46: CC BY-SA 4.0 | J46: https://commons.wikimedia.org/wiki/File:Fairy_Tale_Canyon_(22-06-2026)_(113).jpg
B47: 2 | C47: img/photo-02e36cdcc5f11231.jpg | D47: img/t_photo-02e36cdcc5f11231.jpg | E47: 600 | F47: 450 | G47: Fairy Tale Canyon (22-06-2026) (42) | H47: Incall | I47: CC BY-SA 4.0 | J47: https://commons.wikimedia.org/wiki/File:Fairy_Tale_Canyon_(22-06-2026)_(42).jpg
A49: #table:videos | B49: Видео — 3
A50: #keys | C50: t | D50: u | E50: ch | F50: y
A51: #labels | B51: № / строки ниже | C51: Заголовок | D51: Ссылка | E51: Канал | F51: Год
B52: 1 | C52: Skazka Canyon - The Most Beautiful Place In Kyrgyzstan | D52: https://www.youtube.com/watch?v=ttbX3Wmft4Q | E52: не подтверждён (страница не открывалась) | F52: н/д
B53: 2 | C53: Skazka: Kyrgyzstan's Fairytale Canyon (6 Min) | D53: https://www.youtube.com/watch?v=HuABzkLztRI | E53: не подтверждён | F53: н/д
B54: 3 | C54: Kyrgyzstan's Most Stunning Rock Formations: Skazka Canyon & Jeti-Ögüz | D54: https://www.youtube.com/watch?v=A5WrRW0t6Jw | E54: не подтверждён | F54: н/д
A56: #table:photo_links | B56: Фото-ссылки (внешние) — 6
A57: #keys | C57: cap | D57: url | E57: by
A58: #labels | B58: № / строки ниже | C58: Подпись | D58: Ссылка | E58: Автор
B59: 1 | C59: Fairy Tale Canyon (22-06-2026) (57) | D59: https://commons.wikimedia.org/wiki/File:Fairy_Tale_Canyon_(22-06-2026)_(57).jpg | E59: Incall
B60: 2 | C60: Fairy Tale Canyon (22-06-2026) (60) | D60: https://commons.wikimedia.org/wiki/File:Fairy_Tale_Canyon_(22-06-2026)_(60).jpg | E60: Incall
B61: 3 | C61: Skazka Canyon, Kyrgyzstan (29685812067) | D61: https://commons.wikimedia.org/wiki/File:Skazka_Canyon,_Kyrgyzstan_(29685812067).jpg | E61: Ninara from Helsinki, Finland
B62: 4 | C62: Skazka Canyon, Kyrgyzstan (30754163968) | D62: https://commons.wikimedia.org/wiki/File:Skazka_Canyon,_Kyrgyzstan_(30754163968).jpg | E62: Ninara from Helsinki, Finland
B63: 5 | C63: Skazka Canyon, Kyrgyzstan (42813842430) | D63: https://commons.wikimedia.org/wiki/File:Skazka_Canyon,_Kyrgyzstan_(42813842430).jpg | E63: Ninara from Helsinki, Finland
B64: 6 | C64: Skazka Canyon, Kyrgyzstan (43713805835) | D64: https://commons.wikimedia.org/wiki/File:Skazka_Canyon,_Kyrgyzstan_(43713805835).jpg | E64: Ninara from Helsinki, Finland
A67: #section | B67: Дорога
A68: how | B68: Как добраться (кратко) | C68: Из Бишкека: трасса через Балыкчи по южному берегу, ≈120 км от Балыкчи, поворот направо по указателю «Сказка» примерно в 4 км западнее Тосора; 2 км грунтовки до шлагбаума/парковки. Из Каракола по южной дороге ≈100 км (1,5–2 ч). На общественном транспорте: маршрутка Каракол → Бишкек по южному берегу (№310/315 от южной автостанции Каракола) — попросить высадить у поворота, затем 2 км пешком; из Бишкека маршрутки на Боконбаево/Каджи-Сай с Бишкекского автовокзала (ул. Алма-Атинская 1/1; Западный закрыт с 10.2024) (расписание и цена не подтверждены на 2025–2026).
A69: needcar | B69: Нужна ли машина | C69: Желателен автомобиль или такси; в сухую погоду проходит любая легковая. 4×4 не нужен. Пешком от трассы 2 км — реально при поездке на маршрутке.
A70: self | B70: Самостоятельно / с гидом | C70: Да. Тропы интуитивны, но разветвлены — запоминай путь назад; гид не обязателен.
A71: roadtype | B71: Тип дороги | C71: Асфальт по трассе Балыкчи — Каракол; последние 2 км — грунтовка/гравий до шлагбаума и парковки, в сухую погоду проезжает обычная легковая; после дождя размокает, низкие машины паркуют раньше. TripAdvisor: «песчаная неасфальтированная дорога».
A72: traveltime | B72: Время в пути | C72: От Тосора 10–15 мин, от Боконбаево 35–45 мин, от Каракола 1,5–2 ч, от Балыкчи 2–2,5 ч, от Бишкека ≈4–4,5 ч на машине. Осмотр: 40 мин – 2 ч (до 4 ч с полным обходом).
A73: transfer | B73: Трансфер | C73: Ориентиры 2024 (форум eurasia.travel): такси из Тосора/Тамги в Сказку с 2 ч ожидания — 1500 сомов за машину (3 чел.); частная машина Каракол → Тосор с остановками — 5000 сомов. MYWAY (2026) публикует маршрут Каракол–Сказка–Каракол, цены на странице по запросу. Экскурсия из Бишкека (Sputnik8, 2026) — 430 $ за группу до нескольких человек, 10 ч.
A74: p_sum | B74: Дорога: сводка | C74: Проще всего — своя машина или такси: поворот с трассы Балыкчи — Каракол (южный берег) ≈4 км западнее Тосора, затем 2 км грунтовки до шлагбаума и парковки; 4×4 не нужен. Без машины — маршрутка №315/310 с южной автостанции Каракола (≈2 ч) с высадкой у поворота и 2 км пешком. Ночевать логичнее всего в Тосоре или Тамге (юрты на пляже, гостевые дома 30–50 $), приезжать к рассвету или за 2 часа до заката, обязательно с водой.
A75: #table:routes | B75: Подъезды — 3
A76: #keys | C76: rec | D76: title | E76: from | F76: route | G76: km | H76: time | I76: surface | J76: vehicle | K76: season | L76: last | M76: parking_d | N76: parking_price | O76: trail_d | P76: haz | Q76: src | R76: hub | S76: hub_lat | T76: hub_lon | U76: rkm | V76: parking_lat | W76: parking_lon | X76: trail_lat | Y76: trail_lon | Z76: road | AA76: has_rt
A77: #labels | B77: № / строки ниже | C77: Рекомендован (да/нет) | D77: Название варианта | E77: Откуда | F77: Маршрут | G77: Км | H77: Время | I77: Покрытие | J77: Машина | K77: Сезон | L77: Последние АЗС/магазины | M77: Парковка | N77: Парковка: цена | O77: Тропа от парковки | P77: Опасности | Q77: Источник | R77: Город-старт | S77: Старт: широта | T77: Старт: долгота | U77: Км по графу дорог | V77: Парковка: широта | W77: Парковка: долгота | X77: Тропа: широта | Y77: Тропа: долгота | Z77: Геометрия дороги (JSON, генерируется) | AA77: Есть маршрут на карте (да/нет)
B78: 1 | C78: да | D78: С запада: из Бишкека через Балыкчи по южному берегу | E78: Бишкек (≈270 км) / Балыкчи (≈120 км) | F78: Бишкек → Токмок → Боомское ущелье → Балыкчи → южный берег (Кызыл-Туу, Боконбаево, Каджи-Сай) → поворот направо по указателю «Сказка» ≈4 км западнее Тосора → 2 км грунтовки до шлагбаума | G78: ≈270 от Бишкека, ≈120 от Балыкчи, ≈30–35 от Боконбаево | H78: ≈4–4,5 ч от Бишкека; 2–2,5 ч от Балыкчи; 35–45 мин от Боконбаево | I78: Асфальт по трассе (хорошего качества); последние 2 км — грунт/песчаный гравий до парковки | J78: седан | K78: Круглый год; после дождя грунтовка размокает — низкие машины оставляют раньше | L78: АЗС, банкоматы, магазины — Балыкчи и Боконбаево (последний крупный пункт); магазины и кафе в Каджи-Сае и Тосоре; связь у трассы есть (Beeline усилил Боконбаево/Тамгу в 2026) | M78: Площадка у шлагбаума/будки кассира в ≈2 км от трассы; рядом простой туалет. Парковка небольшая — в сезон тесно из-за автобусов | N78: Входит в сбор ≈50 сомов/чел (2021 Kaktus: 50 сомов с человека на машине, 30 пешком); отдельной платы за машину не найдено | O78: Тропы расходятся прямо от парковки; короткий круг ≈1 ч, расширенный по гребням ≈2 ч | P78: Мокрая глина после дождя, сели в сухих руслах при грозе, жара без тени | Q78: https://brokennavigation.com/travel-guides/central-asia/kyrgyzstan/fairytale-skazka-canyon-kyrgyzstan/ | R78: Бишкек | S78: 42.8746 | T78: 74.5698 | U78: 272 | V78: 42.156489 | W78: 77.354031 | X78: 42.1565 | Y78: 77.3543 | Z78: [[42.876, 74.536], [42.897, 74.598], [42.876, 74.688], [42.88, 74.812], [42.872, 74.927], [42.876, 75.092], [42.835, 75.167], [42.822, 75.212], [42.826, 75.266], [42.822, 75.365], [42.814, 75.389], [42.814, 75.435], [42.806, 75.468], [42.814, 75.563], [42.802, 75.616], [42.748, 75.715], [42.723, 75.789], [42.694, 75.802], [42.661, 75.827], [42.628, 75.794], [42.616, 75.785], [42.6, 75.785], [42.587, 75.794], [42.575, 75.818], [42.525, 75.847], [42.505, 75.872], [42.48, 75.959], [42.468, 76.074], [42.447, 76.144], [42.435, 76.157], [42.41, 76.152], [42.381, 76.165], [42.327, 76.214], [42.311, 76.218], [42.29, 76.239], [42.27, 76.28], [42.29, 76.408], [42.282, 76.458], [42.241, 76.561], [42.142, 76.746], [42.109, 76.891], [42.113, 76.944], [42.109, 77.014], [42.129, 77.283]] | AA78: да
B79: 2 | C79: нет | D79: С востока: из Каракола по южному берегу | E79: Каракол (≈100–112 км) | F79: Каракол → Кызыл-Суу → Джети-Огуз (поворот) → Барскоон → Тамга → Тосор → через ≈4 км после Тосора поворот налево к каньону | G79: ≈100–112 | H79: 1,5–2 ч | I79: Асфальт; последние 2 км грунтовка | J79: седан | K79: Круглый год | L79: АЗС и банкоматы — Каракол, Кызыл-Суу; магазины в Барскооне, Тамге, Тосоре | M79: Та же площадка у шлагбаума | N79: см. выше | O79: От парковки | P79: После 17:00 трудно поймать маршрутку/такси обратно (Nomad's Land) | Q79: https://nomadsland.travel/en/before-you-go/kyrgyzstan/sights/skazka-fairy-tale-canyon | R79: Каракол | S79: 42.4907 | T79: 78.3936 | U79: 103 | V79: 42.156489 | W79: 77.354031 | Z79: [[42.484, 78.4], [42.48, 78.322], [42.447, 78.252], [42.414, 78.157], [42.369, 78.074], [42.34, 78.037], [42.257, 77.827], [42.191, 77.72], [42.15, 77.584], [42.129, 77.456], [42.129, 77.283]] | AA79: да
B80: 3 | C80: нет | D80: Пешком от трассы (при поездке на маршрутке) | E80: Остановка у поворота на трассе | F80: Высадка у указателя «Сказка» → 2 км вверх по грунтовке до шлагбаума (часто подвозят попутки) | G80: 2 (в одну сторону) | H80: 25–35 мин | I80: Грунт | J80: пешком/верхом | K80: Круглый год; летом — утро/вечер | L80: Магазины — Тосор (≈7 км) | M80: — | O80: Шлагбаум/касса | P80: Жара, нет воды | Q80: https://www.margauxsfootprints.com/post/how-to-get-to-skazka-canyon-from-karakol-by-marshrutka | AA80: нет
A82: #table:transport | B82: Транспорт и туры — 9
A83: #keys | C83: mode | D83: provider | E83: from | F83: details | G83: price | H83: year | I83: contact | J83: src
A84: #labels | B84: № / строки ниже | C84: Вид | D84: Перевозчик | E84: Откуда | F84: Подробно | G84: Цена | H84: Год цены | I84: Контакт | J84: Источник
B85: 1 | C85: маршрутка | D85: №315 Каракол → Боконбаево / №310 Каракол → Балыкчи (южный берег) | E85: Каракол, южная автостанция (площадка у дороги) | F85: Отправление по заполнению примерно каждый час ≈11:30–16:30; 1,5–2 ч; попросить высадить у поворота на Сказку | G85: 150 сомов (2023, Broken Navigation); 100–150 сомов (Nomad's Land); в одном отчёте 400 сомов с багажом (Margaux's Footprints, год не указан) | H85: 2023–2025 | I85: — | J85: https://brokennavigation.com/travel-guides/central-asia/kyrgyzstan/fairytale-skazka-canyon-kyrgyzstan/
B86: 2 | C86: маршрутка | D86: Бишкек → Боконбаево / южный берег | E86: Бишкек, Бишкекский автовокзал (ул. Алма-Атинская 1/1 — с 10.2024 все рейсы на Иссык-Куль, Западный автовокзал закрыт) | F86: Южным берегом ходит немного рейсов, дольше и дороже северного; ≈5 ч до Боконбаево, далее маршрутка/такси | G86: не подтверждено; Бишкек–Каракол 500 сомов (2026) | H86: 2024–2026 | I86: — | J86: https://kaktus.media/doc/512072_izmeneny_otpravnye_tochki_mejdygorodnih_marshrytov_iz_bishkeka.html
B87: 3 | C87: маршрутка | D87: Местные рейсы по южному берегу | E87: Тосор | F87: Маршрутки по трассе ≈каждые 20 мин, можно и автостопом | G87: 30–50 сомов | H87: 2023 | I87: — | J87: https://brokennavigation.com/travel-guides/central-asia/kyrgyzstan/fairytale-skazka-canyon-kyrgyzstan/
B88: 4 | C88: такси | D88: Частное такси | E88: Каракол | F88: В одну сторону | G88: 2100 сомов за машину | H88: н/д (Nomad's Land) | I88: — | J88: https://nomadsland.travel/en/before-you-go/kyrgyzstan/sights/skazka-fairy-tale-canyon
B89: 5 | C89: такси | D89: Местные водители Тосора/Тамги | E89: Тосор, Тамга | F89: С ожиданием 2 ч | G89: 1500 сомов за машину (3 чел.) | H89: 2024 | I89: — | J89: eurasia.travel форум (этап 1)
B90: 6 | C90: такси | D90: Yandex Go | E90: Каракол | F90: Сервис работает в Караколе (Эконом, с 12.2025 «Комфорт» от 36 сомов); для межгорода надёжнее договариваться с водителем | G90: по приложению | H90: 2025 | I90: приложение Yandex Go | J90: https://economist.kg/transport/2025/12/19/v-iandieks-go-v-karakolie-poiavilsia-tarif-komfort/
B91: 7 | C91: трансфер | D91: MYWAY | E91: Каракол | F91: Каракол → Сказка → Каракол, легковые/микроавтобусы | G91: на сайте по запросу | H91: 2026 | I91: https://myway.kg/en/transfers/route/karakol-to-fairy-tale-canyon-round-trip/18 | J91: https://myway.kg/en/transfers/route/karakol-to-fairy-tale-canyon-round-trip/18
B92: 8 | C92: тур | D92: Sputnik8 «Каньон Сказка и южный берег Иссык-Куля» | E92: Бишкек | F92: 10 ч, вход включён | G92: 430 $ за машину | H92: 2026 | I92: https://www.sputnik8.com/ru/bishkek/activities/60011-kanon-skazka-i-yuzhnyy-bereg-issyk-kulya | J92: https://www.sputnik8.com/ru/bishkek/activities/60011-kanon-skazka-i-yuzhnyy-bereg-issyk-kulya
B93: 9 | C93: авто с водителем | D93: Частный водитель | E93: Каракол | F93: Каракол → Тосор с остановками Джети-Огуз, Барскоон | G93: 5000 сомов | H93: 2024 | I93: — | J93: eurasia.travel форум (этап 1)
A96: #section | B96: Сезон и что взять
A97: when | B97: Когда ехать (подробно) | C97: Круглый год (снега почти нет). Комфортнее всего май–июнь и сентябрь–октябрь; летом — только рано утром или вечером. В октябре 2022 плату не брали (сезонная касса). Зимой короткий день и возможен лёд.
A98: diff | B98: Сложность (подробно) | C98: Лёгкая: 1–2 ч прогулки, небольшой набор высоты. Осторожность на сыпучих гребнях и крутых спусках; после дождя не ходить.
A99: hours | B99: Часы работы | C99: Google Maps (03.10.2026): ежедневно 24 часа; TripAdvisor: 00:00–23:59. Фактически кассир у шлагбаума работает в светлое время в сезон (май–сентябрь); вне сезона въезд свободный.
A100: daytime | B100: Лучшее время суток | C100: Рассвет (4:00–6:00 летом, по отзывам TripAdvisor) или последние 1–2 часа перед закатом — боковой свет и прохлада. Полдень избегать.
A101: p_season | B101: Сезон (подробно) | C101: Круглый год (снега почти нет). Апрель–июнь и сентябрь–октябрь — комфортно (15–25 °C); июль–август — >30 °C, только рассвет/вечер, толпы с автобусов; касса работает в сезон (≈май–сентябрь, 9:00–17:00), вне сезона въезд часто свободный; зима — холодно, возможен лёд, короткий день. После дождей не ходить.
A102: bring | B102: Что взять | C102: 1–1,5 л воды на человека, закрытая обувь с протектором, головной убор, солнцезащитный крем, ветровка (на гребнях ветер), наличные сомы на вход, заряженный телефон/камера.
A104: #section | B104: Важно
A105: warn | B105: Важно / предупреждения | C105: Тени и воды внутри нет — в жару не ходить в полдень. Гребни сыпучие, после дождя глина скользкая; в грозу и ливень в сухие русла не заходить (сели). Плату у шлагбаума (≈50 сомов) собирают частные лица — это не госсбор, чека не дают (Kaktus.media 2021). Не ломать хрупкие формы и не вырезать надписи. Названия «Китайская стена», «дракон» — туристические сравнения.
A106: entry | B106: Вход (подробно) | C106: 50 сомов с человека — стабильно по отчётам 2015, 2018, 2020, 2024 (zigzagonearth, travel-tramp, The Planet Edit, eurasia.travel форум) и в отзывах Yandex/TripAdvisor; Kaktus.media (06.2021): 50 сомов с человека на машине / 30 сомов пешком, сбор ведут частные лица у шлагбаума без документов; Too.kg (старые данные) — 40 сомов. Вне сезона (октябрь 2022) плату не брали. Официального тарифа нет — это местный сбор.
A107: net | B107: Связь (подробно) | C107: У трассы и в Тосоре/Тамге связь есть; Beeline в апреле 2026 усилил сеть в Тамге, Барскооне, Боконбаево (economist.kg). Внутри каньона стабильный приём не подтверждён ни одним замером; Yandex-отзывы не упоминают проблем. Скачай офлайн-карту.
A108: p_permits | B108: Разрешения | C108: Не нужны. Местный сбор у шлагбаума ≈50 сомов/чел (собирают частные лица, без чека), вне сезона часто не берут.
A109: p_access | B109: Доступность (дети, пожилые…) | C109: С детьми — да (короткие тропы, но сыпучие склоны, нужен присмотр); пожилым — короткий нижний круг; на коляске — нет (грунт, уклоны); с собакой — можно, но жара и отсутствие воды.
A111: #section | B111: Ночлег и еда
A112: stay | B112: Ночлег (кратко) | C112: В самом каньоне — нет (на 2022 недостроенный глэмпинг). Ближайшие: Yurt Camp Tosor (Тосор, 10 мин), Guesthouse Gulmira и Guesthouse Aziza (Тосор), Yurt Camp Meiman Ordo; на южном берегу — Lake Glamping IK, Ak-Tengir Yurt Resort; в Боконбаево — гостевые дома CBT (ориентир юрточных лагерей южного берега от 1600 руб./чел. в 2024). Цены на 2026 не подтверждены.
...

Sheet kg-altyn-arashan
A1: #title | B1: Алтын-Арашан | C1: kg-altyn-arashan · ← к оглавлению
A2: #section | B2: Основное
A3: id | B3: ID места (kg-…, alt-…) | C3: kg-altyn-arashan
A4: country | B4: Страна (kg / alt) | C4: kg
A5: publish | B5: Публикация | C5: опубликовано
A6: status | B6: Статус проверки | C6: Проверено
A7: name | B7: Название | C7: Алтын-Арашан
A8: full | B8: Полное название | C8: Алтын-Арашан (долина реки Арашан, горячие источники)
A9: cat | B9: Категория | C9: Горная долина / Горячие источники
A10: reg | B10: Регион | C10: Иссык-Кульская область
A11: dist | B11: Район | C11: Ак-Суйский район
A12: lat | B12: Широта | C12: 42.373
A13: lon | B13: Долгота | C13: 78.612
A14: elev | B14: Высота | C14: ≈2435–2600 м: трек-платформы (loc.wiki/AllTrails) дают 2350–2435 м у гостевых домов, Too.kg и Visit Kyrgyzstan — 2600 м у источников; Nomad's Land — 2580 м. Значение «3000 м» у некоторых сайтов завышено.
A15: near | B15: Ближайший пункт | C15: Ак-Суу (бывш. Теплоключенка), ≈10–12 км восточнее Каракола; от Ак-Суу до источников ≈15 км вверх по ущелью
A16: tags | B16: Теги (через ;) | C16: valleys;4x4;medium;top;no-car;hiking;horses;yurts
A17: top | B17: В топе (да/нет) | C17: да
A18: rank | B18: Место в рейтинге | C18: 11
A19: updated_at | B19: Изменено (дата)
A20: updated_by | B20: Кто изменил
A22: #section | B22: Коротко на карточке (плашки)
A23: months | B23: Месяцы сезона (1;2;…12) | C23: 6;7;8;9;10
A24: month_scores | B24: Оценка месяцев (JSON: месяц → 2 лучшее, 1 подходит), напр. {"6":1,"7":2}
A25: s_diff | B25: Сложность (коротко) | C25: Средняя
A26: s_when | B26: Когда (коротко) | C26: Июн – окт
A27: s_acc | B27: Доступ (коротко) | C27: Нужен 4×4
A28: s_onsite | B28: Время на месте (коротко) | C28: 3–5 ч вверх, ≈4 ч…
A29: s_entry | B29: Вход (коротко) | C29: Въезд в ущелье Арашан
A30: s_net | B30: Связь (коротко) | C30: Мобильной связи в…
A31: rating_v | B31: Рейтинг | C31: 4.8
A32: rating_n | B32: Кол-во оценок | C32: 706
A33: rating_src | B33: Источник рейтинга | C33: Google
A35: #section | B35: Обзор — тексты
A36: short | B36: Коротко (1–2 предложения) | C36: Высокогорная долина с радоновыми и сероводородными горячими источниками (35–41 °C), реликтовым еловым лесом и видом на трапецию пика Палатка (4260 м). От Ак-Суу — 15 км пешком (3–5 ч) или 1,5–2,5 ч на УАЗе по одной из самых тяжёлых дорог Прииссыккулья.
A37: desc | B37: Описание | C37: Алтын-Арашан («золотой источник») — долина реки Арашан над селом Ак-Суу, с 1963 года — природный заказник. У слияния рек стоит горстка гостевых домов и юрточных лагерей, у каждого — своя купальня: радоновая вода 35 °C и сероводородная 41 °C круглый год; есть и «дикие» каменные ванны у реки. Над долиной господствует пик Палатка (Аксуйская стена, 4260 м). Дорога от Ак-Суу — 15 км каменистого подъёма с бродами: обычные машины и прокатные авто сюда не пускают, ездят УАЗ-469/«буханки», ГАЗ-66, Nissan Patrol с местными водителями; пешком — 3–5 ч при наборе ≈600 м, тропа простая и очевидная. Отсюда начинается или заканчивается классический трек через перевал Ала-Куль (3900 м) в Каракольское ущелье, а в 5 км выше курорта уходит приток к озеру. Электричество — от генераторов и солнца, оплата только наличными, мобильная связь практически отсутствует. Ночью даже летом бывает −2…−5 °C.
A38: guide | B38: Почему стоит приехать / текст аудиогида | C38: Поднимайся пешком, а вниз возьми «буханку» — так увидишь и ущелье, и получишь порцию экстрима на камнях и бродах, из-за которых прокатные компании запрещают сюда заезжать. Купальни принадлежат разным гостевым домам: у кого-то деревянный сруб с сероводородной водой 41 °C, у кого-то бесплатная каменная ванна прямо у реки — пройдись и выбери. Вечером, когда туристы однодневных туров уезжают, долина остаётся тем немногим, кто ночует: смотри на Палатку в закатном свете и на звёзды без городской засветки. Возьми наличные сомы и тёплый спальник: карт не принимают, а ночью холодно даже в июле. Если планируешь Ала-Куль — не делай его «за день из купальни»: перевал 3900 м требует акклиматизации и отдельного дня.
A39: see | B39: Что посмотреть | C39: Горячие купальни при гостевых домах (радон 35 °C, сероводород 41 °C) и «дикие» ванны у реки; пик Палатка / Аксуйская стена (4260 м); реликтовый тянь-шаньский еловый лес; верховья долины Арашан и приток к Ала-Кулю; юрточные лагеря; зимой — заснеженная долина (доступ только на УАЗе или пешком).
A40: skip | B40: Кому не стоит | C40: Если у тебя один день и больная спина — 2,5 ч тряски на УАЗе в одну сторону тебя не порадуют. Если ждёшь спа-курорт с инфраструктурой — здесь срубы, генераторы и уличные туалеты. Если едешь на прокатной легковушке — въезд в ущелье договором проката обычно запрещён.
A42: #section | B42: Медиа
A43: #table:photos | B43: Фото — 2
A44: #keys | C44: f | D44: t | E44: w | F44: h | G44: cap | H44: by | I44: lic | J44: page
A45: #labels | B45: № / строки ниже | C45: Файл (img/…) | D45: Миниатюра (img/t_…) | E45: Ширина | F45: Высота | G45: Подпись | H45: Автор | I45: Лицензия | J45: Страница-источник
B46: 1 | C46: img/photo-b46c6da7e33ef241.jpg | D46: img/t_photo-b46c6da7e33ef241.jpg | E46: 600 | F46: 400 | G46: Altyn Arashan | H46: Aidar Em | I46: CC BY-SA 4.0 | J46: https://commons.wikimedia.org/wiki/File:Altyn_Arashan.jpg
B47: 2 | C47: img/photo-2ab82baa20d3ec97.jpg | D47: img/t_photo-2ab82baa20d3ec97.jpg | E47: 600 | F47: 400 | G47: Altyn Arashan resort, Kyrgyzstan | H47: Adam Harangozó | I47: CC BY-SA 4.0 | J47: https://commons.wikimedia.org/wiki/File:Altyn_Arashan_resort,_Kyrgyzstan.jpg
A49: #table:videos | B49: Видео — 3
A50: #keys | C50: t | D50: u | E50: ch | F50: y
A51: #labels | B51: № / строки ниже | C51: Заголовок | D51: Ссылка | E51: Канал | F51: Год
B52: 1 | C52: UAZ bukhanka Going to Altyn Arashan for hot springs Kyrgyzstan. Road blocked with avalanche | D52: https://www.youtube.com/watch?v=hK3BZIAxXlU | E52: не подтверждён | F52: н/д
B53: 2 | C53: Hot Springs Of Altyn Arashan by the river. Kyrgyzstan. Thermal baths | D53: https://www.youtube.com/watch?v=gTyYakPmj4g | E53: не подтверждён | F53: н/д
B54: 3 | C54: Hiking to Altyn Arashan's Natural Hot Springs | D54: https://www.youtube.com/watch?v=_0GT7iJSd_M | E54: не подтверждён | F54: н/д
A56: #table:photo_links | B56: Фото-ссылки (внешние) — 6
A57: #keys | C57: cap | D57: url | E57: by
A58: #labels | B58: № / строки ниже | C58: Подпись | D58: Ссылка | E58: Автор
B59: 1 | C59: Altyn Arashan resort, Kyrgyzstan 2 | D59: https://commons.wikimedia.org/wiki/File:Altyn_Arashan_resort,_Kyrgyzstan_2.jpg | E59: Adam Harangozó
B60: 2 | C60: Altyn Arashan resort, Kyrgyzstan 3 | D60: https://commons.wikimedia.org/wiki/File:Altyn_Arashan_resort,_Kyrgyzstan_3.jpg | E60: Adam Harangozó
B61: 3 | C61: Arashan River in Altyn Arashan, Kyrgyzstan | D61: https://commons.wikimedia.org/wiki/File:Arashan_River_in_Altyn_Arashan,_Kyrgyzstan.jpg | E61: Adam Harangozó
B62: 4 | C62: Horses at Altyn Arashan, Kyrgyzstan | D62: https://commons.wikimedia.org/wiki/File:Horses_at_Altyn_Arashan,_Kyrgyzstan.jpg | E62: Adam Harangozó
B63: 5 | C63: Horses at Altyn Arashan | D63: https://commons.wikimedia.org/wiki/File:Horses_at_Altyn_Arashan.jpg | E63: Adam Harangozó
B64: 6 | C64: Yurts and resort in Altyn Arashan, Kyrgyzstan | D64: https://commons.wikimedia.org/wiki/File:Yurts_and_resort_in_Altyn_Arashan,_Kyrgyzstan.jpg | E64: Adam Harangozó
A67: #section | B67: Дорога
A68: how | B68: Как добраться (кратко) | C68: 1) Каракол → Ак-Суу: маршрутка №350 с рынка/центра Каракола (ранее ≈15 сомов, 2017; актуальная цена не подтверждена), далее пешком 15 км вверх по долине (3–5 ч) или на местном УАЗе. 2) Прямой трансфер на 4×4 из Каракола (35 км, ≈2–2,5 ч): Arashan Transfer, MYWAY, CBT Karakol, GetYourGuide. 3) Пешком с перевала Ала-Куль (вторая часть кольцевого трека).
A69: needcar | B69: Нужна ли машина | C69: Нет, если готов идти 15 км в гору; да — только подготовленный 4×4 (УАЗ, ГАЗ-66, Patrol) с местным водителем. Обычная легковая и прокатные авто — нет.
A70: self | B70: Самостоятельно / с гидом | C70: Да: пешком тропа простая, безопасна для одиночных путешественников (Backpack Adventures); ночлег бронировать заранее в сезон. Для перевала Ала-Куль — опыт и акклиматизация, гид по желанию.
A71: roadtype | B71: Тип дороги | C71: Из Каракола до Ак-Суу — асфальт; далее 15 км каменистой грунтовки с крутыми участками, валунами и бродами; по отзывам, машины приходится «поддомкрачивать» на камнях; «прокатные компании запрещают эту дорогу» (TripAdvisor 2024–2025). Зимой возможны лавинные завалы.
A72: traveltime | B72: Время в пути | C72: Каракол → Ак-Суу 20–30 мин; Ак-Суу → источники: пешком 3–5 ч (15 км, набор ≈600 м), на УАЗе 1,5–2,5 ч; прямой трансфер из Каракола ≈2–2,5 ч в одну сторону.
A73: transfer | B73: Трансфер | C73: Из Каракола, 2026: MYWAY — Patrol 9200 сомов, УАЗ 13 200, ГАЗ-66 17 600 за машину (не окончательные); Arashan Transfer — 85 $/место (дневной тур), 55–85 $ шаттл, 290–360 $ частный УАЗ; GetYourGuide — 90 $/чел; по отзывам 2024–2025 — 5000–11 000 сомов за джип; SaryTours 03.2026 — 3000–5000 сомов в одну сторону на местном УАЗе. Маршрутка №350 — копейки (15 сомов в 2017).
A74: p_sum | B74: Дорога: сводка | C74: Лучший вариант — подняться пешком из Ак-Суу (15–16 км, +600–700 м, 3–5 ч), а вниз спуститься на УАЗе, либо сделать Алтын-Арашан финалом кольца Каракольское ущелье → Ала-Куль → Алтын-Арашан. Своей/прокатной легковой сюда нельзя: 16 км русла с валунами и двумя бродами проходят только местные УАЗы и ГАЗ-66 (Arashan Transfer от 55 $/место, частный УАЗ от 290 $; MYWAY от 9200 сомов за Patrol). Ночевать стоит минимум одну ночь в гостевом доме с купальней (≈20–59 $), брать наличные и тёплый спальник.
A75: #table:routes | B75: Подъезды — 2
A76: #keys | C76: rec | D76: title | E76: from | F76: route | G76: km | H76: time | I76: surface | J76: vehicle | K76: season | L76: last | M76: parking_d | N76: parking_price | O76: trail_d | P76: haz | Q76: src | R76: hub | S76: hub_lat | T76: hub_lon | U76: rkm | V76: parking_lat | W76: parking_lon | X76: trail_lat | Y76: trail_lon | Z76: road | AA76: has_rt
A77: #labels | B77: № / строки ниже | C77: Рекомендован (да/нет) | D77: Название варианта | E77: Откуда | F77: Маршрут | G77: Км | H77: Время | I77: Покрытие | J77: Машина | K77: Сезон | L77: Последние АЗС/магазины | M77: Парковка | N77: Парковка: цена | O77: Тропа от парковки | P77: Опасности | Q77: Источник | R77: Город-старт | S77: Старт: широта | T77: Старт: долгота | U77: Км по графу дорог | V77: Парковка: широта | W77: Парковка: долгота | X77: Тропа: широта | Y77: Тропа: долгота | Z77: Геометрия дороги (JSON, генерируется) | AA77: Есть маршрут на карте (да/нет)
B78: 1 | C78: да | D78: Из Каракола через Ак-Суу (Теплоключенку) по долине Арашан | E78: Каракол (≈35 км до источников) | F78: Каракол → с. Ак-Суу (≈12 км, асфальт) → верхняя окраина Ак-Суу, шлагбаум Каракольского лесхоза → 15–16 км вверх по долине реки Арашан → курорт Алтын-Арашан | G78: ≈12 до Ак-Суу + 15–16 по ущелью | H78: Каракол → Ак-Суу 20–30 мин; на УАЗе ≈2–2,5 ч; пешком 3–5 ч вверх, ≈4 ч вниз | I78: До Ак-Суу асфальт; далее каменистое русло с валунами, крутыми подъёмами и двумя бродами, набор ≈700 м; в сильные дожди дорогу закрывают | J78: 4×4 (только подготовленный УАЗ/ГАЗ-66/Patrol с местным водителем); пешком/верхом | K78: Пешком — круглый год; основной сезон июнь–сентябрь, в мае–июне высокие броды; зимой возможны лавинные завалы | L78: АЗС, банкоматы, супермаркеты — Каракол; магазины — Ак-Суу; связь пропадает выше Ак-Суу | M78: Своя машина — в Ак-Суу у начала грунтовки/шлагбаума лесхоза (официальной охраняемой стоянки не найдено; договориться с местными или оставить в гостевом доме Ак-Суу/Каракола) | N78: въезд машины в ущелье по тарифу лесхоза — 80 сомов (легковая), но легковые дальше не проезжают | O78: Пешая тропа идёт вдоль джип-дороги от верхней окраины Ак-Суу; шлагбаум лесхоза с оплатой за въезд | P78: Броды в паводок, камнепады и лавины зимой, резкая смена погоды, высота 2,4–2,6 км | Q78: https://arashantransfer.com/ | R78: Каракол | S78: 42.4907 | T78: 78.3936 | U78: 16 | Z78: [[42.484, 78.4], [42.509, 78.586]] | AA78: да
B79: 2 | C79: нет | D79: Через перевал Ала-Куль из Каракольского ущелья (кольцевой трек) | E79: Каракол → вход в нацпарк «Каракол» (маршрутка №101) | F79: Вход в нацпарк → лагерь Сирота (≈15 км) → озеро Ала-Куль (9,5 км, +1111 м) → перевал Ала-Куль ≈3900 м → спуск в Алтын-Арашан (15 км, +596/−1584 м) → Ак-Суу (15 км) | G79: ≈55 (4 дня) | H79: 3–4 дня | I79: Пешая тропа; на перевале осыпи, снежники до июля | J79: пешком/верхом | K79: Конец июня — сентябрь | L79: Каракол; в лагере Сирота — чайная юрта (чай ≈100 сомов, 2022) | M79: Машину оставить в Караколе | O79: Подвесной мост у входа в нацпарк Каракол (сбор 300 сомов) | P79: Высота 3900 м, горная болезнь, снег на перевале, крутая осыпь | Q79: https://beyondwildplaces.com/guide-to-the-ala-kul-trek-kyrgyzstan/ | R79: Каракол | S79: 42.4907 | T79: 78.3936 | U79: 16 | Z79: [[42.484, 78.4], [42.509, 78.586]] | AA79: да
A81: #table:transport | B81: Транспорт и туры — 10
A82: #keys | C82: mode | D82: provider | E82: from | F82: details | G82: price | H82: year | I82: contact | J82: src
A83: #labels | B83: № / строки ниже | C83: Вид | D83: Перевозчик | E83: Откуда | F83: Подробно | G83: Цена | H83: Год цены | I83: Контакт | J83: Источник
B84: 1 | C84: маршрутка | D84: №350 Каракол → Ак-Суу (Теплоключенка) | E84: Каракол, у рынка | F84: Частые рейсы днём; далее пешком 15 км или УАЗ | G84: ≈40 сомов (Ак-Суу → Каракол, 2025) | H84: 2025 | I84: — | J84: https://beyondwildplaces.com/guide-to-the-ala-kul-trek-kyrgyzstan/
B85: 2 | C85: трансфер | D85: Arashan Transfer — дневной тур | E85: Каракол, Giraffe Coffee, 08:00 | F85: 2,5 ч вверх, 7 ч в долине с ожиданием, возврат к 19:00; выезд гарантирован от 2 человек; оплата картой онлайн | G85: 85 $/место | H85: 2026 | I85: WhatsApp +996 777 889 992, hello@arashantransfer.com, arashantransfer.com | J85: https://arashantransfer.com/
B86: 3 | C86: трансфер | D86: Arashan Transfer — шаттл для трекеров | E86: Каракол | F86: В одну сторону, без ожидания | G86: 55 $ на подтверждённые даты / 85 $ открыть новую дату | H86: 2026 | I86: WhatsApp +996 777 889 992 | J86: https://arashantransfer.com/
B87: 4 | C87: авто с водителем | D87: Arashan Transfer — частный джип | E87: Каракол | F87: УАЗ-469 до 4 чел. или УАЗ-452 до 8 чел., свой график | G87: от 290 $ за машину (до 360 $ за УАЗ-452) | H87: 2026 | I87: WhatsApp +996 777 889 992 | J87: https://arashantransfer.com/
B88: 5 | C88: трансфер | D88: MYWAY | E88: Каракол | F88: Nissan Patrol 4 чел / УАЗ 7 / ГАЗ-66 17 / КамАЗ 28 чел; цены «не окончательные из-за дефицита топлива» | G88: 9200 / 13 200 / 17 600 / 24 200 сомов за машину | H88: 2026 | I88: https://myway.kg/en/transfers/route/karakol-to-altyn-arashan/15 | J88: https://myway.kg/en/transfers/route/karakol-to-altyn-arashan/15
B89: 6 | C89: авто с водителем | D89: Местные УАЗы в Ак-Суу | E89: Ак-Суу | F89: По договорённости | G89: 3000–5000 сомов в одну сторону (SaryTours 03.2026); 5000–11 000 сомов за джип (TripAdvisor 2024–2025) | H89: 2024–2026 | I89: — | J89: этап 1
B90: 7 | C90: тур | D90: GetYourGuide «Altyn Arashan: 4x4 Transfer & Hot Springs» | E90: Каракол | F90: 10 ч, купальня не включена | G90: 90 $/чел | H90: 2026 | I90: getyourguide.com | J90: этап 1
B91: 8 | C91: тур | D91: Ak-Sai Travel «The Taste of Tien-Shan» | E91: Каракол/Бишкек | F91: 9 дней с палаточными лагерями (Джети-Огуз, Телети, Каракол, Ала-Куль, Алтын-Арашан), портеры, спецмашина, сборы и купальни включены; июль–август | G91: 1500 $/чел (+170 $ одноместное) | H91: 2026 | I91: WhatsApp +996 770 901 616, info@ak-sai.com | J91: https://ak-sai.com/en/ak-sai-travel-camps/tent-camps/altyn-arashan
B92: 9 | C92: лошадь | D92: Arashan Transfer / хозяева гостевых домов | E92: Алтын-Арашан | F92: 2 ч по долине; полдня и многодневка до Ала-Куля — по запросу | G92: 25 $/чел за 2 ч | H92: 2026 | I92: WhatsApp +996 777 889 992 | J92: этап 1 (arashantransfer.com)
B93: 10 | C93: пешком | D93: — | E93: Ак-Суу | F93: 15 км, ≈4 ч вниз (+224/−786 м) — тропа очевидная | G93: бесплатно (сбор лесхоза) | H93: 2025 | I93: — | J93: https://beyondwildplaces.com/guide-to-the-ala-kul-trek-kyrgyzstan/
A96: #section | B96: Сезон и что взять
A97: when | B97: Когда ехать (подробно) | C97: Июнь–сентябрь — основной сезон; октябрь — золотые лиственницы и меньше людей (Backpack Adventures). Зимой долина доступна (УАЗ/пешком), купальни работают, но бывают лавины на дороге (видео 2023). В мае–июне возможны броды выше нормы.
A98: diff | B98: Сложность (подробно) | C98: Пешком: средняя — 15 км, набор ≈600 м, 3–5 ч, тропа очевидная, безопасно для одиночек. На машине: тяжёлое бездорожье только для подготовленного 4×4 с местным водителем. Трек на Ала-Куль через перевал 3900 м — сложный, отдельная оценка.
A99: hours | B99: Часы работы | C99: Долина открыта круглосуточно; купальни при гостевых домах — по договорённости с хозяевами, обычно до вечера; официального режима нет. Google Maps: 24 часа.
A100: daytime | B100: Лучшее время суток | C100: Выезд из Каракола утром (трансферы стартуют 8:00–9:00); купание — вечером после отъезда однодневных групп или ранним утром; при ночёвке — звёзды.
A101: p_season | B101: Сезон (подробно) | C101: Июнь–сентябрь — основной сезон (июль–август многолюдно); конец сентября–октябрь — золотые лиственницы, ночью до −5 °C; зима — доступ на УАЗе/пешком, купальни работают, лавины на дороге; май–июнь — высокие броды. Снег в августе возможен.
A102: bring | B102: Что взять | C102: Наличные сомы (карт нет), трекинговая обувь, тёплый слой и шапка (ночью до −5 °C), дождевик, вода/фильтр (речную воду кипятить), купальник и полотенце, перекус, пауэрбанк, налобный фонарь, офлайн-карта, спальник при палатке.
A104: #section | B104: Важно
A105: warn | B105: Важно / предупреждения | C105: Дорога — экстремальная: только 4×4 с местным водителем, прокатные авто по договору сюда нельзя. Высота 2,4–2,6 км и холодные ночи даже летом; погода меняется резко (снег в августе бывает). Воду из реки кипятить. Связи нет — предупреди о маршруте. Зимой — лавины на дороге. Перевал Ала-Куль (3900 м) — отдельный сложный день, не «прогулка от купальни». Радоновые ванны — по 15–20 минут, есть медицинские противопоказания. С 2025 года на въезде в ущелье — шлагбаум лесхоза с платой за въезд (иностранцам 220 сомов/чел + 80 за легковую); требуй квитанцию.
A106: entry | B106: Вход (подробно) | C106: Въезд в ущелье Арашан — платный шлагбаум Каракольского лесхоза (Kaktus.media, 10.06.2025): с человека — граждане КР 20 сомов, граждане стран бывшего СССР 100, иностранцы 220 сомов; с транспорта — легковая 80, большие машины 170, автобусы/грузовики 300 сомов. Купальни: дикие ванны у реки — бесплатно; купальня гостевого дома ≈250 сомов/чел (Arashan Transfer, 2026) или 200–500 сомов (SaryTours 03.2026); отдельная кабина — ≈12 $/чел/ч; для ночующих гостей часто бесплатно. Нацпарк Каракол со стороны Каракольского ущелья — 300 сомов/чел (2025).
A107: net | B107: Связь (подробно) | C107: Мобильной связи в долине практически нет (Too.kg: «связи нет»; TripAdvisor: ограниченные электричество и интернет). По NomadCar у домиков возможен слабый приём O!/MegaCom. Beeline в 2026 усилил сеть в Караколе и Ак-Суйском районе, но не в ущелье. Карты — офлайн, деньги — наличные.
A108: p_permits | B108: Разрешения | C108: Пропуск не нужен. Шлагбаум Каракольского лесхоза у въезда в ущелье (с 2025): иностранцы 220 сомов, граждане СНГ 100, КР 20 сомов/чел; легковая 80, большие машины 170 сомов — требовать квитанцию. При трекинге через Ала-Куль дополнительно сбор нацпарка «Каракол» 300 сомов/чел на подвесном мосту.
A109: p_access | B109: Доступность (дети, пожилые…) | C109: С детьми — на УАЗе можно, но тряска 2–2,5 ч; пешком для подростков. Пожилым — только на машине, учитывать высоту 2,5 км. На коляске — нет. С собакой — можно пешком (скот и пастушьи собаки).
A111: #section | B111: Ночлег и еда
A112: stay | B112: Ночлег (кратко) | C112: Гостевой дом Elsa — 1700 сомов/чел с завтраком (отзыв 2025) или 4000 сомов за двоих с обедом и ужином (окт. 2022, Т—Ж); юрточные лагеря ≈3600 сомов/ночь с завтраком и ужином (TripAdvisor 2025); Eco Yurtcamp Arashan, Arashan Hotel (купальня для постояльцев бесплатно, 2025); Ala-Kul Guesthouse Altyn-Arashan; палатка — ≈100 сомов (2017). Visit Kyrgyzstan: простые гостевые дома 10–15 $/ночь. Кровать в гостевом доме 300 сомов + ужин 250 + завтрак 150 (2017, устарело).
...

Sheet kg-son-kul
A1: #title | B1: Сон-Куль | C1: kg-son-kul · ← к оглавлению
A2: #section | B2: Основное
A3: id | B3: ID места (kg-…, alt-…) | C3: kg-son-kul
A4: country | B4: Страна (kg / alt) | C4: kg
A5: publish | B5: Публикация | C5: опубликовано
A6: status | B6: Статус проверки | C6: Проверено
A7: name | B7: Название | C7: Сон-Куль
A8: full | B8: Полное название | C8: Озеро Сон-Куль (Сонкёль)
A9: cat | B9: Категория | C9: Озеро
A10: reg | B10: Регион | C10: Нарынская область
A11: dist | B11: Район | C11: Единой административной принадлежности в источниках не…
A12: lat | B12: Широта | C12: 41.841
A13: lon | B13: Долгота | C13: 75.155
A14: elev | B14: Высота | C14: 3016 м над уровнем моря (map.kg, asiamountains.net, Ak-Sai, Caravanistan); Too.kg округляет до 3000 м.
A15: near | B15: Ближайший пункт | C15: Постоянных сёл на берегу нет. Базы: Кочкор (через Калмак-Ашуу, ~3 ч), село Кызарт (старт конных маршрутов), Сары-Булак, Нарын (~90 км к юго-востоку по прямой, через Терскей-Торпок), с юго-запада — Ак-Талаа/Баетов (Молдо-Ашуу) и Чаек/Кызыл-Кия (Кара-Кече).
A16: tags | B16: Теги (через ;) | C16: lakes;any-car;medium;top;free;no-car;hiking;horses;yurts
A17: top | B17: В топе (да/нет) | C17: да
A18: rank | B18: Место в рейтинге | C18: 13
A19: updated_at | B19: Изменено (дата)
A20: updated_by | B20: Кто изменил
A22: #section | B22: Коротко на карточке (плашки)
A23: months | B23: Месяцы сезона (1;2;…12) | C23: 5;6;7;8;9;10
A24: month_scores | B24: Оценка месяцев (JSON: месяц → 2 лучшее, 1 подходит), напр. {"6":1,"7":2} | C24: {"5":1,"6":1,"7":2,"8":2,"9":1,"10":1}
A25: s_diff | B25: Сложность (коротко) | C25: Средняя
A26: s_when | B26: Когда (коротко) | C26: Май – окт
A27: s_acc | B27: Доступ (коротко) | C27: На любой машине
A28: s_onsite | B28: Время на месте (коротко) | C28: 2 дня
A29: s_entry | B29: Вход (коротко) | C29: Бесплатно
A30: s_net | B30: Связь (коротко) | C30: Связь только местами
A31: rating_v | B31: Рейтинг | C31: 4.9
A32: rating_n | B32: Кол-во оценок | C32: 382
A33: rating_src | B33: Источник рейтинга | C33: Google
A35: #section | B35: Обзор — тексты
A36: short | B36: Коротко (1–2 предложения) | C36: Второе по величине озеро Кыргызстана на высоте 3016 м среди бескрайнего джайлоо: летом — юрточные лагеря, табуны лошадей и отары, зимой — безлюдная ледяная равнина.
A37: desc | B37: Описание | C37: Сон-Куль — пресное высокогорное озеро во Внутреннем Тянь-Шане между хребтами Сонкуль-Тоо (север) и Молдо-Тоо (юг): около 29 км в длину и 17–18 км в ширину, площадь ~278 км², глубина до 13–14 м (по map.kg — до 22 м). В озеро впадает 18 ручьёв, вытекает одна река Сон-Куль. Ледостав — со второй половины октября–ноября до конца апреля. До 1959 года рыбы в озере не было; сейчас здесь сиг, пелядь, голый осман. Часть акватории входит в заказник Каратал-Жапырык (1994), озеро — Рамсарское водно-болотное угодье (2011): летом здесь гнездятся до 66 видов водоплавающих, включая краснокнижного горного гуся. Пастбища вокруг (~108 тыс. га) — одни из главных летних джайлоо страны; постоянных посёлков нет, с июня по сентябрь работают около 15 юрточных лагерей. На северном берегу — каменный мавзолей Тайлак-баатыра конца XIX века.
A38: guide | B38: Почему стоит приехать / текст аудиогида | C38: Ночуй минимум одну ночь: главное на Сон-Куле — закат над водой, звёздное небо без засветки и утренний туман над джайлоо. Возьми лошадь у хозяев лагеря (около 700 сом в день) и прокатись вдоль берега к табунам, попробуй свежий кумыс и посмотри, как доят кобылиц. Если есть 2–3 дня, приходи верхом из Кызарта через Килемче и перевал Джалгыз-Карагай (3400 м) — так озеро открывается сверху, как его видели кочевники. На северном берегу найди мавзолей Тайлак-баатыра. Даже в июле ночью бывает мороз — спальник и пуховка обязательны.
A39: see | B39: Что посмотреть | C39: Закат и звёздное небо над озером; табуны и юрты чабанов на джайлоо; дойку кобылиц и приготовление кумыса; гнездящихся водоплавающих птиц (горный гусь, журавли, лебеди) — Рамсарское угодье; мавзолей Тайлак-баатыра на северном берегу; серпантины перевалов Калмак-Ашуу, Молдо-Ашуу («33 попугая» — Терскей-Торпок); каскад Кок-Джерты на реке Сон-Куль (4 км ниже истока); зимой — ледяное озеро (зимний юрточный лагерь ставится ежегодно — Caravanistan).
A40: skip | B40: Кому не стоит | C40: У тебя всего один день — дорога туда и обратно из Кочкора займёт 6–7 часов, а смысл места в ночёвке. Ты плохо переносишь высоту 3000 м и ночные заморозки и не готов к удобствам на улице. Ты едешь в октябре–мае без зимней экспедиционной подготовки — лагерей нет, перевалы под снегом.
A42: #section | B42: Медиа
A43: #table:photos | B43: Фото — 2
A44: #keys | C44: f | D44: t | E44: w | F44: h | G44: cap | H44: by | I44: lic | J44: page
A45: #labels | B45: № / строки ниже | C45: Файл (img/…) | D45: Миниатюра (img/t_…) | E45: Ширина | F45: Высота | G45: Подпись | H45: Автор | I45: Лицензия | J45: Страница-источник
B46: 1 | C46: img/photo-517369dc02e51a04.jpg | D46: img/t_photo-517369dc02e51a04.jpg | E46: 600 | F46: 341 | G46: Animals pasture on the steppe of Song-kul. (3968862352) | H46: Peretz Partensky from San Francisco, USA | I46: CC BY-SA 2.0 | J46: https://commons.wikimedia.org/wiki/File:Animals_pasture_on_the_steppe_of_Song-kul._(3968862352).jpg
B47: 2 | C47: img/photo-07696bd10485f0f9.jpg | D47: img/t_photo-07696bd10485f0f9.jpg | E47: 600 | F47: 389 | G47: Cows grazing on the shore of Song-Kul. (3968097979) | H47: Peretz Partensky from San Francisco, USA | I47: CC BY-SA 2.0 | J47: https://commons.wikimedia.org/wiki/File:Cows_grazing_on_the_shore_of_Song-Kul._(3968097979).jpg
A49: #table:videos | B49: Видео — 0
A50: #keys | C50: t | D50: u | E50: ch | F50: y
A51: #labels | B51: № / строки ниже | C51: Заголовок | D51: Ссылка | E51: Канал | F51: Год
A53: #table:photo_links | B53: Фото-ссылки (внешние) — 6
A54: #keys | C54: cap | D54: url | E54: by
A55: #labels | B55: № / строки ниже | C55: Подпись | D55: Ссылка | E55: Автор
B56: 1 | C56: Donkey on Song-Kul steppe. (3968092627) | D56: https://commons.wikimedia.org/wiki/File:Donkey_on_Song-Kul_steppe._(3968092627).jpg | E56: Peretz Partensky from San Francisco, USA
B57: 2 | C57: Horse standing by Song Kul Lake - Kyrgyztan | D57: https://commons.wikimedia.org/wiki/File:Horse_standing_by_Song_Kul_Lake_-_Kyrgyztan.jpg | E57: ElPrismaDeFer - [1]
B58: 3 | C58: Kyrgyzstan yurts at Song Kul (48221119097) | D58: https://commons.wikimedia.org/wiki/File:Kyrgyzstan_yurts_at_Song_Kul_(48221119097).jpg | E58: Kalpak Travel
B59: 4 | C59: Lake Song-Kol- horse, dog and dunny - panoramio | D59: https://commons.wikimedia.org/wiki/File:Lake_Song-Kol-_horse,_dog_and_dunny_-_panoramio.jpg | E59: Raki_Man
B60: 5 | C60: Lk Song-Kol - panoramio | D60: https://commons.wikimedia.org/wiki/File:Lk_Song-Kol_-_panoramio.jpg | E60: Raki_Man
B61: 6 | C61: Riding at Song Kol lake | D61: https://commons.wikimedia.org/wiki/File:Riding_at_Song_Kol_lake.jpg | E61: Kondephy
A64: #section | B64: Дорога
A65: how | B65: Как добраться (кратко) | C65: Автомобильные направления: 1) Кочкор → Сары-Булак → Калмак-Ашуу (~3400 м) → северо-восточный берег — самый популярный, ~3 ч из Кочкора; 2) Нарын → Терскей-Торпок («33 попугая») → юго-восточный берег; 3) Ак-Талаа/Баетов → Молдо-Ашуу → южный берег; 4) Жумгальская долина/Кызыл-Кия → Кара-Кече → юго-запад. Из Бишкека ~280 км (Too.kg) через Балыкчы и Кочкор. Пеше-конные: Кызарт → Килемче → Джалгыз-Карагай (3400 м) → Сон-Куль (2–3 дня, CBT Kochkor), также перевалы Туз-Ашуу, Чиль-Бель, Узбек.
A66: needcar | B66: Нужна ли машина | C66: Да: общественного транспорта к озеру нет. Нужен внедорожник/джип с водителем из Кочкора или Нарына, собственное 4×4, либо лошадь/пеший поход. На седане не ехать (visitkyrgyzstan.org).
A67: self | B67: Самостоятельно / с гидом | C67: Да, на своём 4×4 или наняв водителя в Кочкоре; пропусков не нужно. Юрту летом можно найти на месте, но в июле–августе лучше бронировать через CBT/лагеря за 1–2 недели. Наличные обязательны (нет банкоматов и терминалов).
A68: roadtype | B68: Тип дороги | C68: Асфальт до Кочкора; далее грунт и гравий через перевалы с серпантинами (Калмак-Ашуу, Молдо-Ашуу, Кара-Кече); на берегу — колеи по джайлоо. Нужен высокий клиренс; на отдельных участках можно пробить колесо. Состояние каждого перевала проверять на дату поездки.
A69: traveltime | B69: Время в пути | C69: Бишкек — Кочкор 3–4 ч (маршрутка); Кочкор — Сон-Куль 3–4 ч на джипе (CBT Kochkor: обратный трансфер с Батай-Арала — 3 ч); Бишкек — Сон-Куль на машине ~6–7 ч; конный переход из Кызарта — 2 дня по 4–6 ч.
A70: transfer | B70: Трансфер | C70: Кочкор — Сон-Куль на джипе: 2500–3500 сом за машину (visitkyrgyzstan.org); ~$20 за место туда-обратно (Caravanistan); Бишкек — Кочкор маршрутка 350 сом, Бишкек — Нарын 600 сом (CBT Naryn, май 2026); тур из Бишкека на 2 дня — $650 за 1–2 чел (Tripster).
A71: p_sum | B71: Дорога: сводка | C71: Самый простой путь — Бишкек → Кочкор (маршрутка 350 сом, 3–4 ч), там через CBT Kochkor или частника джип до озера через Сары-Булак и Калмак-Ашуу (≈85 км от трассы, 3–3,5 ч; ориентир ≈5200 сом за машину на 4–6 чел., 2026). Лучший опыт — 2–3-дневный конный переход из села Кызарт через Килемче (от ≈15–20 тыс. сом/чел. у местных гидов, туры 280–440 $/€). Ночуйте в юрточных лагерях северного или южного берега (1000–2000 сом с ужином и завтраком у пастухов, 35–115 $ в Ak-Sai), кэш берите заранее — банкоматов и магазинов на озере нет. С сентября 2026 у Батай-Арала (юго-запад, заповедник Каратал-Жапырык) стоит ограждение — туда на машине не заезжать.
A72: #table:routes | B72: Подъезды — 5
A73: #keys | C73: rec | D73: title | E73: from | F73: route | G73: km | H73: time | I73: surface | J73: vehicle | K73: season | L73: last | M73: parking_d | N73: parking_price | O73: trail_d | P73: haz | Q73: src | R73: hub | S73: hub_lat | T73: hub_lon | U73: rkm | V73: parking_lat | W73: parking_lon | X73: trail_lat | Y73: trail_lon | Z73: road | AA73: has_rt
A74: #labels | B74: № / строки ниже | C74: Рекомендован (да/нет) | D74: Название варианта | E74: Откуда | F74: Маршрут | G74: Км | H74: Время | I74: Покрытие | J74: Машина | K74: Сезон | L74: Последние АЗС/магазины | M74: Парковка | N74: Парковка: цена | O74: Тропа от парковки | P74: Опасности | Q74: Источник | R74: Город-старт | S74: Старт: широта | T74: Старт: долгота | U74: Км по графу дорог | V74: Парковка: широта | W74: Парковка: долгота | X74: Тропа: широта | Y74: Тропа: долгота | Z74: Геометрия дороги (JSON, генерируется) | AA74: Есть маршрут на карте (да/нет)
B75: 1 | C75: да | D75: С северо-востока: Кочкор → Сары-Булак → перевал Калмак-Ашуу (основной) | E75: Кочкор (база); Бишкек ≈280 км, 6–7 ч | F75: Бишкек → Балыкчы → Кочкор → Сары-Булак (трасса на Нарын) → поворот на запад → перевал Калмак-Ашуу (~3400–3450 м) → спуск на северо-восточный берег; дальше колеи по берегу к лагерям | G75: ≈85 км от Сары-Булака по грунту; ≈280 км от Бишкека | H75: Кочкор → озеро 3–3,5 ч на джипе; Бишкек → озеро 6–7 ч | I75: Асфальт до Сары-Булака; дальше гравий/грунт, серпантин на Калмак-Ашуу; на берегу — колеи по джайлоо. В сухую погоду — самая простая дорога (Wikivoyage: проходима обычной машиной); после дождя грязь | J75: кроссовер (в сухую погоду и седан с высоким клиренсом); 4×4 надёжнее | K75: Июнь — сентябрь (безопасно); снег до начала июня; Калмак-Ашуу закрывали по погоде уже 2 ноября (2022) | L75: Последние АЗС, банкоматы, магазины и уверенная связь — в Кочкоре; в Сары-Булаке — придорожные магазины. На озере банкоматов, АЗС и магазинов нет | M75: У выбранного юрточного лагеря — бесплатно для гостей; отдельных платных парковок нет | N75: бесплатно | O75: Не требуется — дорога доходит до лагерей | P75: Грязь и размыв после дождя, пробитые колёса на камнях, туман и снег на перевале в начале/конце сезона, заморозки ночью | Q75: https://en.wikivoyage.org/wiki/Song_Kul | R75: Кочкор | S75: 42.215 | T75: 75.755 | U75: 79 | Z75: [[42.195, 75.773], [42.154, 75.69], [42.179, 75.447], [42.162, 75.385], [42.121, 75.286], [42.068, 75.064], [41.981, 74.907]] | AA75: да
B76: 2 | C76: да | D76: Пешком или верхом из Кызарта через Килемче | E76: Село Кызарт (≈70–77 км от Кочкора по трассе на Чаек) или перевал Кызарт (55 км от Кочкора) | F76: Кызарт → долина/джайлоо Килемче (ночь в юрте) → перевал Джалгыз-Карагай (~3300–3400 м) → Сон-Куль; обратно через Туз-Ашуу (~3200–3400 м) в Кызарт | G76: ≈47 км верхом за 3 дня (18 + 14 + 23 км); пешком от перевала Кызарт ≈27 км за 2 дня | H76: 2–3 дня, по 3,5–6 ч в седле | I76: Конные тропы по пастбищам, без машинной дороги | J76: пешком/верхом | K76: Середина июня — конец сентября (туры с 1 июня до 25 сентября) | L76: Кочкор (банкоматы, магазины); в Кызарте — небольшие магазины; связи на тропе нет | M76: Машину оставляют у гостевого дома/конюха в Кызарте по договорённости | N76: по договорённости | O76: Село Кызарт (Жумгальский р-н), у дома конюха/оператора | P76: Грозы на открытых перевалах, холодные ночи, нужна минимальная практика верховой езды | Q76: https://beyondwildplaces.com/horse-trek-to-song-kul-lake-in-kyrgyzstan/ | R76: Кочкор | S76: 42.215 | T76: 75.755 | U76: 79 | Z76: [[42.195, 75.773], [42.154, 75.69], [42.179, 75.447], [42.162, 75.385], [42.121, 75.286], [42.068, 75.064], [41.981, 74.907]] | AA76: да
B77: 3 | C77: нет | D77: С юго-востока: из Нарына через перевал Терскей-Торпок («33 попугая») | E77: Нарын (≈90 км до озера) | F77: Нарын → на запад по долине → ущелья (≈20 км) → серпантин «33 попугая» на перевал ~3133 м → юго-восточный берег | G77: ≈90 км от Нарына | H77: Не найдено точно; ориентир 3–4 ч | I77: Горный грунт с плотным серпантином; после дождя заметно сложнее; в хорошую погоду проходит и обычная машина (Eurasia Travel) | J77: кроссовер / 4×4 | K77: Июнь — сентябрь; зимой занесён снегом | L77: Нарын — последние АЗС, банкоматы, магазины, CBT Naryn | M77: У лагерей южного/юго-восточного берега | N77: бесплатно | O77: — | P77: Узкий серпантин, грязь после дождя | Q77: https://eurasia.travel/kyrgyzstan/naryn/33-parrots-pass/ | R77: Нарын | S77: 41.4287 | T77: 75.9911 | U77: 176 | Z77: [[41.399, 75.975], [41.412, 76.037], [41.428, 76.053], [41.445, 76.058], [41.469, 76.016], [41.498, 75.996], [41.523, 75.95], [41.564, 75.901], [41.614, 75.884], [41.639, 75.86], [41.68, 75.781], [41.713, 75.748], [41.733, 75.748], [41.779, 75.769], [41.812, 75.773], [41.849, 75.736], [41.861, 75.756], [41.878, 75.769], [41.952, 75.765], [41.989, 75.74], [42.022, 75.699], [42.063, 75.662], [42.129, 75.662], [42.142, 75.666], [42.154, 75.69], [42.179, 75.447], [42.162, 75.385], [42.121, 75.286], [42.068, 75.064], [41.981, 74.907]] | AA77: да
B78: 4 | C78: нет | D78: С юго-запада: из Ак-Талинского района (Баетов/Кара-Ой/Куртка) через Молдо-Ашуу | E78: Нарын (дорога Нарын — Баетов 120 км) / Казарман | F78: Нарын → Ак-Талинский район → Кара-Ой/Куртка → каньон Куртки → 9 шпилек серпантина → перевал Молдо-Ашуу (3346 м) → южный берег | G78: Кара-Ой → Сон-Куль ≈45,6 км | H78: Ориентир 1,5–2 ч от Кара-Оя; переезд Сон-Куль — Казарман через Молдо-Ашуу ≈8 ч | I78: Хорошо поддерживаемая гравийка, без асфальта, сыпучий гравий на шпильках; дорога Нарын — Баетов в 2025 г. частично ремонтировалась и асфальтировалась | J78: кроссовер / 4×4 | K78: Июнь — сентябрь; в первой половине июня бывает закрыт; с ноября по март почти непроходим | L78: Нарын; Баетов — магазины (АЗС и банкомат в Баетове в источниках не подтверждены) | M78: У лагерей южного берега | N78: бесплатно | O78: Из Куртки — старт 2–3-дневных конных маршрутов к Сон-Кулю (Nomad's Land) | P78: Туман и облака на серпантине, скользко в дождь, снег в июне | Q78: https://www.zigzagonearth.com/?p=5940 | R78: Нарын | S78: 41.4287 | T78: 75.9911 | U78: 80 | X78: 41.46 | Y78: 75.02 | Z78: [[41.399, 75.975], [41.424, 75.851], [41.424, 75.785], [41.416, 75.74], [41.362, 75.629], [41.358, 75.604], [41.362, 75.538], [41.354, 75.501], [41.362, 75.286], [41.379, 75.22], [41.383, 75.097], [41.395, 75.047]] | AA78: да
B79: 5 | C79: нет | D79: С северо-запада: из Жумгальской долины (Баш-Куугандый/Чаек) через Кара-Кече | E79: Чаек / Баш-Куугандый (трасса Кочкор — Чаек — Суусамыр) | F79: Баш-Куугандый → ущелье Кара-Кече мимо угольного разреза → перевал Кара-Кече (≈3350–3384 м) → юго-западный берег | G79: ≈75 км грунта от Баш-Куугандыя | H79: ≈4–4,5 ч | I79: Грунт/гравий, поддерживается ради угольного разреза; песок и угольная пыль, тяжёлые грузовики | J79: 4×4 / кроссовер с клиренсом | K79: Конец июня — сентябрь; открывается одним из последних | L79: Чаек — магазины, АЗС; в ущелье частичная связь, кафе и магазинов нет | M79: У лагерей юго-западного берега; не заезжать за ограждение Батай-Арала | N79: бесплатно | O79: — | P79: 03.07.2026 сель разрушил мост на 30–32 км дороги Дыйкан — Кара-Кече — Молдо-Ашуу, проезд был полностью закрыт без срока восстановления — проверить перед поездкой. Угольные КамАЗы, загрязнённая река (воду не пить), песчаные участки | Q79: https://too.kg/en/kara-keche-gorge/ | R79: Кочкор | S79: 42.215 | T79: 75.755 | U79: 79 | Z79: [[42.195, 75.773], [42.154, 75.69], [42.179, 75.447], [42.162, 75.385], [42.121, 75.286], [42.068, 75.064], [41.981, 74.907]] | AA79: да
A81: #table:transport | B81: Транспорт и туры — 12
A82: #keys | C82: mode | D82: provider | E82: from | F82: details | G82: price | H82: year | I82: contact | J82: src
A83: #labels | B83: № / строки ниже | C83: Вид | D83: Перевозчик | E83: Откуда | F83: Подробно | G83: Цена | H83: Год цены | I83: Контакт | J83: Источник
B84: 1 | C84: маршрутка | D84: Бишкекский автовокзал (ул. Алма-Атинская 1/1) | E84: Бишкек → Кочкор | F84: 3–4 ч; в Кочкоре остановка у супермаркета «Глобус» | G84: 350 сом | H84: 2026 | J84: CBT Naryn (уже известно)
B85: 2 | C85: маршрутка | D85: Маршрутка №541 (направление Чаек) | E85: Бишкекский автовокзал → село Кызарт | F85: Уходит рано утром (до 7:00) по заполнении; попросить высадить в Кызарте; ≈270 км, ~4 ч | G85: не указана | H85: 2025 | J85: https://beyondwildplaces.com/horse-trek-to-song-kul-lake-in-kyrgyzstan/
B86: 3 | C86: шеринг-такси | D86: Стоянка такси у автостанции Кочкора | E86: Кочкор → Кызарт | F86: Машины весь день; можно и автостопом | G86: 200 сом/место (ранее) — 350–400 сом/место (2025); частная машина ≈3000 сом | H86: 2025 | J86: https://en.wikivoyage.org/wiki/Song_Kul
B87: 4 | C87: трансфер | D87: CBT Kochkor и частные водители | E87: Кочкор → Сон-Куль (джип 4×4) | F87: Делится на 4–6 пассажиров; CBT собирает группы | G87: ≈5200 сом за машину (2026); исторически 80–100 $ за машину туда-обратно (Wikivoyage); 2500–3500 сом в одну сторону (этап 1) | H87: 2026 | I87: CBT Kochkor: WhatsApp +996 776 467 565, Telegram +996 705 467 565, 1cbtinfokochkor@gmail.com | J87: https://visitkyrgyzstan.org/where-to-stay-song-kul
B88: 5 | C88: лошадь | D88: Лагеря на берегу (напр. SonKol-Land Mirlan) | E88: На озере | F88: Прокат лошади у юрточного лагеря | G88: 250 сом/час; гид 500–700 сом (+ лошадь гида) | H88: 2024 | J88: https://www.madornomad.com/song-kol-lake-kyrgyzstan-guide/
B89: 6 | C89: тур | D89: Местный гид Тимур (@mirbekov.timur) / Tatosh (tatoshguide@gmail.com, через Stalbek Guesthouse) | E89: Кызарт → Килемче → Сон-Куль → Кызарт | F89: 3 дня: лошадь, шлем, гид, 2 ночи в юртах, питание; без трансфера до Кызарта | G89: 20 000 сом/чел. (стандарт), 15 000 сом/чел. при группе из двух | H89: 2025 | I89: Instagram @mirbekov.timur; tatoshguide@gmail.com | J89: https://beyondwildplaces.com/horse-trek-to-song-kul-lake-in-kyrgyzstan/
B90: 7 | C90: тур | D90: Kyrgyzstan-tourism.com (групповой конный тур) | E90: Бишкек (трансфер до Кызарта включён) | F90: 3 дня, 47 км верхом, перевалы Чаар-Арча и Туз-Ашуу (3310 м); выезды каждые 3 дня 15.06–18.08.2026 | G90: 380 $ (2 чел.) / 330 $ (3) / 300 $ (4) / 280 $ (5) с человека | H90: 2026 | I90: kyrgyzstan-tourism.com, WhatsApp через сайт | J90: https://kyrgyzstan-tourism.com/group-tours/3-days-2-mountain-passes-1-unforgettable-lake-horse-trek-to-song-kol-from-280/
B91: 8 | C91: тур | D91: Journal of Nomads + E2 Travel | E91: Кызарт → Килемче → Туз-Ашуу → Сон-Куль → Кызарт | F91: 3 дня/2 ночи; 1 июня — 25 сентября; бронь за 10 дней, депозит 60 € | G91: 440 € (2 чел.) … 250 € (8–10 чел.) с человека | H91: 2026–2027 | I91: journalofnomads.com | J91: https://www.journalofnomads.com/song-kul-lake-horse-riding-tours/
B92: 9 | C92: тур | D92: Terra Montis Adventures (WeTravel) | E92: Кызарт → Килемче → Сон-Куль → перевал Каракыя → Кызарт | F92: 3 дня, 1–8 чел.; юрты, питание, англоязычный гид, лошади | G92: 300 $ (депозит 200 $) | H92: н/д | I92: wetravel.com | J92: https://www.wetravel.com/trips/3-day-horseback-riding-tour-from-kyzart-to-son-kul-lake-terra-montis-adventures-4183564291
B93: 10 | C93: тур | D93: Tripster «Сон-Куль с юрточным лагерем» | E93: Бишкек, через Ортотокой и Калмак-Ашуу | F93: 2 дня, до 15 чел., ночь в юрточном лагере на южном берегу (на 10.2026 «временно недоступно») | G93: 120 €/чел. | H93: 2026 | I93: experience.tripster.ru/experience/86383/ | J93: https://experience.tripster.ru/experience/86383/
B94: 11 | C94: тур | D94: Tripster «На окраину мира» (индивидуально) | E94: Бишкек | F94: 2 дня через Калмак-Ашуу | G94: 650 $ за 1–2 чел. | H94: 2026 | I94: experience.tripster.ru/experience/55144/ | J94: https://experience.tripster.ru/experience/55144/
B95: 12 | C95: аренда авто | D95: Прокаты Бишкека | E95: Бишкек | F95: Для Калмак-Ашуу в сухую погоду хватит кроссовера; для Кара-Кече/Молдо-Ашуу лучше 4×4 | G95: не найдено в этой сессии
A98: #section | B98: Сезон и что взять
A99: when | B99: Когда ехать (подробно) | C99: Июнь — сентябрь (юрточные лагеря работают примерно с конца мая — начала июня до середины сентября/начала октября); пик и гарантированно открытые лагеря — июль–август; для тишины — июнь и сентябрь. CBT Kochkor проводит конные туры с середины июня до конца сентября. Озеро замерзает со второй половины октября до конца апреля; перевалы зимой закрываются снегом.
A100: diff | B100: Сложность (подробно) | C100: Средняя по логистике: прогулки у озера лёгкие, но подъезд — 3–4 ч по высокогорным грунтовкам и перевалам до 3400+ м. Конные/пешие переходы из Кызарта — средние (2 перевала выше 3000–3400 м, 4–6 ч в день; CBT Kochkor). Высота 3016 м — нужна акклиматизация.
A101: hours | B101: Часы работы | C101: Открытая природная территория без кассы. Юрточные лагеря — сезонно (Ak-Sai: июнь — сентябрь); в межсезонье на берегу никого нет, кроме зимнего лагеря (по запросу).
A102: daytime | B102: Лучшее время суток | C102: Закат и ночь (звёзды) — главное; ранним утром — туман над водой и дойка кобылиц. Перевалы лучше проходить днём: утром возможны заморозки и лёд, вечером — грозы.
A103: p_season | B103: Сезон (подробно) | C103: Май — до середины июня: снег на перевалах, лагеря открываются с конца мая (некоторые с 15 мая). Середина июня — август: все подъезды открыты, лагеря работают, пик — июль–август, днём до +20…+25, ночью около 0; грозы. Август — фестивали национальных игр на джайлоо. Сентябрь: тише, холоднее, лагеря закрываются к середине сентября — 20 октября. Октябрь — апрель: озеро подо льдом (~200 дней), перевалы закрываются снегом (Калмак-Ашуу и Молдо-Ашуу закрывали уже 2 ноября).
A104: bring | B104: Что взять | C104: Тёплый спальник или флис/пуховку (ночью мороз даже летом), шапку и перчатки, дождевик, солнцезащиту (УФ на 3000 м), налобный фонарь, power bank (электричество есть не везде), наличные сомы, таблетки от горной болезни/аптечку, обувь для мокрой травы, офлайн-карты. Воду из озера пить только кипячёной.
A106: #section | B106: Важно
A107: warn | B107: Важно / предупреждения | C107: Высота 3016 м — горная болезнь возможна, особенно при подъёме из Бишкека за один день. Погода меняется быстро; ночью заморозки даже в июле–августе; грозы на открытом джайлоо — не стой на возвышенностях. Дороги через перевалы — грунт, риск пробить колесо, снег в начале/конце сезона. Связи почти нет, банкоматов и магазинов нет. Были жалобы на завышение цен таксистами из Кызарта (TripAdvisor, май 2025) — договаривайся о цене заранее. Собаки у чабанских стоянок.
A108: entry | B108: Вход (подробно) | C108: Бесплатно: входного билета или экосбора на Сон-Куль ни в одном источнике 2019–2026 гг. не найдено. Платишь только за лагерь, лошадей и транспорт.
A109: net | B109: Связь (подробно) | C109: Связь только местами (Too.kg). У лагеря Ak-Sai заявлено покрытие MegaCom и Wi-Fi через Starlink; у большинства пастушеских лагерей связи нет (Caravanistan, visitkyrgyzstan.org). Beeline и O! на озере не подтверждены. Сигнал иногда ловится на перевалах.
A110: p_permits | B110: Разрешения | C110: Пропуск не нужен; входных билетов и экосборов нет. Юго-западная часть (Батай-Арал) — заповедник Каратал-Жапырык: с 09.2026 огорожена, проезд машин закрыт.
A111: p_access | B111: Доступность (дети, пожилые…) | C111: С детьми — да, при акклиматизации (3016 м) и тёплой одежде; лучше ночь в Кочкоре по пути. Пожилым — на джипе через Калмак-Ашуу, комфортные лагеря (Ak-Sai). На коляске — практически нет (трава, кочки, выгребные туалеты). С собакой можно, но у чабанских стоянок агрессивные собаки.
...

Sheet kg-0002
A1: #title | B1: Ущелье Кара-Булак | C1: kg-0002 · ← к оглавлению
A2: #section | B2: Основное
A3: id | B3: ID места (kg-…, alt-…) | C3: kg-0002
A4: country | B4: Страна (kg / alt) | C4: kg
A5: publish | B5: Публикация | C5: опубликовано
A6: status | B6: Статус проверки | C6: Проверено
A7: name | B7: Название | C7: Ущелье Кара-Булак
A8: full | B8: Полное название | C8: Ущелье Кара-Булак
A9: cat | B9: Категория | C9: Ущелье
A10: reg | B10: Регион | C10: Чуйская область
A11: dist | B11: Район | C11: Аламудунский район Чуйской области
A12: lat | B12: Широта | C12: 42.679407
A13: lon | B13: Долгота | C13: 74.622574
A14: elev | B14: Высота | C14: Около 1800 м у экорезорта Kara Bulak (sxodim, karabulak.kg); склоны ущелья выше. Соседняя гора Тыша — 2300 м (hiking.kg).
A15: near | B15: Ближайший пункт | C15: Сёла Арашан и Кой-Таш (подъезд через урочище Татыр); Бишкек — 25–27 км (sxodim, triptokyrgyzstan).
A16: tags | B16: Теги (через ;) | C16: gorges;any-car;easy;year-round;hiking;horses
A17: top | B17: В топе (да/нет) | C17: нет
A18: rank | B18: Место в рейтинге | C18: 78
A19: updated_at | B19: Изменено (дата)
A20: updated_by | B20: Кто изменил
A22: #section | B22: Коротко на карточке (плашки)
A23: months | B23: Месяцы сезона (1;2;…12) | C23: 1;2;3;4;5;6;7;8;9;10;11;12
A24: month_scores | B24: Оценка месяцев (JSON: месяц → 2 лучшее, 1 подходит), напр. {"6":1,"7":2}
A25: s_diff | B25: Сложность (коротко) | C25: Лёгкая
A26: s_when | B26: Когда (коротко) | C26: Круглый год
A27: s_acc | B27: Доступ (коротко) | C27: На любой машине
A28: s_onsite | B28: Время на месте (коротко) | C28: 2 ч 25 мин
A29: s_entry | B29: Вход (коротко) | C29: Отдельного входного…
A30: s_net | B30: Связь (коротко) | C30: На территории…
A31: rating_v | B31: Рейтинг
A32: rating_n | B32: Кол-во оценок
A33: rating_src | B33: Источник рейтинга
A35: #section | B35: Обзор — тексты
A36: short | B36: Коротко (1–2 предложения) | C36: Небольшое ущелье в Кыргызском Ала-Тоо в 25–27 км от Бишкека, над урочищем Татыр: цветные скалы, родники, водопад и панорамы Чуйской долины; в ущелье — экорезорт Kara Bulak.
A37: desc | B37: Описание | C37: Кара-Булак («чёрный родник») — ущелье в предгорьях Кыргызского Ала-Тоо между Аламединским ущельем и Чункурчаком. Triptokyrgyzstan описывает цветные скалы, зелёные холмы, водопад, множество родников и ручьёв и панорамы Бишкека, Чуйской долины и снежных вершин. Подъезд — по дороге через Татыр в сторону Чункурчака (в 2026 г. её асфальтируют) и далее крутым серпантином через перевальчик. Основную часть ущелья занимает частный экорезорт Kara Bulak (2ГИС 4.8/5, 903 оценки): коттеджи, кафе национальной кухни, баня, конные прогулки. Окрестности подходят для пеших и конных прогулок; рядом — гора Тыша, «Небесный мост» и Голубиный водопад по дороге к Алтын-Тёру.
A38: guide | B38: Почему стоит приехать / текст аудиогида | C38: Кара-Булак — ближайший к Бишкеку «горный выходной»: всего час на машине, а вид на Чуйскую долину сверху как с самолёта. Самая живописная часть — серпантин после Татыра: остановись на перевальчике до спуска в ущелье. Ущелье во многом занято частным экорезортом, поэтому для прогулки по его территории и конной поездки (700 сом/час по данным 2022 г.) договорись с ресепшеном. Если хочется просто погулять — поднимись на соседнюю гору Тыша (6 км, ~2,5 часа, +540 м).
A39: see | B39: Что посмотреть | C39: Цветные скалы и родники ущелья, водопад (triptokyrgyzstan); панорамы Бишкека и Чуйской долины с серпантина; по пути — «Небесный мост» и Голубиный водопад (hiking.kg); гора Тыша (2300 м) с видом на город и хребет.
A40: skip | B40: Кому не стоит | C40: Ты ищешь дикое ущелье без инфраструктуры — здесь доминирует частный курорт. Нет машины: общественного транспорта до ущелья нет. Хочешь высокогорье и ледники — лучше Ала-Арча или Аламедин.
A42: #section | B42: Медиа
A43: #table:photos | B43: Фото — 0
A44: #keys | C44: f | D44: t | E44: w | F44: h | G44: cap | H44: by | I44: lic | J44: page
A45: #labels | B45: № / строки ниже | C45: Файл (img/…) | D45: Миниатюра (img/t_…) | E45: Ширина | F45: Высота | G45: Подпись | H45: Автор | I45: Лицензия | J45: Страница-источник
A47: #table:videos | B47: Видео — 1
A48: #keys | C48: t | D48: u | E48: ch | F48: y
A49: #labels | B49: № / строки ниже | C49: Заголовок | D49: Ссылка | E49: Канал | F49: Год
B50: 1 | C50: Путешествие в Кара Булак /урочище Чункурчак | D50: https://www.youtube.com/watch?v=earRq-hoC-4 | E50: не проверено | F50: не проверено; права уточнить
A52: #table:photo_links | B52: Фото-ссылки (внешние) — 0
A53: #keys | C53: cap | D53: url | E53: by
A54: #labels | B54: № / строки ниже | C54: Подпись | D54: Ссылка | E54: Автор
A57: #section | B57: Дорога
A58: how | B58: Как добраться (кратко) | C58: Бишкек → Кой-Таш → Арашан → урочище Татыр по дороге на Чункурчак (асфальт, работы 2026), затем поворот на Кара-Булак и крутой серпантин через перевальчик (triptokyrgyzstan; hiking.kg). Около 1 ч на машине (sxodim). Пешком — 5–6 ч из Кара-Кыя (karabulak.kg).
A59: needcar | B59: Нужна ли машина | C59: Да: своя машина, такси или трансфер резорта; общественного транспорта до ущелья нет (sxodim: «личный автомобиль, около 1 часа»).
A60: self | B60: Самостоятельно / с гидом | C60: Да, на машине — пропусков не нужно. Прогулки по территории частного экорезорта согласовывать с ним; пеший маршрут из Кара-Кыя сверить с karabulak.kg.
A61: roadtype | B61: Тип дороги | C61: Асфальт до Татыра (дорогу Арашан — Чункурчак длиной 21,7 км асфальтируют в 2026 г.: первый слой уложен на 20,7 км к концу июля, economist.kg 11.08.2026); поворот на Кара-Булак — крутой грунтовый серпантин, неподходящий для низкой городской машины (hiking.kg).
A62: traveltime | B62: Время в пути | C62: Около 1 ч из Бишкека на машине (sxodim; hiking.kg — 1 ч 5 мин до старта на Тышу, 32 км). Пеший подход из Кара-Кыя — 5–6 ч в одну сторону (karabulak.kg).
A63: transfer | B63: Трансфер | C63: Не подтверждено: цены трансфера резорта не опубликованы. Ориентир — такси по городскому тарифу Yandex Go/inDrive на ~30 км (цена не проверена).
A64: p_sum | B64: Дорога: сводка | C64: Кара-Булак — ближайший к Бишкеку «горный выходной»: около часа на машине через Кой-Таш, Арашан и урочище Татыр (дорогу на Чункурчак асфальтируют в 2026 г.), последний подъём — крутой грунтовый серпантин, низкой машине лучше не соваться. Общественного транспорта нет: своя машина, такси или тур с джипом (Tripster «Над облаками у Бишкека» — €173 за машину, 7 ч). Ущелье в основном занято экорезортом Kara Bulak: конные прогулки 700 сом/ч, коттедж от 7400–8700 сом за двоих; для свободной прогулки поднимитесь на соседнюю гору Тыша (6 км, +540 м).
A65: #table:routes | B65: Подъезды — 2
A66: #keys | C66: rec | D66: title | E66: from | F66: route | G66: km | H66: time | I66: surface | J66: vehicle | K66: season | L66: last | M66: parking_d | N66: parking_price | O66: trail_d | P66: haz | Q66: src | R66: hub | S66: hub_lat | T66: hub_lon | U66: rkm | V66: parking_lat | W66: parking_lon | X66: trail_lat | Y66: trail_lon | Z66: road | AA66: has_rt
A67: #labels | B67: № / строки ниже | C67: Рекомендован (да/нет) | D67: Название варианта | E67: Откуда | F67: Маршрут | G67: Км | H67: Время | I67: Покрытие | J67: Машина | K67: Сезон | L67: Последние АЗС/магазины | M67: Парковка | N67: Парковка: цена | O67: Тропа от парковки | P67: Опасности | Q67: Источник | R67: Город-старт | S67: Старт: широта | T67: Старт: долгота | U67: Км по графу дорог | V67: Парковка: широта | W67: Парковка: долгота | X67: Тропа: широта | Y67: Тропа: долгота | Z67: Геометрия дороги (JSON, генерируется) | AA67: Есть маршрут на карте (да/нет)
B68: 1 | C68: да | D68: Из Бишкека через Кой-Таш — Арашан — Татыр (дорога на Чункурчак) | E68: Бишкек (25–32 км, ≈1 ч) | F68: Бишкек → юг (Кой-Таш) → с. Арашан → урочище Татыр по дороге Арашан — Чункурчак → поворот на Кара-Булак → серпантин через перевальчик → экорезорт | G68: 25–32 | H68: ≈1 ч | I68: Асфальт до Татыра (дорога Арашан — Чункурчак 21,7 км: первый слой асфальта уложен на 20,7 км к концу июля 2026); поворот на Кара-Булак — крутой грунтовый серпантин | J68: кроссовер (седан — только в сухую погоду и с осторожностью; hiking.kg не рекомендует низкие машины) | K68: Круглый год (резорт работает всегда), зимой серпантин может быть в снегу/льду | L68: АЗС, банкоматы, супермаркеты — Бишкек и Кой-Таш; в ущелье — только кафе резорта; Wi-Fi у резорта | M68: Бесплатная парковка экорезорта (для гостей); для подъёма на Тышу — парковка у старта по hiking.kg | N68: бесплатно для гостей | O68: Подъём на гору Тыша (2300 м) от парковки — 6 км, 2 ч 25 мин, +540 м (hiking.kg) | P68: Скользкий серпантин в дождь/снег; дорожные работы на дороге Арашан — Чункурчак (2026) | Q68: этап 1 (economist.kg 11.08.2026; hiking.kg); https://kaktus.media/doc/543024_v_mintranse_rasskazali_kogda_nachnyt_asfaltirovat_dorogy_na_chynkyrchak.html | R68: Бишкек | S68: 42.8746 | T68: 74.5698 | U68: 13 | V68: 42.675483 | W68: 74.621712 | Z68: [[42.876, 74.536], [42.897, 74.598], [42.876, 74.688]] | AA68: да
B69: 2 | C69: нет | D69: Пешком из Кара-Кыя | E69: Кара-Кыя (окраина Бишкека) | F69: Кара-Кыя → через предгорья → Кара-Булак | G69: не найдено | H69: 5–6 ч в одну сторону | I69: Тропа | J69: пешком/верхом | K69: Май — октябрь | L69: Бишкек | M69: — | O69: Маршрут — уточнять у karabulak.kg | P69: Жара без тени летом, ориентирование | Q69: этап 1 (karabulak.kg) | R69: Бишкек | S69: 42.8746 | T69: 74.5698 | U69: 13 | Z69: [[42.876, 74.536], [42.897, 74.598], [42.876, 74.688]] | AA69: да
A71: #table:transport | B71: Транспорт и туры — 7
A72: #keys | C72: mode | D72: provider | E72: from | F72: details | G72: price | H72: year | I72: contact | J72: src
A73: #labels | B73: № / строки ниже | C73: Вид | D73: Перевозчик | E73: Откуда | F73: Подробно | G73: Цена | H73: Год цены | I73: Контакт | J73: Источник
B74: 1 | C74: такси | D74: Yandex Go / inDrive из Бишкека | E74: Бишкек | F74: ≈30 км, ≈1 ч; обратную машину в ущелье поймать трудно — заказывайте с ожиданием или договаривайтесь заранее | G74: не найдено | J74: этап 1
B75: 2 | C75: аренда авто | D75: прокаты Бишкека | E75: Бишкек | F75: Кроссовер для серпантина | G75: седан $20–40, 4×4 $65–100 в день | H75: 2026 | J75: https://indyguide.com/article/suv-rental
B76: 3 | C76: тур | D76: Tripster — гид Станислав «Над облаками у Бишкека» | E76: Бишкек | F76: 7 ч на внедорожнике: серпантин, «парящий» мост, водопад в 200 м от моста, этнокомплекс Кара-Булак (Татыр) | G76: €173 за экскурсию | H76: 2026 | I76: experience.tripster.ru | J76: https://www.putevka.com/trip/kirgiziya/bishkek/70445
B77: 4 | C77: тур | D77: Sputnik8 — гид Камчыбек «Небесный мост в ущелье Чункурчак» | E77: Бишкек | F77: 4 ч, мост и водопад (та же дорога через Татыр); входные билеты оплачиваются отдельно | G77: $100 (1–3 чел.) / $140 (4–6 чел.) | H77: 2026 | I77: sputnik8.com | J77: https://www.sputnik8.com/ru/bishkek/activities/53556-nebesnyy-most-v-uschelie-chunkurchak
B78: 5 | C78: тур | D78: Triptokyrgyzstan «1 Day Tour to the mountains near Bishkek» | E78: Бишкек | F78: Однодневный тур | G78: по запросу | I78: triptokyrgyzstan.com | J78: этап 1
B79: 6 | C79: трансфер | D79: экорезорт Kara Bulak | E79: Бишкек | F79: По запросу при бронировании | G79: не опубликовано | I79: +996 556 98 00 09, +996 558 39 98 84, +996 312 96 19 03 | J79: https://ph.trip.com/hotels/ysyk-ata-hotel-detail-11269253/eco-resort-kara-bulak
B80: 7 | C80: лошадь | D80: экорезорт Kara Bulak | E80: Кара-Булак | F80: Конные прогулки по ущелью | G80: 700 сом/ч + проводник 1000 сом | H80: 2022 | I80: +996 558 39 98 84 | J80: https://sxodim.com/bishkek/place/zona-otdyha-kara-bulak
A83: #section | B83: Сезон и что взять
A84: when | B84: Когда ехать (подробно) | C84: Май — октябрь: зелёные склоны весной и в начале лета, золотые — осенью; резорт работает круглый год (2ГИС), но зимой серпантин может быть заснежен (editorial).
A85: diff | B85: Сложность (подробно) | C85: Лёгкая: прогулки по ущелью и у резорта; восхождение на Тышу — 2/5 по hiking.kg (6 км от парковки, 2 ч 25 мин, +540 м). Пеший подход из Кара-Кыя к резорту — 5–6 ч (karabulak.kg).
A86: hours | B86: Часы работы | C86: Ущелье — природная территория без режима. Экорезорт Kara Bulak: ежедневно 08:00–24:00 по 2ГИС (на 10.2026), круглосуточно по sxodim (2022). Вход на территорию резорта — по согласованию.
A87: daytime | B87: Лучшее время суток | C87: Утро — чистый воздух и лучшая видимость Чуйской долины до дневной дымки; закат — с серпантина над Татыром (editorial).
A88: p_season | B88: Сезон (подробно) | C88: Апрель — май: зелёные склоны, после дождей серпантин грязный. Июнь — август: жарко внизу, на 1800 м комфортно; выходные — много гостей резорта. Сентябрь — октябрь: золотые склоны, лучшая видимость. Ноябрь — март: резорт работает, серпантин может быть в снегу — нужна зимняя резина/4×4.
A89: bring | B89: Что взять | C89: Удобную обувь для прогулок, ветровку (1800 м и выше), воду и перекус для похода на Тышу, солнцезащиту.
A91: #section | B91: Важно
A92: warn | B92: Важно / предупреждения | C92: Серпантин после Татыра крутой и грунтовый — в дождь и снег скользкий, низким машинам не рекомендуется. Значительная часть ущелья — частная территория экорезорта. В 2026 г. на дороге Арашан — Чункурчак идут дорожные работы.
A93: entry | B93: Вход (подробно) | C93: Отдельного входного билета в ущелье не найдено. На территории резорта платные услуги: конная прогулка 700 сом/ч, стрельба из лука 150 сом/3 выстрела, баня «Ыштык Мончо» 22 000–25 000 сом (sxodim, 2022). Плата за посещение территории без проживания не подтверждена.
A94: net | B94: Связь (подробно) | C94: На территории экорезорта есть Wi-Fi для гостей (2ГИС). Покрытие операторов в самом ущелье не подтверждено.
A95: p_permits | B95: Разрешения | C95: Не нужны. Входного билета в ущелье нет; территория резорта — частная, услуги платные.
A96: p_access | B96: Доступность (дети, пожилые…) | C96: С детьми — да (резорт с детской площадкой). Пожилым — на машине до резорта комфортно, тропы крутые. Коляска — только по территории резорта (не подтверждено). Собаки — в резорт нельзя (Trip.com: pets not allowed).
A98: #section | B98: Ночлег и еда
A99: stay | B99: Ночлег (кратко) | C99: Kara Bulak Eco Resort (karabulak.kg): коттедж на 2 взрослых с завтраком — 7400 сом (sxodim, 2022), от 8700 сом (2ГИС, 2026); вместимость до 40 гостей, баня, SPA, Wi-Fi, кафе. Бронирование также через Ostrovok и Google Hotels.
A100: food | B100: Еда (кратко) | C100: Кафе экорезорта Kara Bulak с национальной кухней (triptokyrgyzstan), кумыс (karabulak.kg), фиточаи в бане (sxodim: 1200–1800 сом). Меню уточнять при бронировании.
A101: #table:stays | B101: Ночлег — 4
A102: #keys | C102: name | D102: type | E102: where | F102: season | G102: price | H102: year | I102: contact | J102: src
A103: #labels | B103: № / строки ниже | C103: Название | D103: Тип | E103: Где | F103: Сезон | G103: Цена | H103: Год цены | I103: Контакт | J103: Источник
B104: 1 | C104: Kara Bulak Eco Resort | D104: экорезорт (коттеджи, 15 номеров, баня, бассейн, ресторан) | E104: в ущелье, 1800 м | F104: круглый год | G104: коттедж на 2 взрослых с завтраком 7400 сом (2022); от 8700 сом (2ГИС, 2026) | H104: 2022–2026 | I104: +996 556 98 00 09 (Trip.com), +996 558 39 98 84, Instagram @karabulak.kg; Ostrovok, Trip.com | J104: https://ph.trip.com/hotels/ysyk-ata-hotel-detail-11269253/eco-resort-kara-bulak
B105: 2 | C105: Jannat Resort | D105: курорт (спа, крытый бассейн) | E105: с. Кой-Таш (по пути) | F105: круглый год | G105: ≈$171 за ночь | H105: 2026 | I105: Expedia/Travelocity | J105: https://www.travelocity.com/Ala-Archa-National-Park-Chuy-Province.d6101694.Vacation-Attraction
B106: 3 | C106: Mountain View Hot Spring Resort | D106: курорт с горячими источниками | E106: с. Кой-Таш | F106: круглый год | G106: не указано | H106: 2026 | I106: Expedia/Travelocity | J106: https://www.travelocity.com/Ala-Archa-National-Park-Chuy-Province.d6101694.Vacation-Attraction
B107: 4 | C107: Гостиницы Бишкека | D107: город | E107: 25–32 км | F107: круглый год | G107: широкий выбор | J107: editorial
A109: #table:food | B109: Еда — 2
A110: #keys | C110: name | D110: where | E110: details | F110: src
A111: #labels | B111: № / строки ниже | C111: Название | D111: Где | E111: Подробно | F111: Источник
B112: 1 | C112: Кафе экорезорта Kara Bulak | D112: в ущелье | E112: Национальная кухня, кумыс; меню уточнять при бронировании | F112: этап 1 (triptokyrgyzstan, karabulak.kg)
B113: 2 | C113: Кафе Кой-Таша и Бишкека | D113: по пути | E113: Закупитесь в Бишкеке, если идёте на Тышу — на тропе еды нет | F113: editorial
...

Sheet kg-0003
A1: #title | B1: Национальный парк Ала-Арча | C1: kg-0003 · ← к оглавлению
A2: #section | B2: Основное
A3: id | B3: ID места (kg-…, alt-…) | C3: kg-0003
A4: country | B4: Страна (kg / alt) | C4: kg
A5: publish | B5: Публикация | C5: опубликовано
A6: status | B6: Статус проверки | C6: Проверено
A7: name | B7: Название | C7: Национальный парк Ала-Арча
A8: full | B8: Полное название | C8: Национальный парк Ала-Арча
A9: cat | B9: Категория | C9: Национальный парк
A10: reg | B10: Регион | C10: Чуйская область
A11: dist | B11: Район | C11: Аламудунский район
A12: lat | B12: Широта | C12: 42.64484
A13: lon | B13: Долгота | C13: 74.48032
A14: elev | B14: Высота | C14: От ~1500 м в нижней части ущелья до 4895 м (пик Семёнова-Тян-Шанского) — asiamixtravel 2026. Ориентиры маршрутов: водопад Ак-Сай ~2860 м, хижина Рацека ~3380 м (adventuresoflilnicki, 16.09.2026); стартовая зона у альплагеря — около 2150 м (расчёт: водопад 2860 м минус набор 700 м по hiking.kg).
A15: near | B15: Ближайший пункт | C15: Кашка-Суу (адрес парка в 2ГИС)
A16: tags | B16: Теги (через ;) | C16: parks;any-car;hard;top;no-car;hiking;horses;yurts
A17: top | B17: В топе (да/нет) | C17: да
A18: rank | B18: Место в рейтинге | C18: 1
A19: updated_at | B19: Изменено (дата)
A20: updated_by | B20: Кто изменил
A22: #section | B22: Коротко на карточке (плашки)
A23: months | B23: Месяцы сезона (1;2;…12) | C23: 5;6;7;8;9;10
A24: month_scores | B24: Оценка месяцев (JSON: месяц → 2 лучшее, 1 подходит), напр. {"6":1,"7":2} | C24: {"5":1,"6":1,"7":2,"8":2,"9":2,"10":1}
A25: s_diff | B25: Сложность (коротко) | C25: Сложная
A26: s_when | B26: Когда (коротко) | C26: Май – окт
A27: s_acc | B27: Доступ (коротко) | C27: На любой машине
A28: s_onsite | B28: Время на месте (коротко) | C28: 40 мин в одну…
A29: s_entry | B29: Вход (коротко) | C29: С 11
A30: s_net | B30: Связь (коротко) | C30: У КПП и альплагеря…
A31: rating_v | B31: Рейтинг | C31: 4.7
A32: rating_n | B32: Кол-во оценок | C32: 3871
A33: rating_src | B33: Источник рейтинга | C33: Google
A35: #section | B35: Обзор — тексты
A36: short | B36: Коротко (1–2 предложения) | C36: Ала-Арча — государственный природный парк в ущелье Кыргызского Ала-Тоо в ~40 км к югу от Бишкека: еловые и арчовые леса, ледники и вершины до 4895 м, самые популярные однодневные треки страны.
A37: desc | B37: Описание | C37: Ала-Арча — горный природный парк в Аламудунском районе Чуйской области, в одноимённом ущелье реки Ала-Арча на северном склоне Кыргызского Ала-Тоо. Высоты — от ~1500 м до 4895 м; в верховьях ледники Ак-Сай, Адыгене и др., на склонах — ели Шренка и арча, давшая имя ущелью. С 1 мая 2025 г. по поручению президента в парк запрещён въезд машин с ДВС: гостей оставляют на парковке у КПП (≈700 мест), а дальше бесплатно возят ~80 электробусов (около 12 км до альплагеря и начала троп). На территории — ресторан, кафе, коттеджи, юрточный городок, газовые мангалы (костры и шашлык на дровах запрещены). Классические маршруты — водопад Ак-Сай (4,3 км, +700 м), хижина Рацека (~3380 м) у ледника Ак-Сай, ущелье Адыгене; зимой рядом работает горнолыжная база.
A38: guide | B38: Почему стоит приехать / текст аудиогида | C38: Ала-Арча — лучший способ за один день из Бишкека попасть в настоящие высокие горы: садись на автобус №1 у площади Усубалиева и через час ты у КПП. Дальше бесплатный электробус довезёт до альплагеря — оттуда стартуют все тропы. Для первого раза хватит водопада Ак-Сай: 4,3 км и +700 м, около 2,5 часа вверх, с видом на ледниковый цирк. Если хорошо акклиматизирован — продолжи к хижине Рацека (~3380 м), но выходи рано: после обеда в горах часто портится погода. Костры запрещены, так что бери термос и перекус или обедай в кафе у альплагеря.
A39: see | B39: Что посмотреть | C39: Прогулочные участки вдоль Ала-Арчи, альплагерь, водопад Ак-Сай; хижина Рацека — отдельный более трудный поход.
A40: skip | B40: Кому не стоит | C40: Ты уже ходил в похожие ущелья (Аламедин, Кегеты) и ищешь безлюдье — в выходные здесь многолюдно. Тебе нужна поездка на своей машине до троп — с мая 2025 г. внутрь пускают только электромобили. Не готов к набору 700+ м даже на «лёгкий» водопад.
A42: #section | B42: Медиа
A43: #table:photos | B43: Фото — 2
A44: #keys | C44: f | D44: t | E44: w | F44: h | G44: cap | H44: by | I44: lic | J44: page
A45: #labels | B45: № / строки ниже | C45: Файл (img/…) | D45: Миниатюра (img/t_…) | E45: Ширина | F45: Высота | G45: Подпись | H45: Автор | I45: Лицензия | J45: Страница-источник
B46: 1 | C46: img/photo-3892277193e31d1c.jpg | D46: img/t_photo-3892277193e31d1c.jpg | E46: 600 | F46: 449 | G46: Национальный парк Ала-Арча | H46: Nikolai Bulykin | I46: CC BY-SA 4.0 | J46: https://commons.wikimedia.org/wiki/File:%D0%90%D0%BB%D0%B0-%D0%90%D1%80%D1%87%D0%B0_%D1%81%D0%B2%D0%B5%D1%80%D1%85%D1%83_(1).jpg
B47: 2 | C47: img/photo-2e255e4b1611203f.jpg | D47: img/t_photo-2e255e4b1611203f.jpg | E47: 600 | F47: 265 | G47: Kyrgyzstan Alpinism, Ala Archa National Park (7208606302) | H47: Thomas Depenbusch (Depi) from Cologne, Germany | I47: CC BY 2.0 | J47: https://commons.wikimedia.org/wiki/File:Kyrgyzstan_Alpinism,_Ala_Archa_National_Park_(7208606302).jpg
A49: #table:videos | B49: Видео — 3
A50: #keys | C50: t | D50: u | E50: ch | F50: y
A51: #labels | B51: № / строки ниже | C51: Заголовок | D51: Ссылка | E51: Канал | F51: Год
B52: 1 | C52: Ala-Archa NATIONAL PARK in Kyrgyzstan | D52: https://www.youtube.com/watch?v=VnN-OeicdW0 | E52: не проверено | F52: не проверено; права уточнить
B53: 2 | C53: Hiking in Ala Archa National Park | D53: https://www.youtube.com/watch?v=uDGmSwYI06g | E53: не проверено | F53: не проверено; права уточнить
B54: 3 | C54: Ratzek Hut & Ak-Sai Glacier | D54: https://www.youtube.com/watch?v=15oFvVkTY0M | E54: не проверено | F54: не проверено; права уточнить
A56: #table:photo_links | B56: Фото-ссылки (внешние) — 6
A57: #keys | C57: cap | D57: url | E57: by
A58: #labels | B58: № / строки ниже | C58: Подпись | D58: Ссылка | E58: Автор
B59: 1 | C59: Hiking in Ala Archa | D59: https://commons.wikimedia.org/wiki/File:Hiking_in_Ala_Archa.jpg | E59: Adamboluu
B60: 2 | C60: Ala Archa 1 | D60: https://commons.wikimedia.org/wiki/File:Ala_Archa_1.JPG | E60: Mass Ave 975
B61: 3 | C61: Ala Archa National Park banner | D61: https://commons.wikimedia.org/wiki/File:Ala_Archa_National_Park_banner.jpg | E61: Davide Mauro
B62: 4 | C62: Ala Archa trek 01 | D62: https://commons.wikimedia.org/wiki/File:Ala_Archa_trek_01.jpg | E62: Davide Mauro
B63: 5 | C63: Entrance of Ala Archa National Park | D63: https://commons.wikimedia.org/wiki/File:Entrance_of_Ala_Archa_National_Park.jpg | E63: Davide Mauro
B64: 6 | C64: Kyrgyzstan Ala Archa National Park 03 | D64: https://commons.wikimedia.org/wiki/File:Kyrgyzstan_Ala_Archa_National_Park_03.jpg | E64: Vitaliknyc
A67: #section | B67: Дорога
A68: how | B68: Как добраться (кратко) | C68: Автобус №1 (полуэкспресс): старая площадь Усубалиева (угол Абдымомунова и Эркиндик) → КПП парка, 08:00–19:00, интервал 20–30 мин, 45–60 мин в пути, 50 сом наличными / 40 сом картой (economist.kg 05.2025; adventuresoflilnicki 09.2026; маршрут по городу изменён 02.09.2025). Такси 40–60 мин. Машины с ДВС оставляют на парковке у КПП, дальше — бесплатный электробус ~12 км до альплагеря.
A69: needcar | B69: Нужна ли машина | C69: Для подъезда — да, но достаточно городского автобуса №1 или такси. Внутри парка личный транспорт не нужен: бесплатные электробусы до альплагеря и начала троп.
A70: self | B70: Самостоятельно / с гидом | C70: Да: автобус №1, билет на КПП (по QR-коду), бесплатный электробус и маркированные популярные тропы. Для хижины Рацека и ледников нужна горная подготовка; ночёвку в хижине бронируют через Ak-Sai Travel.
A71: roadtype | B71: Тип дороги | C71: Асфальт от Бишкека до КПП (горный серпантин в конце); внутри парка — асфальтированная дорога для электробусов до альплагеря; выше — горные тропы.
A72: traveltime | B72: Время в пути | C72: Из центра Бишкека: автобус №1 — 45–60 мин, такси — 40–60 мин (~40 км; hiking.kg — 43 км, 1 ч 10 мин). От альплагеря: водопад Ак-Сай — 4,3 км, ~2,5 ч вверх, +700 м (hiking.kg); хижина Рацека — 5,7 км в одну сторону (asiamixtravel), обычно 3,5–4,5 ч вверх (editorial).
A73: transfer | B73: Трансфер | C73: Автобус №1 — 50 сом наличными / 40 сом картой (2025–2026); такси Бишкек — Ала-Арча 800–1500 сом в одну сторону (vc.ru 2026); туры $30–80 с человека; электробус внутри парка — бесплатно.
A74: p_sum | B74: Дорога: сводка | C74: Проще всего — автобус №1 от старой площади Усубалиева (50 сом наличными / 40 картой, 08:00–19:00, каждые 20–30 мин) или такси ≈1000 сом до КПП; машины с ДВС оставляют на большой парковке у входа. На КПП — билет 250 сом (дети 7–14 — 180), дальше бесплатный электробус ~12 км до альплагеря (каждые 10–15 мин днём). С 19.02.2026 у альплагеря работает гондола Doppelmayr (1 км, 2166→2494 м, 600 сом туда-обратно, только безнал, по вторникам не работает). Классика на день — водопад Ак-Сай (≈4 км, +450–700 м); подготовленным — хижина Рацека (6,4 км, +1100 м, 3380 м; койка 700–1400 сом, бронь через Ak-Sai Travel). Выезжайте рано: в выходные очереди на электробус.
A75: #table:routes | B75: Подъезды — 1
A76: #keys | C76: rec | D76: title | E76: from | F76: route | G76: km | H76: time | I76: surface | J76: vehicle | K76: season | L76: last | M76: parking_d | N76: parking_price | O76: trail_d | P76: haz | Q76: src | R76: hub | S76: hub_lat | T76: hub_lon | U76: rkm | V76: parking_lat | W76: parking_lon | X76: trail_lat | Y76: trail_lon | Z76: road | AA76: has_rt
A77: #labels | B77: № / строки ниже | C77: Рекомендован (да/нет) | D77: Название варианта | E77: Откуда | F77: Маршрут | G77: Км | H77: Время | I77: Покрытие | J77: Машина | K77: Сезон | L77: Последние АЗС/магазины | M77: Парковка | N77: Парковка: цена | O77: Тропа от парковки | P77: Опасности | Q77: Источник | R77: Город-старт | S77: Старт: широта | T77: Старт: долгота | U77: Км по графу дорог | V77: Парковка: широта | W77: Парковка: долгота | X77: Тропа: широта | Y77: Тропа: долгота | Z77: Геометрия дороги (JSON, генерируется) | AA77: Есть маршрут на карте (да/нет)
B78: 1 | C78: да | D78: Из Бишкека по асфальту через Кашка-Суу до КПП, далее электробус | E78: Бишкек (≈40 км, 40–60 мин) | F78: Бишкек → юг по ул. Ж. Абдрахманова/Ахунбаева → Кой-Таш/Кашка-Суу → КПП парка (метка 42.64484, 74.48032) → электробус ~12 км по ущелью до альплагеря «Ала-Арча» (≈2150–2200 м) | G78: ≈40 до КПП + 12 внутри парка | H78: 40–60 мин до КПП; электробус ≈10–20 мин | I78: Асфальт до КПП и внутри парка (дорога для электробусов) | J78: седан (до КПП); внутрь — только электромобили (880 сом) | K78: Круглый год; электробусы ходят круглосуточно (днём каждые 10 мин, ночью 30–40 мин — summitx 2025; asocialnomad 2026 — каждые 15 мин, обратные до ~19:00–20:00) | L78: АЗС, банкоматы, супермаркеты — Бишкек и Кой-Таш; у КПП и альплагеря — кафе и кофейни; карточные терминалы на КПП ненадёжны, держите наличные; связь — до альплагеря | M78: Новая парковка перед КПП: 700 мест на старте с расширением до 2500 (24.kg, 04.2025); машины с ДВС дальше не пускают; турникеты и терминалы оплаты на КПП | N78: 50 сом (hiking.kg, дата не указана); актуальный тариф 2026 не подтверждён | O78: Альплагерь «Ала-Арча» — конечная электробусов: старт троп на водопад Ак-Сай/хижину Рацека, в ущелье Адыгене и прогулочной дорожки вдоль реки; рядом — нижняя станция гондолы | P78: Очереди на электробус в выходные; выше альплагеря — горняшка, камнепады, лавины вне сезона; в 2026 г. стройка канатки и отелей местами перекрыла старые тропы (eurasia.travel форум, 05.2026) | Q78: https://kaktus.media/doc/523788_v_yshele_ala_archa_zapyshen_avtobysnyy_marshryt.html | R78: Бишкек | S78: 42.8746 | T78: 74.5698 | U78: 5 | V78: 42.6448 | W78: 74.4803 | X78: 42.565 | Y78: 74.484 | Z78: [[42.876, 74.536], [42.868, 74.478]] | AA78: да
A80: #table:transport | B80: Транспорт и туры — 8
A81: #keys | C81: mode | D81: provider | E81: from | F81: details | G81: price | H81: year | I81: contact | J81: src
A82: #labels | B82: № / строки ниже | C82: Вид | D82: Перевозчик | E82: Откуда | F82: Подробно | G82: Цена | H82: Год цены | I82: Контакт | J82: Источник
B83: 1 | C83: маршрутка | D83: Автобус №1 (ISUZU 12 м, газ) | E83: Бишкек, старая площадь Т. Усубалиева (угол Абдымомунова и Эркиндик) → КПП парка | F83: 08:00–19:00, интервал 20–30 мин, 45–60 мин в пути; по ул. Ж. Абдрахманова; запущен 16.05.2025, сделан постоянным | G83: 50 сом наличными / 40 сом картой | H83: 2025–2026 | J83: https://kaktus.media/doc/523788_v_yshele_ala_archa_zapyshen_avtobysnyy_marshryt.html
B84: 2 | C84: такси | D84: Yandex Go / inDrive | E84: Бишкек → КПП | F84: 40–60 мин | G84: ≈1000 сом в одну сторону (asocialnomad 2026); 800–1500 сом (vc.ru 2026); ранее 860 сом (akchabar 2025) | H84: 2025–2026 | J84: https://asocialnomad.com/?p=67183
B85: 3 | C85: другое | D85: Электробусы/электрокары парка (~80 машин) | E85: КПП → альплагерь | F85: ~12 км; входит в стоимость билета; круглосуточно | G85: бесплатно (в составе входного билета) | H85: 2025–2026 | I85: КПП +996 312 883 205 | J85: https://summitx.info/en/articles/64816882
B86: 4 | C86: канатная дорога | D86: Гондола Doppelmayr «Ала-Арча» | E86: альплагерь (2166 м) → верхняя станция 2494 м (район «Разбитого сердца») | F86: 1000 м, 16 кабин по 10 мест + 2 VIP, 1000 чел/ч; открыта 19.02.2026; по вторникам не работает (asocialnomad); 2-я очередь ~12 км к входу — строится с 03.2026 | G86: взрослые 600 сом, дети 400 сом туда-обратно, только безнал | H86: 2026 | J86: https://economist.kg/novosti/2026/02/18/proiezd-na-novoi-kanatkie-v-ala-archie-budiet-stoit-600-somov-podrobnosti/
B87: 5 | C87: другое | D87: Личный электромобиль | E87: КПП → внутрь парка | F87: Только электромобили | G87: 880 сом (с 08–11.06.2026; ранее 800) | H87: 2026 | J87: https://kaktus.media/doc/547793_v_parke_ala_archa_povysili_stoimost_posesheniia_i_vezda_elektromobiley.html
B88: 6 | C88: тур | D88: Tripster, Sputnik8, KG Country, Ak-Sai Travel | E88: Бишкек | F88: Однодневные экскурсии; Ak-Sai — бронь хижины Рацека, альпинизм | G88: $30–80 с человека | H88: 2026 | I88: ak-sai.com | J88: этап 1 (vc.ru)
B89: 7 | C89: другое | D89: Носильщики (портеры) до хижины Рацека | E89: альплагерь → Рацек | F89: WhatsApp | G89: 250 сом/кг | H89: 2025 | I89: +996 708 885 618 | J89: https://summitx.info/en/articles/64816882
B90: 8 | C90: велосипед | D90: самостоятельно | E90: Бишкек | F90: Велосипедисты доезжают своим ходом (подъём ~40 км) | H90: 2026 | J90: https://www.weproject.media/articles/detail/kak-provesti-idealnyy-den-v-ala-arche-letom-marshrut-s-novoy-kanatnoy-dorogoy/?amp=y
A93: #section | B93: Сезон и что взять
A94: when | B94: Когда ехать (подробно) | C94: Май — октябрь — основной сезон походов (asiamixtravel 2026); июль — сентябрь — лучшее время для хижины Рацека. Зимой парк открыт (электробусы ходят круглосуточно по hiking.kg), тропы в снегу и лавиноопасны, рядом катание на лыжах.
A95: diff | B95: Сложность (подробно) | C95: Единой сложности у парка нет: прогулка вдоль реки, тропа к водопаду и подъём к хижине Рацека требуют разной подготовки.
A96: hours | B96: Часы работы | C96: Парк открыт ежедневно; электробусы курсируют круглосуточно (hiking.kg), Google и 2ГИС указывают «24 часа». Офис администрации — 09:00–17:30, сб–вс выходные (сайт парка) — не путать с режимом КПП. Автобус №1 ходит 08:00–19:00. КПП: +996 312 883 205.
A97: daytime | B97: Лучшее время суток | C97: Раннее утро: меньше людей в электробусах и на тропе, стабильная погода; в горах после полудня чаще облака и гроза. В выходные приезжай к открытию — очереди на электробус (editorial).
A98: p_season | B98: Сезон (подробно) | C98: Май — октябрь — основной сезон; июль — сентябрь — лучшее время для Рацека и Адыгене; выходные — очереди на электробус. Ноябрь — апрель: парк открыт, тропы в снегу, лавиноопасно выше альплагеря; ледолазание и лыжи (Кашка-Суу). Праздничные дни иногда с бесплатным входом (1 мая 2025). Новые тарифы с 08.06.2026.
A99: bring | B99: Что взять | C99: Треккинговую обувь, ветровку и тёплый слой (высоты 2150–3400 м), воду 1,5–2 л и перекус (костры запрещены), солнцезащиту, наличные для КПП (карточные терминалы ненадёжны — vc.ru), палки для спуска; для Рацека — налобный фонарь и пуховку.
A101: #section | B101: Важно
A102: warn | B102: Важно / предупреждения | C102: С 1 мая 2025 г. въезд машин с ДВС запрещён — парковка у КПП и электробус. Костры и мангалы на дровах запрещены (только газовые мангалы в спецзонах). Выше альплагеря — высота 2800–3400 м: горная болезнь, резкая смена погоды, лавины и камнепады вне сезона; поворачивай назад при ухудшении видимости (asiamixtravel). Тарифы меняются — проверяй на КПП +996 312 883 205.
A103: entry | B103: Вход (подробно) | C103: С 11.06.2026: взрослые 250 сом, дети 7–14 лет 180 сом, до 7 лет бесплатно; въезд личного электромобиля 880 сом (24.kg 11.06.2026; asiamixtravel 2026; Reporter.kg). До этого (с 01.05.2025): 200/150 сом, электромобиль 800 сом (banks.kg, economist.kg). Билет — по QR-коду на КПП. Парковка у КПП — 50 сом (hiking.kg, без даты). Тариф на сайте парка (пеший вход бесплатно, авто 700 сом) устарел.
A104: net | B104: Связь (подробно) | C104: У КПП и альплагеря мобильная связь обычно есть, выше по тропам — нестабильна; «не рассчитывай на надёжное покрытие в горах» (asiamixtravel 2026). Оператор по участкам не подтверждён.
A105: p_permits | B105: Разрешения | C105: Билет на КПП (QR): взрослые 250 сом, дети 7–14 — 180, до 7 лет бесплатно (с 08.06.2026); электромобиль 880 сом. Электробус включён. Гондола — отдельно, только безнал. Погранпропуск не нужен. Костры запрещены.
A106: p_access | B106: Доступность (дети, пожилые…) | C106: С детьми — да (электробус, дорожка вдоль реки 1,3 км, гондола; детский билет 180 сом). Пожилым — электробус + гондола + дорожка вдоль реки. Коляска — дорожка вдоль реки подходит (eurasia.travel), остальное — нет. Скидок для людей с инвалидностью в тарифе 2026 нет (критика в соцсетях). Собаки — правил не найдено.
A108: #section | B108: Ночлег и еда
A109: stay | B109: Ночлег (кратко) | C109: В парке: гостиница/коттеджи у альплагеря, юрточный городок, ресторан (banks.kg 2025); хижина Рацека (~3380 м, бронь через Ak-Sai Travel); рядом — ALTO Cabins, Manzara A-Frames, горнолыжная база Кашка-Суу (adventuresoflilnicki 2026). Цены 2026 в источниках не указаны.
A110: food | B110: Еда (кратко) | C110: Ресторан и кафе с напитками и выпечкой у альплагеря, юрточный городок (banks.kg, 2025); популярен горный чай из термоса и пикник у газовых мангалов в отведённых зонах. Конкретные меню и цены не подтверждены.
A111: #table:stays | B111: Ночлег — 6
A112: #keys | C112: name | D112: type | E112: where | F112: season | G112: price | H112: year | I112: contact | J112: src
...

Sheet kg-0004
A1: #title | B1: Озеро Тулпар-Куль | C1: kg-0004 · ← к оглавлению
A2: #section | B2: Основное
A3: id | B3: ID места (kg-…, alt-…) | C3: kg-0004
A4: country | B4: Страна (kg / alt) | C4: kg
A5: publish | B5: Публикация | C5: опубликовано
A6: status | B6: Статус проверки | C6: Проверено
A7: name | B7: Название | C7: Озеро Тулпар-Куль
A8: full | B8: Полное название | C8: Озеро Тулпар-Куль
A9: cat | B9: Категория | C9: Озеро
A10: reg | B10: Регион | C10: Ошская область
A11: dist | B11: Район | C11: Алайский район Ошской области
A12: lat | B12: Широта | C12: 39.505431
A13: lon | B13: Долгота | C13: 72.935057
A14: elev | B14: Высота | C14: Около 3500 м (too.kg; у юрточного лагеря — sarymogol.com). Утверждение Visit Alay о «той же высоте, что и базовый лагерь» не принято как точная отметка.
A15: near | B15: Ближайший пункт | C15: Сары-Могол — около 25 км к северо-западу (Visit Alay, Backpack Adventures); база для трансферов, лошадей и CBT. Также доступ верхом из Кашка-Суу (too.kg).
A16: tags | B16: Теги (через ;) | C16: lakes;any-car;easy;top;no-car;hiking;horses;yurts
A17: top | B17: В топе (да/нет) | C17: да
A18: rank | B18: Место в рейтинге | C18: 10
A19: updated_at | B19: Изменено (дата)
A20: updated_by | B20: Кто изменил
A22: #section | B22: Коротко на карточке (плашки)
A23: months | B23: Месяцы сезона (1;2;…12) | C23: 5;6;7;8;9;10
A24: month_scores | B24: Оценка месяцев (JSON: месяц → 2 лучшее, 1 подходит), напр. {"6":1,"7":2} | C24: {"5":1,"6":2,"7":2,"8":2,"9":1,"10":1}
A25: s_diff | B25: Сложность (коротко) | C25: Лёгкая
A26: s_when | B26: Когда (коротко) | C26: Май – окт
A27: s_acc | B27: Доступ (коротко) | C27: На любой машине
A28: s_onsite | B28: Время на месте (коротко) | C28: 5–8 ч
A29: s_entry | B29: Вход (коротко) | C29: Входного билета нет
A30: s_net | B30: Связь (коротко) | C30: Конкретное покрытие…
A31: rating_v | B31: Рейтинг | C31: 4.9
A32: rating_n | B32: Кол-во оценок | C32: 38
A33: rating_src | B33: Источник рейтинга | C33: Google
A35: #section | B35: Обзор — тексты
A36: short | B36: Коротко (1–2 предложения) | C36: Тулпар-Куль — высокогорное озеро (~3500 м) в Алайской долине, в шаговой доступности от базового лагеря пика Ленина (7134 м), с юрточными лагерями на берегу.
A37: desc | B37: Описание | C37: Тулпар-Куль (Тулпар-Кёл) — довольно большое прозрачное озеро на высоте около 3500 м у подножия Заалайского хребта, в шаговой доступности от Ачык-Таша — базового лагеря пика Ленина (too.kg). В тихую погоду в нём отражается пик Ленина (7134 м). До озера 25 км от села Сары-Могол: около 45 мин на машине, 4–5 ч верхом или 8–9 ч пешком (Visit Alay). Летом на берегу работают юрточные лагеря CBT и частных хозяев (от 1000 сом за ночь с завтраком и ужином — Visit Alay). От озера начинаются однодневные треки к «Перевалу путешественников» (~4100 м) и к языку ледника Ленина, многодневные — на пик Юхина и Раздельную (Visit Alay, CBT). Район в пограничной зоне — нужен пропуск (Visit Alay).
A38: guide | B38: Почему стоит приехать / текст аудиогида | C38: Приходи к озеру рано утром: в штиль пик Ленина отражается в воде, а после обеда погода в Заалае часто портится (отзывы TripAdvisor). Ночуй в юрте на берегу — от 1000 сом с ужином и завтраком (Visit Alay) — и на следующий день поднимись на «Перевал путешественников» (~4100 м): 3 ч вверх, 2 ч вниз и панорама всей стены Ленина. Не забудь пограничный пропуск — оформление занимает 10–20 дней (Visit Alay). Если попадёшь на третьи выходные июля, в Сары-Моголе проходит фестиваль конных и ячьих игр.
A39: see | B39: Что посмотреть | C39: Отражение пика Ленина (7134 м) в озере; стена Заалайского хребта; базовый лагерь Ачык-Таш рядом; трек на «Перевал путешественников» (~4100 м) и к леднику Ленина; сурки на лугах (too.kg, Visit Alay, TripAdvisor).
A40: skip | B40: Кому не стоит | C40: Ты не успеваешь оформить пограничный пропуск (10–20 дней). Плохо переносишь высоту — ночёвка на ~3500 м без акклиматизации тяжела. Тебе хватит вида на пик Ленина с трассы у Сары-Таша.
A42: #section | B42: Медиа
A43: #table:photos | B43: Фото — 2
A44: #keys | C44: f | D44: t | E44: w | F44: h | G44: cap | H44: by | I44: lic | J44: page
A45: #labels | B45: № / строки ниже | C45: Файл (img/…) | D45: Миниатюра (img/t_…) | E45: Ширина | F45: Высота | G45: Подпись | H45: Автор | I45: Лицензия | J45: Страница-источник
B46: 1 | C46: img/photo-c34e8e7197737128.jpg | D46: img/t_photo-c34e8e7197737128.jpg | E46: 450 | F46: 600 | G46: Озеро Тулпар-Куль | H46: Mamatkazy | I46: CC0 | J46: https://commons.wikimedia.org/wiki/File:%D0%A2%D1%83%D0%BB%D0%BF%D0%B0%D1%80-%D0%9A%D3%A9%D0%BB.jpg
B47: 2 | C47: img/photo-92cfb162c663b42f.jpg | D47: img/t_photo-92cfb162c663b42f.jpg | E47: 600 | F47: 300 | G47: Camp next to Tulpar Kol Lake | H47: Kondephy | I47: CC BY-SA 4.0 | J47: https://commons.wikimedia.org/wiki/File:Camp_next_to_Tulpar_Kol_Lake.jpg
A49: #table:videos | B49: Видео — 3
A50: #keys | C50: t | D50: u | E50: ch | F50: y
A51: #labels | B51: № / строки ниже | C51: Заголовок | D51: Ссылка | E51: Канал | F51: Год
B52: 1 | C52: Tulpar Kul | D52: https://www.youtube.com/watch?v=vEgbZJ6M1WQ | E52: не проверено | F52: не проверено
B53: 2 | C53: Lake Tulpar: Kyrgyzstan's Hidden Wonder | D53: https://www.youtube.com/watch?v=goPPMNROsoY | E53: не проверено | F53: не проверено
B54: 3 | C54: Il Tulpar Lake e il campo base del Lenin Peak | D54: https://www.youtube.com/watch?v=8Miqz_6mFZs | E54: не проверено | F54: не проверено
A56: #table:photo_links | B56: Фото-ссылки (внешние) — 0
A57: #keys | C57: cap | D57: url | E57: by
A58: #labels | B58: № / строки ниже | C58: Подпись | D58: Ссылка | E58: Автор
A61: #section | B61: Дорога
A62: how | B62: Как добраться (кратко) | C62: Из Оша до Сары-Могола (~4 ч, CBT): маршрутка с автовокзала Оша в 14:00, прибытие около 18:00, 300 сом; шеринг-такси с нового автовокзала 400 сом/место; частная машина 3000 сом (Backpack Adventures; рейс в 14:00 подтверждён расписанием на 27.08.2026 — I Love KG). Расстояние Ош — Сары-Могол ~220 км, около 4 ч чистого хода (I Love KG). Из Сары-Могола 25 км до юрточного лагеря у озера: ~45 мин–1 ч на машине (Visit Alay, CBT), 4–5 ч верхом или 8–9 ч пешком (Visit Alay).
A63: needcar | B63: Нужна ли машина | C63: Да: до Сары-Могола — маршрутка/такси; от Сары-Могола до озера — машина CBT/частная (1500 сом за машину), лошадь или пеший переход 8–9 ч.
A64: self | B64: Самостоятельно / с гидом | C64: Да, с пограничным пропуском: маршрутка/такси до Сары-Могола, оттуда машина CBT или пешком; палатку можно ставить бесплатно в отведённых местах (Visit Alay).
A65: roadtype | B65: Тип дороги | C65: Ош — Сары-Таш — Сары-Могол — асфальт (трасса через Талдык); от Сары-Могола до озера 25 км грунтовой дороги по Алайской долине с бродами, проходимой для машин/внедорожников за ~45 мин (Visit Alay; тип покрытия — editorial по описаниям).
A66: traveltime | B66: Время в пути | C66: Ош → Сары-Могол ~4 ч (CBT; маршрутка 14:00–18:00); Сары-Могол → озеро ~45 мин–1 ч на машине (Visit Alay, CBT), 4–5 ч верхом, 8–9 ч пешком (Visit Alay).
A67: transfer | B67: Трансфер | C67: Ош → Сары-Могол: маршрутка 300 сом, шеринг 400 сом/место, частная машина 3000 сом; Сары-Могол → Тулпар-Куль 1500 сом за машину в одну сторону (Backpack Adventures, Visit Alay; данные 2023–2025, уточнять). Альтернатива из отчёта The Gone Goat: шеринг Ош → Сары-Могол 500 сом/место (3 ч), водитель до Тулпар-Куля 500–800 сом.
A68: p_sum | B68: Дорога: сводка | C68: Из Оша — маршрутка или шеринг до Сары-Могола (220 км, 4–5 ч; маршрутка 14:00 с Нового автовокзала, 300 сом), ночь в гостевом доме, утром машина CBT до озера (23–25 км, ~45 мин–1 ч, 1500–2000 сом за машину) или верхом 4–5 ч. На берегу — юрточные лагеря CBT, Buaisha и других (1000–2000 сом с ужином и завтраком; $30 с трёхразовым питанием), сезон ~конец июня — начало сентября. Главная прогулка — Перевал Путешественников (4150 м, 16 км туда-обратно, 5–8 ч). Пропуск формально нужен для Ачык-Таша; к озеру часто ездят без него, но безопаснее оформить.
A69: #table:routes | B69: Подъезды — 3
A70: #keys | C70: rec | D70: title | E70: from | F70: route | G70: km | H70: time | I70: surface | J70: vehicle | K70: season | L70: last | M70: parking_d | N70: parking_price | O70: trail_d | P70: haz | Q70: src | R70: hub | S70: hub_lat | T70: hub_lon | U70: rkm | V70: parking_lat | W70: parking_lon | X70: trail_lat | Y70: trail_lon | Z70: road | AA70: has_rt
A71: #labels | B71: № / строки ниже | C71: Рекомендован (да/нет) | D71: Название варианта | E71: Откуда | F71: Маршрут | G71: Км | H71: Время | I71: Покрытие | J71: Машина | K71: Сезон | L71: Последние АЗС/магазины | M71: Парковка | N71: Парковка: цена | O71: Тропа от парковки | P71: Опасности | Q71: Источник | R71: Город-старт | S71: Старт: широта | T71: Старт: долгота | U71: Км по графу дорог | V71: Парковка: широта | W71: Парковка: долгота | X71: Тропа: широта | Y71: Тропа: долгота | Z71: Геометрия дороги (JSON, генерируется) | AA71: Есть маршрут на карте (да/нет)
B72: 1 | C72: да | D72: Ош — Гульча — Талдык — Сары-Таш — Сары-Могол — Тулпар-Куль | E72: Ош | F72: Ош — Гульча — перевал Талдык (3615 м) — Сары-Таш — на запад по Алайской долине до Сары-Могола — на юг 23–25 км по грунтовке через Алайскую долину и реку Кызыл-Суу к озеру | G72: ~220 до Сары-Могола + 23–25 до озера | H72: 4–5 ч (до 5–7 ч на общественном) + 45 мин–1 ч | I72: Асфальт Памирского тракта до Сары-Могола (местами ремонт/грунт); от Сары-Могола — грунтовка с бродами, после Сары-Могола «дорога становится непроходимой» для седана (форум), кроссовер проходит | J72: кроссовер / 4×4 (последние 25 км); седан — до Сары-Могола | K72: Конец мая — сентябрь; лагеря работают ~25.06–05.09 (The Gone Goat 2024) или до начала октября (Beyond Wild Places) | L72: Последняя надёжная АЗС и банкомат — Ош/Гульча (в Сары-Моголе банкоматов нет — только наличные, elprismadefer); магазины и базар — Сары-Могол; 4G в Сары-Моголе (SIM на базаре 400 сом/50 ГБ, nomadasaurus 2026); у озера связь местами на возвышенностях (Beyond Wild Places) | M72: У юрточных лагерей на берегу (для гостей) | N72: бесплатно для гостей | O72: Тропа на Перевал Путешественников и к Ачык-Ташу начинается от лагерей у озера | P72: Высота 3500 м — горная болезнь; броды после дождей; ночные заморозки; военные патрули у погранзоны | Q72: https://www.nomadasaurus.com/sary-mogol-kyrgyzstan/ | R72: Ош | S72: 40.5283 | T72: 72.7985 | U72: 201 | V72: 39.5075 | W72: 72.9365 | X72: 39.5054 | Y72: 72.9351 | Z72: [[40.529, 72.803], [40.529, 72.812], [40.533, 72.923], [40.496, 73.034], [40.471, 73.063], [40.434, 73.088], [40.335, 73.195], [40.29, 73.29], [40.249, 73.34], [40.245, 73.368], [40.261, 73.41], [40.273, 73.43], [40.302, 73.451], [40.306, 73.467], [40.29, 73.484], [40.24, 73.5], [40.203, 73.496], [40.162, 73.509], [40.067, 73.566], [40.047, 73.571], [39.935, 73.492], [39.873, 73.418], [39.778, 73.232], [39.766, 73.191], [39.75, 73.183], [39.741, 73.187], [39.737, 73.249], [39.725, 73.261], [39.708, 73.261], [39.708, 73.212], [39.679, 72.997], [39.684, 72.96], [39.667, 72.832], [39.655, 72.803]] | AA72: да
B73: 2 | C73: нет | D73: Пешком/верхом из Сары-Могола | E73: Сары-Могол | F73: Сары-Могол — через Алайскую долину на юг к озеру | G73: 23–25 | H73: 6 ч (Beyond Wild Places) – 8–9 ч пешком; 4–5 ч верхом | I73: грунт, броды | J73: пешком/верхом | K73: июнь–сентябрь | L73: Сары-Могол | M73: Гостевой дом в Сары-Моголе | O73: Сары-Могол | P73: Visit Alay называет пешую дорогу «малопривлекательной» (25 км по долине, nomadasaurus) — лучше машиной туда, пешком обратно | Q73: https://visitalay.com/lenin-peak-base-camp/ | R73: Сары-Могол | S73: 39.68 | T73: 72.89 | U73: 3 | Z73: [[39.667, 72.832], [39.655, 72.803]] | AA73: да
B74: 3 | C74: нет | D74: Верхом из Кашка-Суу | E74: Кашка-Суу (Алайская долина) | F74: Кашка-Суу — Тулпар-Куль | G74: не найдено | H74: не найдено | I74: тропа | J74: верхом | K74: лето | L74: не найдено | Q74: https://too.kg/en/tulpar-kul-lake/ | R74: Кашка-Суу | S74: 42.699318 | T74: 74.531734 | U74: 756 | Z74: [[42.868, 74.478], [42.847, 74.243], [42.822, 74.103], [42.818, 73.938], [42.798, 73.872], [42.781, 73.88], [42.641, 73.905], [42.587, 73.888], [42.525, 73.855], [42.492, 73.859], [42.414, 73.839], [42.29, 73.847], [42.27, 73.843], [42.253, 73.826], [42.212, 73.727], [42.187, 73.624], [42.175, 73.463], [42.187, 73.232], [42.195, 73.191], [42.195, 73.121], [42.204, 73.084], [42.245, 73.018], [42.249, 72.981], [42.237, 72.968], [42.204, 72.972], [42.175, 72.948], [42.154, 72.841], [42.121, 72.795], [42.105, 72.791], [42.055, 72.816], [42.01, 72.824], [41.989, 72.849], [41.911, 72.907], [41.878, 72.981], [41.878, 73.018], [41.841, 73.187], [41.799, 73.228], [41.795, 73.241], [41.795, 73.298], [41.787, 73.323], [41.775, 73.335], [41.758, 73.335], [41.742, 73.319], [41.733, 73.294], [41.733, 73.249], [41.713, 73.216], [41.705, 73.166], [41.709, 73.117], [41.742, 73.034], [41.742, 73.01], [41.696, 72.898], [41.68, 72.915], [41.672, 72.907], [41.655, 72.799], [41.614, 72.663], [41.63, 72.634], [41.622, 72.572], [41.568, 72.506], [41.564, 72.49], [41.535, 72.449], [41.523, 72.42], [41.515, 72.362], [41.498, 72.317], [41.474, 72.275], [41.436, 72.234], [41.42, 72.23], [41.403, 72.222], [41.383, 72.255], [41.37, 72.259], [41.313, 72.234], [41.288, 72.242], [41.247, 72.238], [41.185, 72.189], [41.144, 72.189], [41.094, 72.185], [41.078, 72.193], [41.057, 72.247], [41.057, 72.28], [41.045, 72.325], [41.041, 72.341], [41.012, 72.486], [41.032, 72.572], [41.061, 72.651], [41.065, 72.671], [41.061, 72.7], [41.032, 72.754], [41.012, 72.762], [40.975, 72.816], [40.958, 72.824], [40.929, 72.853], [40.9, 72.902], [40.896, 72.927], [40.925, 72.981], [40.917, 72.993], [40.834, 72.972], [40.797, 72.956], [40.76, 72.931], [40.715, 72.878], [40.694, 72.865], [40.673, 72.857], [40.612, 72.853], [40.529, 72.812], [40.533, 72.923], [40.496, 73.034], [40.471, 73.063], [40.434, 73.088], [40.335, 73.195], [40.29, 73.29], [40.249, 73.34], [40.245, 73.368], [40.261, 73.41], [40.273, 73.43], [40.302, 73.451], [40.306, 73.467], [40.29, 73.484], [40.24, 73.5], [40.203, 73.496], [40.162, 73.509], [40.067, 73.566], [40.047, 73.571], [39.935, 73.492], [39.873, 73.418], [39.778, 73.232], [39.766, 73.191], [39.75, 73.183], [39.741, 73.187], [39.737, 73.249], [39.725, 73.261], [39.708, 73.261], [39.708, 73.212], [39.679, 72.997], [39.684, 72.96], [39.667, 72.832], [39.655, 72.803]] | AA74: да
A76: #table:transport | B76: Транспорт и туры — 7
A77: #keys | C77: mode | D77: provider | E77: from | F77: details | G77: price | H77: year | I77: contact | J77: src
A78: #labels | B78: № / строки ниже | C78: Вид | D78: Перевозчик | E78: Откуда | F78: Подробно | G78: Цена | H78: Год цены | I78: Контакт | J78: Источник
B79: 1 | C79: маршрутка | D79: Ош → Дароот-Коргон через Сары-Таш и Сары-Могол | E79: Новый автовокзал Оша | F79: Один рейс в день, плановое отправление 14:00, уходит только при заполнении; 4–5 ч | G79: 300 сом | H79: 2026 | J79: https://www.nomadasaurus.com/sary-mogol-kyrgyzstan/
B80: 2 | C80: шеринг-такси | D80: Ош → Сары-Могол | E80: Новый автовокзал Оша | F80: Уходит по заполнению, регулярно; ~3–4 ч | G80: 400 сом/место (nomadasaurus 2026); 500 сом/место (The Gone Goat 2024) | H80: 2024–2026 | J80: https://www.nomadasaurus.com/sary-mogol-kyrgyzstan/
B81: 3 | C81: такси | D81: Машина CBT / местные водители Сары-Могол → Тулпар-Куль | E81: Сары-Могол | F81: 23–25 км, 45 мин–1 ч; машину делят попутчики | G81: от 1500 сом за машину (Visit Alay); 2000 сом от CBT Guesthouse (Beyond Wild Places); доплата водителю шеринга из Оша 500–800 сом (The Gone Goat 2024) | H81: 2024–2025 | I81: CBT Sary-Mogol +996 556 092627 (WhatsApp) | J81: https://visitalay.com/lenin-peak-base-camp/
B82: 4 | C82: трансфер | D82: Частный трансфер Ош → Тулпар-Куль | E82: Ош | F82: Прямая машина | G82: $150 за машину (цена 2023, nomadasaurus) | H82: 2023 | J82: https://www.nomadasaurus.com/sary-mogol-kyrgyzstan/
B83: 5 | C83: лошадь | D83: CBT Sary-Mogol | E83: Сары-Могол | F83: 4–5 ч верхом до озера; бронь через офис CBT | G83: не найдено | I83: +996 556 092627, sarymogol@gmail.com | J83: https://visitalay.com/lenin-peak-base-camp/
B84: 6 | C84: тур | D84: Tripster «Памирские ландшафты: джип-тур к Тулпар-Кёлю» | E84: Ош | F84: 3 дня, джип, ночь в купольном доме на 3400 м (Талдык), Тулпар-Кёль и базовый лагерь, всё включено; сезон 29.05–07.10 | G84: $390/чел. (группа 4) … $1250 (1 чел.) | H84: 2026–2027 | I84: experience.tripster.ru/experience/94927/ | J84: https://experience.tripster.ru/experience/94927/
B85: 7 | C85: тур | D85: Orexca «Тулпар-Куль и базовый лагерь пика Ленина»; CBT Kyrgyzstan 3 дня; Visit Alay «Best of Alay» 8 дней $850 | E85: Ош | F85: Многодневные туры | G85: Visit Alay $850/чел. (2026–2027) | H85: 2026 | I85: oshtours@gmail.com, +996 556 007030 (Visit Alay) | J85: https://www.orexca.com/rus/kyrgyzstan/tours/tulpar-kul-and-lenin-peak-tour.htm
A88: #section | B88: Сезон и что взять
A89: when | B89: Когда ехать (подробно) | C89: Июнь — сентябрь (CBT); юрточные лагеря работают только летом, сезон треккинга с конца мая — июня; с октября растёт риск снега (Backpack Adventures). Фестиваль конных и ячьих игр — третьи выходные июля (Visit Alay). I Love KG: лучшее время июнь–август, юрточные лагеря закрываются в сентябре.
A90: diff | B90: Сложность (подробно) | C90: Само озеро — легко: подъезд на машине до берега. Треки: «Перевал путешественников» — 3 ч вверх/2 ч вниз до ~4100 м (Visit Alay); трек к леднику ~14 км, перевалы до 3820 м, средней сложности (CBT); пик Юхина 2–3 дня, Раздельная 4–5 дней со снаряжением (Visit Alay).
A91: hours | B91: Часы работы | C91: Природная территория, доступна круглосуточно (TripAdvisor: 00:00–23:59); юрточные лагеря — летний сезон (Backpack Adventures). Нужен пограничный пропуск (Visit Alay).
A92: daytime | B92: Лучшее время суток | C92: Раннее утро — штиль и отражение пика Ленина; погода становится непредсказуемой ближе к вечеру (отзывы TripAdvisor).
A93: p_season | B93: Сезон (подробно) | C93: Май — снег на Талдыке, лагеря закрыты; конец июня — начало сентября — юрточные лагеря работают (The Gone Goat: 25.06–05.09); июль — пик, фестиваль конных игр в третьи выходные июля; август — лучшая погода, грозы после обеда; сентябрь — лагеря закрываются, ночи ниже нуля; октябрь–апрель — снег, только Сары-Могол.
A94: bring | B94: Что взять | C94: Тёплую одежду и пуховку (ночи на 3500 м холодные даже летом), солнцезащиту и очки, паспорт и пограничный пропуск, наличные сомы (в Сары-Моголе банкомат открыт в 2023 г. — economist.kg), трекинговую обувь, аптечку от горной болезни.
A96: #section | B96: Важно
A97: warn | B97: Важно / предупреждения | C97: Пограничный пропуск: Visit Alay (FAQ, обновлён 12.07.2026) — для базового лагеря пика Ленина пропуск обязателен; к Тулпар-Кулю часто ездят без него, но Visit Alay настоятельно советует оформить (≈$35–40, 1–2 недели) из-за военных патрулей. Nature's Off Grid Treasures — для Тулпар-Куля и Перевала путешественников пропуск не нужен, но возможны военные проверки (пропуск 2054 сом, 10–20 дней); The Gone Goat — контроль не обнаружен. I Love KG (2026) — не нужен для трассы и Сары-Могола, нужен для Ачык-Таша. Вывод: формально озеро на грани погранзоны — безопаснее оформить. Высота ~3500 м: риск горной болезни. Погода меняется к вечеру (TripAdvisor). Броды по пути от Сары-Могола после дождей могут быть глубокими (editorial).
A98: entry | B98: Вход (подробно) | C98: Входного билета нет. Пограничный пропуск: ≈$35–40 через Visit Alay (FAQ 07.2026) или 2054 сом (Nature's Off Grid Treasures), 1–3 недели оформления; для самого озера формально может не требоваться (см. предупреждение).
A99: net | B99: Связь (подробно) | C99: Конкретное покрытие Beeline/O!/MegaCom у озера в источниках 2025–2026 не подтверждено. В лагерях базового лагеря пика Ленина (Ачык-Таш, ~10 км) есть «3G WiFi» (The Gone Goat); в Сары-Моголе Wi-Fi ненадёжен, советуют местную SIM (Backpack Adventures). Рассчитывай на отсутствие связи у самого озера.
A100: p_permits | B100: Разрешения | C100: Ачык-Таш и базовый лагерь пика Ленина — погранзона, пропуск обязателен (Visit Alay FAQ 07.2026, I Love KG 2026). К самому Тулпар-Кулю часто ездят без пропуска, КПП нет (The Gone Goat 2024, Beyond Wild Places), но возможны военные проверки — безопаснее оформить. Как: через CBT Sary-Mogol или Visit Alay (~$35–40, 1–2 недели) либо самостоятельно через tour.too.kg (3000 сом, 5–7 раб. дней, офис Исанова 105/3); The Gone Goat/Visit Alay указывают 10–20 дней.
A101: p_access | B101: Доступность (дети, пожилые…) | C101: С детьми — да на машине до лагеря (Tripster указывает подходящим для семей), но высота 3500 м — осторожно с маленькими; пожилым — только с машиной и после акклиматизации; на коляске — нет (грунт, юрты); с собакой — возможно, рядом пастушьи собаки и скот.
A103: #section | B103: Ночлег и еда
A104: stay | B104: Ночлег (кратко) | C104: Юрточные лагеря на берегу: от 1000 сом/ночь с завтраком и ужином (Visit Alay; Backpack Adventures); юрточный лагерь CBT Sary-Mogol «Tulpor-Kul» — тёплые юрты у берега, печь, освещение, общие туалет и душ вне юрт (CBT, sarymogol.com); один из отзывов TripAdvisor советует выбрать альтернативу лагерю CBT. Палатка — бесплатно в отведённых местах. В Сары-Моголе — гостевые дома $15–20 с завтраком (Backpack Adventures). Цены по отчётам: CBT-лагерь 1000 сом ($15) за кровать с ужином и завтраком (Nature's Off Grid Treasures) / $30 с трёхразовым питанием (The Gone Goat); палатка на территории лагеря $8–10; ужин 300 сом, завтрак 250 сом.
A105: food | B105: Еда (кратко) | C105: Ужин и завтрак в юрточном лагере (входят в 1000 сом — Visit Alay): кыргызская домашняя кухня, кымыз у пастухов летом; в Сары-Моголе — блюда в гостевых домах (editorial).
A106: #table:stays | B106: Ночлег — 5
A107: #keys | C107: name | D107: type | E107: where | F107: season | G107: price | H107: year | I107: contact | J107: src
A108: #labels | B108: № / строки ниже | C108: Название | D108: Тип | E108: Где | F108: Сезон | G108: Цена | H108: Год цены | I108: Контакт | J108: Источник
B109: 1 | C109: Юрточный лагерь CBT Sary-Mogol «Tulpor-Kul» | D109: юрточный лагерь | E109: берег Тулпар-Куля | F109: ~конец июня — начало сентября | G109: 1000 сом/ночь с завтраком и ужином (Visit Alay); $30 с трёхразовым питанием (The Gone Goat 2024) | H109: 2024–2025 | I109: +996 556 092627, sarymogol.com | J109: https://visitalay.com/lenin-peak-base-camp/
B110: 2 | C110: Buaisha Yurt Camp | D110: юрточный лагерь | E110: берег Тулпар-Куля | F110: май — начало октября | G110: 2000–4000 сом/чел. с 3-разовым питанием (диапазон по лагерям) | H110: 2024–2025 | J110: https://beyondwildplaces.com/guide-to-hiking-to-travellers-pass-from-tulpar-lake/
B111: 3 | C111: Юрточный лагерь Peak Lenin Guesthouse | D111: юрточный лагерь | E111: у озера | F111: лето | G111: не найдено | H111: 2026 | I111: +996 554 866 786 (WhatsApp), leninpeak@list.ru | J111: https://www.nomadasaurus.com/sary-mogol-kyrgyzstan/
B112: 4 | C112: Ak-Sai Travel Achyk-Tash Base Camp | D112: юрты / глэмпинг / палатки | E112: Ачык-Таш, ~10 км (2,5 ч пешком) от озера, 3600 м | F112: июнь — сентябрь | G112: юрта с завтраком $65, с завтраком и ужином $75, полный пансион $85 (за ночь, двухместное размещение); палатка с завтраком $40; Starlink | H112: 2026 | I112: WhatsApp +996 770 901 616, booking@ak-sai.com | J112: https://ak-sai.com/?p=1199
...

Sheet kg-0007
A1: #title | B1: Ущелье Чычкан | C1: kg-0007 · ← к оглавлению
A2: #section | B2: Основное
A3: id | B3: ID места (kg-…, alt-…) | C3: kg-0007
A4: country | B4: Страна (kg / alt) | C4: kg
A5: publish | B5: Публикация | C5: опубликовано
A6: status | B6: Статус проверки | C6: Проверено
A7: name | B7: Название | C7: Ущелье Чычкан
A8: full | B8: Полное название | C8: Ущелье Чычкан
A9: cat | B9: Категория | C9: Ущелье
A10: reg | B10: Регион | C10: Джалал-Абадская область
A11: dist | B11: Район | C11: Токтогульский район
A12: lat | B12: Широта | C12: 42.1278
A13: lon | B13: Долгота | C13: 72.7858
A14: elev | B14: Высота | C14: Средняя высота ущелья около 2200 м; небольшие озёра на склонах — около 3000 м (too.kg). Скалы поднимаются примерно на 1000 м над рекой (central-asia.live).
A15: near | B15: Ближайший пункт | C15: Внутри ущелья сёл нет — только придорожные кафе, форелевые хозяйства и турбаза. Ближайший город — Токтогул (у выхода ущелья к водохранилищу, ~30–50 км по трассе — не уточнено); по OSM в ~23 км по прямой от точки каталога — Мазар-Суу.
A16: tags | B16: Теги (через ;) | C16: gorges;any-car;easy;free;no-car;hiking;horses
A17: top | B17: В топе (да/нет) | C17: нет
A18: rank | B18: Место в рейтинге | C18: 64
A19: updated_at | B19: Изменено (дата)
A20: updated_by | B20: Кто изменил
A22: #section | B22: Коротко на карточке (плашки)
A23: months | B23: Месяцы сезона (1;2;…12) | C23: 5;6;7;8;9;10
A24: month_scores | B24: Оценка месяцев (JSON: месяц → 2 лучшее, 1 подходит), напр. {"6":1,"7":2}
A25: s_diff | B25: Сложность (коротко) | C25: Лёгкая
A26: s_when | B26: Когда (коротко) | C26: Май – окт
A27: s_acc | B27: Доступ (коротко) | C27: На любой машине
A28: s_onsite | B28: Время на месте (коротко) | C28: от 1–2 ч до дня
A29: s_entry | B29: Вход (коротко) | C29: Бесплатно
A30: s_net | B30: Связь (коротко) | C30: Мобильной связи в…
A31: rating_v | B31: Рейтинг | C31: 4.8
A32: rating_n | B32: Кол-во оценок | C32: 36
A33: rating_src | B33: Источник рейтинга | C33: Google
A35: #section | B35: Обзор — тексты
A36: short | B36: Коротко (1–2 предложения) | C36: Чычкан — около 30 км живописного лесистого ущелья одноимённой реки на трассе Бишкек — Ош между перевалом Ала-Бель и Токтогульским водохранилищем: ели, луга, мёд, форелевые хозяйства и придорожные кафе.
A37: desc | B37: Описание | C37: Ущелье Чычкан тянется примерно на 30 км вдоль реки Чычкан в северной части Ферганского хребта (central-asia.live) — от перевала Ала-Бель на юг к Токтогульскому водохранилищу, куда впадает бурная река (too.kg). Средняя высота — около 2200 м; склоны покрыты тянь-шанской елью, цветами и ягодниками, выше — небольшие озёра на ~3000 м. Название переводится как «мышь» — из-за множества полевых мышей в норах на склонах (too.kg). Ущелье известно ароматным мёдом и лекарственными травами; вдоль трассы работают кафе, форелевые хозяйства, гостевые дома и турбаза «Чычкан» (~240 км трассы Бишкек — Ош). Часть территории — государственный заказник «Чычкан». Мобильной связи в ущелье почти нет (too.kg).
A38: guide | B38: Почему стоит приехать / текст аудиогида | C38: Чычкан — лучшая остановка на долгом пути Бишкек — Ош: после голых склонов Суусамыра и Ала-Беля дорога ныряет в еловый лес вдоль бурной реки. Остановись пообедать форелью в одном из придорожных хозяйств и купи местный мёд — ущелье им славится. Если есть пара часов, поднимись по боковым долинам — на высоте около 3000 м прячутся небольшие озёра. Воду из реки не пей — бери из родников или в кафе. Связи нет, так что предупреди близких, что пропадёшь на пару часов.
A39: see | B39: Что посмотреть | C39: Река Чычкан и еловые склоны вдоль трассы; боковые долины (например, река Итагар) и высокогорные озёра (~3000 м); пасеки и продажа мёда; форелевые хозяйства; водопады, пещеры и петроглифы в окрестностях (central-asia.live — без конкретных мест); перевал Ала-Бель на севере и Токтогульское водохранилище на юге.
A40: skip | B40: Кому не стоит | C40: Ты летишь Бишкек — Ош самолётом и не едешь по трассе — специально сюда ехать 5–6 часов нет смысла. Ищешь уединённые места — у трассы плотное движение. Нужна связь — её здесь почти нет.
A42: #section | B42: Медиа
A43: #table:photos | B43: Фото — 2
A44: #keys | C44: f | D44: t | E44: w | F44: h | G44: cap | H44: by | I44: lic | J44: page
A45: #labels | B45: № / строки ниже | C45: Файл (img/…) | D45: Миниатюра (img/t_…) | E45: Ширина | F45: Высота | G45: Подпись | H45: Автор | I45: Лицензия | J45: Страница-источник
B46: 1 | C46: img/photo-d4c73519f016a152.jpg | D46: img/t_photo-d4c73519f016a152.jpg | E46: 600 | F46: 337 | G46: Ущелье Чычкан | H46: Arthur Dolchenko | I46: CC BY-SA 4.0 | J46: https://commons.wikimedia.org/wiki/File:Chychkan_gorge.jpg
B47: 2 | C47: img/photo-725d0e5a0fc9f3e2.jpg | D47: img/t_photo-725d0e5a0fc9f3e2.jpg | E47: 600 | F47: 450 | G47: Chychkan river | H47: Абдырашит Сатылганов | I47: CC BY-SA 4.0 | J47: https://commons.wikimedia.org/wiki/File:Chychkan_river.jpg
A49: #table:videos | B49: Видео — 2
A50: #keys | C50: t | D50: u | E50: ch | F50: y
A51: #labels | B51: № / строки ниже | C51: Заголовок | D51: Ссылка | E51: Канал | F51: Год
B52: 1 | C52: Кыргызстан, Джалал-абадская область. Ущелье Чычкан, река Итагар | D52: https://www.youtube.com/watch?v=Xm90x0tyweg | E52: не проверен | F52: не проверен
B53: 2 | C53: Дорога в Чичканское ущелье | D53: https://www.youtube.com/watch?v=uBsmqsdu558 | E53: не проверен | F53: не проверен
A55: #table:photo_links | B55: Фото-ссылки (внешние) — 1
A56: #keys | C56: cap | D56: url | E56: by
A57: #labels | B57: № / строки ниже | C57: Подпись | D57: Ссылка | E57: Автор
B58: 1 | C58: Chychkan valley | D58: https://commons.wikimedia.org/wiki/File:Chychkan_valley.jpg | E58: Абдырашит Сатылганов
A61: #section | B61: Дорога
A62: how | B62: Как добраться (кратко) | C62: По трассе Бишкек — Ош (ЭМ-02): из Бишкека через тоннель Тоо-Ашуу, Суусамыр и перевал Ала-Бель — около 5–6 ч (avtoprokat.kg); турбаза «Чычкан» — ~240-й км трассы (TripAdvisor). Сбор за проезд тоннелей трассы Бишкек — Ош: 50 сом для машин с КР-номерами / 200 сом для иностранных (с 01.01.2024). Из Оша/Джалал-Абада — на север через Таш-Кумыр и Токтогул.
A63: needcar | B63: Нужна ли машина | C63: Да: ущелье — участок междугородней трассы. Своя машина, такси или место в маршрутке/шеринг-такси Бишкек — Токтогул/Ош (попросить высадить в ущелье).
A64: self | B64: Самостоятельно / с гидом | C64: Да: остановки прямо у трассы, пропуска не нужны. Для походов в боковые долины — офлайн-карта и запас воды.
A65: roadtype | B65: Тип дороги | C65: Асфальтированная междугородняя трасса Бишкек — Ош по дну ущелья; полноприводный автомобиль на основной трассе в хорошую погоду не обязателен (avtoprokat.kg). Боковые съезды — грунт.
A66: traveltime | B66: Время в пути | C66: Из Бишкека — 5–6 ч на машине (avtoprokat.kg); до Токтогула на маршрутке — дольше, с остановками. Из Оша — ориентировочно 6–7 ч (editorial, не подтверждено).
A67: transfer | B67: Трансфер | C67: Бишкек → Токтогул: маршрутка 400 сом, шеринг-такси 600–800 сом/чел., частное такси 3200–5600 сом (toktogulvisit; год публикации не указан).
A68: p_sum | B68: Дорога: сводка | C68: Чычкан — живописный участок трассы Бишкек — Ош между перевалом Ала-Бель и Токтогулом: его проезжают по дороге на юг и останавливаются на обед с форелью, мёд и кымыз, а при желании ночуют на турбазе «Чычкан» (240-й км, ~40–58 $). На машине из Бишкека 5–6 ч (тоннельный сбор 50/200 сом); без машины — маршрутка/шеринг Бишкек — Токтогул или Бишкек — Ош с остановкой по договорённости. Связи в ущелье почти нет.
A69: #table:routes | B69: Подъезды — 2
A70: #keys | C70: rec | D70: title | E70: from | F70: route | G70: km | H70: time | I70: surface | J70: vehicle | K70: season | L70: last | M70: parking_d | N70: parking_price | O70: trail_d | P70: haz | Q70: src | R70: hub | S70: hub_lat | T70: hub_lon | U70: rkm | V70: parking_lat | W70: parking_lon | X70: trail_lat | Y70: trail_lon | Z70: road | AA70: has_rt
A71: #labels | B71: № / строки ниже | C71: Рекомендован (да/нет) | D71: Название варианта | E71: Откуда | F71: Маршрут | G71: Км | H71: Время | I71: Покрытие | J71: Машина | K71: Сезон | L71: Последние АЗС/магазины | M71: Парковка | N71: Парковка: цена | O71: Тропа от парковки | P71: Опасности | Q71: Источник | R71: Город-старт | S71: Старт: широта | T71: Старт: долгота | U71: Км по графу дорог | V71: Парковка: широта | W71: Парковка: долгота | X71: Тропа: широта | Y71: Тропа: долгота | Z71: Геометрия дороги (JSON, генерируется) | AA71: Есть маршрут на карте (да/нет)
B72: 1 | C72: да | D72: С севера: из Бишкека через Тоо-Ашуу, Суусамыр и Ала-Бель | E72: Бишкек (~240 км до турбазы) | F72: Бишкек → Кара-Балта → тоннель Тоо-Ашуу (сбор) → Суусамырская долина → перевал Ала-Бель (3184 м) → спуск в ущелье Чычкан | G72: ≈240 | H72: 5–6 ч | I72: Асфальт ЭМ-02, серпантины Тоо-Ашуу и Ала-Бель | J72: седан | K72: Круглый год; зимой лавиноопасность и гололёд на Тоо-Ашуу/Ала-Беле, возможны временные закрытия | L72: АЗС и кафе — Суусамыр; банкоматы — Бишкек/Кара-Балта, затем Токтогул; связи в ущелье нет | M72: Площадки у придорожных кафе, форелевых хозяйств и турбазы «Чычкан» (240 км) | N72: бесплатно для гостей кафе | O72: Боковые тропы по еловым склонам от турбаз и кафе; маркированных троп нет | P72: Камнепады, гололёд зимой, грузовики на серпантине | Q72: https://too.kg/en/chychkan-gorge/ | R72: Бишкек | S72: 42.8746 | T72: 74.5698 | U72: 214 | V72: 42.1278 | W72: 72.7858 | X72: 42.13922 | Y72: 72.814293 | Z72: [[42.876, 74.536], [42.868, 74.478], [42.847, 74.243], [42.822, 74.103], [42.818, 73.938], [42.798, 73.872], [42.781, 73.88], [42.641, 73.905], [42.587, 73.888], [42.525, 73.855], [42.492, 73.859], [42.414, 73.839], [42.29, 73.847], [42.27, 73.843], [42.253, 73.826], [42.212, 73.727], [42.187, 73.624], [42.175, 73.463], [42.187, 73.232], [42.195, 73.191], [42.195, 73.121], [42.204, 73.084], [42.245, 73.018], [42.249, 72.981], [42.237, 72.968], [42.204, 72.972], [42.175, 72.948], [42.154, 72.841], [42.121, 72.795]] | AA72: да
B73: 2 | C73: нет | D73: С юга: из Оша/Джалал-Абада через Таш-Кумыр и Токтогул | E73: Ош (~370 км), Токтогул (~30–50 км) | F73: Ош → Джалал-Абад → Таш-Кумыр → Кара-Куль → Токтогул → вверх по ущелью | G73: Токтогул ~30–50 (не уточнено) | H73: от Токтогула ~1 ч | I73: Асфальт | J73: седан | K73: Круглый год | L73: Токтогул: АЗС, банкоматы, магазины, гостевые дома | M73: Как выше | Q73: https://kyrgyzstan-tourism.com/news/suusamyr-and-chychkan-mountain-gems-of-kyrgyzstan-in-summer/ | R73: Ош | S73: 40.5283 | T73: 72.7985 | U73: 347 | Z73: [[40.529, 72.803], [40.529, 72.812], [40.612, 72.853], [40.673, 72.857], [40.694, 72.865], [40.715, 72.878], [40.76, 72.931], [40.797, 72.956], [40.834, 72.972], [40.917, 72.993], [40.925, 72.981], [40.896, 72.927], [40.9, 72.902], [40.929, 72.853], [40.958, 72.824], [40.975, 72.816], [41.012, 72.762], [41.032, 72.754], [41.061, 72.7], [41.065, 72.671], [41.061, 72.651], [41.032, 72.572], [41.012, 72.486], [41.041, 72.341], [41.045, 72.325], [41.057, 72.28], [41.057, 72.247], [41.078, 72.193], [41.094, 72.185], [41.144, 72.189], [41.185, 72.189], [41.247, 72.238], [41.288, 72.242], [41.313, 72.234], [41.37, 72.259], [41.383, 72.255], [41.403, 72.222], [41.42, 72.23], [41.436, 72.234], [41.474, 72.275], [41.498, 72.317], [41.515, 72.362], [41.523, 72.42], [41.535, 72.449], [41.564, 72.49], [41.568, 72.506], [41.622, 72.572], [41.63, 72.634], [41.614, 72.663], [41.655, 72.799], [41.672, 72.907], [41.68, 72.915], [41.696, 72.898], [41.742, 73.01], [41.742, 73.034], [41.709, 73.117], [41.705, 73.166], [41.713, 73.216], [41.733, 73.249], [41.733, 73.294], [41.742, 73.319], [41.758, 73.335], [41.775, 73.335], [41.787, 73.323], [41.795, 73.298], [41.795, 73.241], [41.799, 73.228], [41.841, 73.187], [41.878, 73.018], [41.878, 72.981], [41.911, 72.907], [41.989, 72.849], [42.01, 72.824], [42.055, 72.816], [42.105, 72.791], [42.121, 72.795]] | AA73: да
A75: #table:transport | B75: Транспорт и туры — 7
A76: #keys | C76: mode | D76: provider | E76: from | F76: details | G76: price | H76: year | I76: contact | J76: src
A77: #labels | B77: № / строки ниже | C77: Вид | D77: Перевозчик | E77: Откуда | F77: Подробно | G77: Цена | H77: Год цены | I77: Контакт | J77: Источник
B78: 1 | C78: маршрутка | D78: Бишкек → Токтогул | E78: Бишкек — южная точка отправки у будущего ипподрома «Ак-Кула» (с 10.2024); старые источники называют Западный автовокзал | F78: По wikivoyage: 08:15, 10:50, 13:30, 16:15 (265 сом, устаревшая цена); по toktogulvisit: 10:00, 11:00, 14:00 — 400 сом | G78: 400 сом | H78: не указан / ≈2024 | J78: https://kwx.liehendr.com/content/wikivoyage_en_all_maxi_2025-02/A/Toktogul
B79: 2 | C79: шеринг-такси | D79: Бишкек → Токтогул / Бишкек → Ош | E79: Бишкек | F79: Токтогул 600–800 сом/место; Бишкек — Ош 1500–2500 сом/место (останавливаются в Чычкане по просьбе) | G79: 600–2500 сом | H79: 2025 | J79: https://www.weproject.media/articles/detail/bishkek-osh-vybiraem-samyy-udobnyy-sposob-poezdki/?amp=y
B80: 3 | C80: другое | D80: GoBus Бишкек — Ош | E80: Бишкек | F80: Автобус проходит ущелье; остановка не гарантирована | G80: 1200 сом | H80: 2025 | J80: данные этапа 2 (Kaktus 06.2025)
B81: 4 | C81: маршрутка | D81: Ош → Токтогул; Джалал-Абад → Токтогул | E81: Ош, Джалал-Абад | F81: Ош 07:00; Джалал-Абад 06:00, 09:00 | G81: Ош 600 сом, Джалал-Абад 400 сом | H81: не указан | J81: toktogulvisit (этап 1)
B82: 5 | C82: аренда авто | D82: Прокаты Бишкека (Russian Troika и др.) | E82: Бишкек | F82: Для основной трассы 4×4 не нужен | G82: ≈20–100 $/день | H82: 2025 | J82: данные этапа 2
B83: 6 | C83: другое | D83: Сбор за тоннели трассы Бишкек — Ош | F83: Оплачивается на трассе | G83: 50 сом (КР-номера) / 200 сом (иностранные) | H83: с 01.01.2024 | J83: данные этапа 2
B84: 7 | C84: другое | D84: Точка отправки южных маршрутов из Бишкека | E84: Бишкек | F84: С 28.10.2024 маршруты на Ош, Джалал-Абад, Баткен и Талас отправляются с западной окраины (участок у будущего ипподрома «Ак-Кула», рядом с постом ГАИ); туда идут автобусы №13, №40 и маршрутка №258 | H84: 2024 | J84: https://kaktus.media/doc/512072_izmeneny_otpravnye_tochki_mejdygorodnih_marshrytov_iz_bishkeka.html
A87: #section | B87: Сезон и что взять
A88: when | B88: Когда ехать (подробно) | C88: Май — октябрь: ущелье зелёное, придорожные точки работают (avtoprokat.kg). Зимой трасса проезжая, но соседние перевалы (Ала-Бель, Тоо-Ашуу) скользкие и лавиноопасные.
A89: diff | B89: Сложность (подробно) | C89: Лёгкая: остановки у трассы, короткие прогулки. Походы по боковым долинам к озёрам ~3000 м — средние (editorial; too.kg).
A90: hours | B90: Часы работы | C90: Круглосуточно (участок государственной трассы); кафе и форелевые хозяйства работают в основном в тёплый сезон (avtoprokat.kg). Режим заказника — по правилам ООПТ.
A91: daytime | B91: Лучшее время суток | C91: Днём — для обеда и прогулки; планируй проезд горных перевалов трассы засветло (editorial).
A92: p_season | B92: Сезон (подробно) | C92: Июнь — сентябрь: кафе, форель, кымыз, кемпинг. Сентябрь — октябрь: осенние краски. Ноябрь — апрель: трасса открыта, но перевалы Тоо-Ашуу и Ала-Бель с гололёдом и лавинной опасностью; многие кафе закрыты.
A93: bring | B93: Что взять | C93: Наличные на мёд и форель; тёплую кофту (2200 м, прохладно вечером); воду (речную пить не рекомендуется — too.kg); средство от комаров/клещей для прогулок по лесу (editorial).
A95: #section | B95: Важно
A96: warn | B96: Важно / предупреждения | C96: Воду из реки Чычкан не пей — только из родников или купленную (too.kg). Связи нет. Плотный трафик фур — паркуйся только на обочинах и площадках. Зимой и весной на трассе Бишкек — Ош возможны лавины (видео «На дорогу Бишкек-Ош сошла лавина»), скользкие перевалы. Цены на форель в ресторанах могут быть высокими (отзыв TripAdvisor: 2200 сом/кг).
A97: entry | B97: Вход (подробно) | C97: Бесплатно: участок трассы. Платят только сбор за тоннели трассы Бишкек — Ош (50/200 сом с 01.01.2024), не связанный с ущельем.
A98: net | B98: Связь (подробно) | C98: Мобильной связи в ущелье нет или она ограничена (too.kg; avtoprokat.kg). Wi-Fi — в отдельных отелях (не подтверждено).
A99: p_permits | B99: Разрешения | C99: Не нужны. Сбор за тоннели трассы Бишкек — Ош: 50 сом (КР) / 200 сом (иностранные номера) с 01.01.2024.
A100: p_access | B100: Доступность (дети, пожилые…) | C100: Подходит всем: остановки у дороги, кафе. Коляска — у кафе, тропы нет. С собакой — турбаза «Чычкан» заявлена pet-friendly на Casai, но на trip.com «животные запрещены» — уточнять.
A102: #section | B102: Ночлег и еда
A103: stay | B103: Ночлег (кратко) | C103: • Турбаза/отель «Чычкан» (~240 км трассы Бишкек — Ош): 51–58 $ за стандартный номер, завтрак; TripAdvisor 3.1/5, 10 отзывов (2019–05.2026) — хвалят природу и персонал, ругают сантехнику, сырость и цены ресторана. • Мотель Oson — стандартные номера и люксы, горячая вода, питание (каталог C.A.T., +996 704 663 664; цена не подтверждена). • Несколько гостевых домов и много мест для кемпинга (too.kg).
A104: food | B104: Еда (кратко) | C104: Свежая форель из местных хозяйств; горный мёд и травяной чай из трав ущелья (too.kg, avtoprokat.kg). Кафе мотеля Oson и ресторан турбазы «Чычкан».
A105: #table:stays | B105: Ночлег — 7
A106: #keys | C106: name | D106: type | E106: where | F106: season | G106: price | H106: year | I106: contact | J106: src
A107: #labels | B107: № / строки ниже | C107: Название | D107: Тип | E107: Где | F107: Сезон | G107: Цена | H107: Год цены | I107: Контакт | J107: Источник
B108: 1 | C108: Туристический комплекс «Чычкан» (Chychkan Tourist Complex) | D108: отель/турбаза, 3* | E108: Трасса Бишкек — Ош, 240 км | F108: круглый год (не подтверждено) | G108: ≈40 $/ночь (Casai); 51–58 $ с завтраком (TripAdvisor, этап 1) | H108: 2025–2026 | I108: +996 558 802 052 (trip.com) | J108: https://nz.trip.com/hotels/talas-2-hotel-detail-21853792/hychkan-complex
B109: 2 | C109: Мотель Oson | D109: мотель | E109: ущелье | G109: не подтверждено | I109: +996 704 663 664 | J109: этап 1
B110: 3 | C110: Базы отдыха и коттеджи ущелья (в целом) | D110: турбаза/коттеджи | E110: вдоль трассы | F110: в основном лето | G110: 2500–10 000 сом в сутки | H110: 2026 | J110: https://kyrgyzstan-tourism.com/news/suusamyr-and-chychkan-mountain-gems-of-kyrgyzstan-in-summer/
B111: 4 | C111: Shabdan Guest House | D111: гостевой дом | E111: Токтогул | G111: ≈21 £/ночь, рейтинг 9,4 | H111: 2025–2026 | I111: Booking | J111: https://hotels.easyjet.com/city/kg/toktogul.en-gb.html?aid=356980
B112: 5 | C112: Ainazik guest house | D112: гостевой дом | E112: Токтогул | G112: ≈18,5 £ | H112: 2025–2026 | I112: Booking | J112: https://hotels.easyjet.com/city/kg/toktogul.en-gb.html?aid=356980
...

Sheet kg-0009
A1: #title | B1: Озеро Сары-Челек | C1: kg-0009 · ← к оглавлению
A2: #section | B2: Основное
A3: id | B3: ID места (kg-…, alt-…) | C3: kg-0009
A4: country | B4: Страна (kg / alt) | C4: kg
A5: publish | B5: Публикация | C5: опубликовано
A6: status | B6: Статус проверки | C6: Проверено
A7: name | B7: Название | C7: Озеро Сары-Челек
A8: full | B8: Полное название | C8: Озеро Сары-Челек
A9: cat | B9: Категория | C9: Озеро
A10: reg | B10: Регион | C10: Джалал-Абадская область
A11: dist | B11: Район | C11: Аксыйский район
A12: lat | B12: Широта | C12: 41.8899
A13: lon | B13: Долгота | C13: 71.9602
A14: elev | B14: Высота | C14: 1878 м — уровень озера (Trip to Kyrgyzstan, central-asia.guide). Хвойные леса начинаются с ~2100 м (govori.tv).
A15: near | B15: Ближайший пункт | C15: Аркыт — село у подножия заповедника (~200 семей), база размещения; до берега основного озера ~15 км по дороге заповедника (central-asia.guide, journalofnomads, govori.tv).
A16: tags | B16: Теги (через ;) | C16: lakes;any-car;easy;top;no-car;hiking;horses;yurts
A17: top | B17: В топе (да/нет) | C17: да
A18: rank | B18: Место в рейтинге | C18: 7
A19: updated_at | B19: Изменено (дата)
A20: updated_by | B20: Кто изменил
A22: #section | B22: Коротко на карточке (плашки)
A23: months | B23: Месяцы сезона (1;2;…12) | C23: 5;6;7;8;9;10
A24: month_scores | B24: Оценка месяцев (JSON: месяц → 2 лучшее, 1 подходит), напр. {"6":1,"7":2}
A25: s_diff | B25: Сложность (коротко) | C25: Лёгкая
A26: s_when | B26: Когда (коротко) | C26: Май – окт
A27: s_acc | B27: Доступ (коротко) | C27: На любой машине
A28: s_onsite | B28: Время на месте (коротко) | C28: ≈4 ч
A29: s_entry | B29: Вход (коротко) | C29: Источники расходятся
A30: s_net | B30: Связь (коротко) | C30: По наблюдениям hiking
A31: rating_v | B31: Рейтинг | C31: 4.7
A32: rating_n | B32: Кол-во оценок | C32: 476
A33: rating_src | B33: Источник рейтинга | C33: Google
A35: #section | B35: Обзор — тексты
A36: short | B36: Коротко (1–2 предложения) | C36: Сары-Челек — бирюзовое горное озеро на высоте 1878 м и глубиной до 234 м в Сары-Челекском биосферном заповеднике ЮНЕСКО в Чаткальском хребте, окружённое еловыми и ореховыми лесами; всего в заповеднике семь озёр.
A37: desc | B37: Описание | C37: Сары-Челек — крупнейшее озеро одноимённого государственного биосферного заповедника (входит во Всемирную сеть биосферных резерватов ЮНЕСКО) в Чаткальском хребте Западного Тянь-Шаня. Длина озера около 6,2 км, ширина до 2,6 км, глубина до 234 м, уровень — 1878 м (central-asia.guide). Площадь заповедника — 23 868 га; в нём семь озёр: Сары-Челек, Кыла-Кёль, Чойчок-Кёль, Бакалы-Кёль, Арам-Кёль, Ийри-Кёль и Туюк-Кёль (govori.tv). Берега покрыты еловыми, пихтовыми, ореховыми и яблоневыми лесами. Въезд — от села Аркыт через КПП заповедника, дальше ~15 км по серпантину до парковки у основного озера; у берега есть туалет, урны, крытые беседки и зоны для палаток (central-asia.guide). Отсюда проложена тропа к системе малых озёр и панораме (7,1 км, ~3 ч 15 мин, набор 760 м — hiking.kg). В 2026 году запланирована установка автоматизированного КПП (time.kg, 08.06.2026).
A38: guide | B38: Почему стоит приехать / текст аудиогида | C38: Сары-Челек — главная жемчужина запада Кыргызстана: бирюзовая вода глубиной до 234 м в рамке из елей и орешников. Ночуй в Аркыте и выезжай к озеру рано утром, пока гладь зеркальная и туристов мало. Не ограничивайся парковкой: тропа к малым озёрам и на панораму (около 7 км и 3 часа) открывает вид на цепочку озёр сверху. Купаться, разводить костры и рвать растения в заповеднике нельзя — это строгая ООПТ. Бери наличные сомы: плату берут на шлагбауме, а тарифы на месте могут отличаться от того, что пишут в блогах.
A39: see | B39: Что посмотреть | C39: Основное озеро Сары-Челек (бирюзовая вода, 234 м глубины); цепочка малых озёр (Ийри-Кёль, Кыла-Кёль, Чойчок-Кёль, Бакалы-Кёль, Арам-Кёль, Туюк-Кёль); панорама над озёрами (тропа 7,1 км); еловые и ореховые леса; дикие яблони (govori.tv, hiking.kg).
A40: skip | B40: Кому не стоит | C40: У тебя меньше 3–4 дней на запад страны: из Бишкека ~540 км и ~11 ч в одну сторону (hiking.kg). Ты хочешь купаться и жарить шашлык у воды — в заповеднике это запрещено. Едешь до середины мая — дорога может быть закрыта снегом.
A42: #section | B42: Медиа
A43: #table:photos | B43: Фото — 2
A44: #keys | C44: f | D44: t | E44: w | F44: h | G44: cap | H44: by | I44: lic | J44: page
A45: #labels | B45: № / строки ниже | C45: Файл (img/…) | D45: Миниатюра (img/t_…) | E45: Ширина | F45: Высота | G45: Подпись | H45: Автор | I45: Лицензия | J45: Страница-источник
B46: 1 | C46: img/photo-3b28246abe32781f.jpg | D46: img/t_photo-3b28246abe32781f.jpg | E46: 600 | F46: 400 | G46: Озеро Сары-Челек | H46: Kondephy | I46: CC BY-SA 4.0 | J46: https://commons.wikimedia.org/wiki/File:Sary_Chelek_Lake.jpg
B47: 2 | C47: img/photo-e049c6ca214f5bab.jpg | D47: img/t_photo-e049c6ca214f5bab.jpg | E47: 600 | F47: 400 | G47: Территория заповедника Сары-Челек · Sary-Chelek Reserve (12).jpg | H47: Mixathefast24 | I47: CC BY-SA 4.0 | J47: https://commons.wikimedia.org/wiki/File:Sary-Chelek_Reserve_(12).jpg
A49: #table:videos | B49: Видео — 3
A50: #keys | C50: t | D50: u | E50: ch | F50: y
A51: #labels | B51: № / строки ниже | C51: Заголовок | D51: Ссылка | E51: Канал | F51: Год
B52: 1 | C52: Сары-Челек — магия горного озера | D52: https://www.youtube.com/watch?v=K1N_xO5DwMo | E52: не проверен | F52: не проверен
B53: 2 | C53: Погрузиться в мир нетронутой природы. Пять причин побывать на озере Сары-Челек | D53: https://www.youtube.com/watch?v=2WuKlpuAPdU | E53: не проверен | F53: не проверен
B54: 3 | C54: Дорога Бишкек - оз.Сары-Челек | D54: https://www.youtube.com/watch?v=ykxVanzO1LA | E54: не проверен | F54: не проверен
A56: #table:photo_links | B56: Фото-ссылки (внешние) — 6
A57: #keys | C57: cap | D57: url | E57: by
A58: #labels | B58: № / строки ниже | C58: Подпись | D58: Ссылка | E58: Автор
B59: 1 | C59: Территория заповедника Сары-Челек · Sary-Chelek Reserve (3).jpg | D59: https://commons.wikimedia.org/wiki/File:Sary-Chelek_Reserve_(3).jpg | E59: Mixathefast24
B60: 2 | C60: Территория заповедника Сары-Челек · Sary-Chelek Reserve (8).jpg | D60: https://commons.wikimedia.org/wiki/File:Sary-Chelek_Reserve_(8).jpg | E60: Mixathefast24
B61: 3 | C61: Территория заповедника Сары-Челек · Sary Chelek Nature Reserve.jpg | D61: https://commons.wikimedia.org/wiki/File:Sary_Chelek_Nature_Reserve.jpg | E61: Kondephy
B62: 4 | C62: Sarychelek (6) | D62: https://commons.wikimedia.org/wiki/File:Sarychelek_(6).jpg | E62: Mirzoulugʻbek
B63: 5 | C63: Sarychelek (8) | D63: https://commons.wikimedia.org/wiki/File:Sarychelek_(8).jpg | E63: Mirzoulugʻbek
B64: 6 | C64: Домик у озеры Сары-Челек | D64: https://commons.wikimedia.org/wiki/File:%D0%94%D0%BE%D0%BC%D0%B8%D0%BA_%D1%83_%D0%BE%D0%B7%D0%B5%D1%80%D1%8B_%D0%A1%D0%B0%D1%80%D1%8B-%D0%A7%D0%B5%D0%BB%D0%B5%D0%BA.jpg | E64: Panpanchik
A67: #section | B67: Дорога
A68: how | B68: Как добраться (кратко) | C68: Из Бишкека — по трассе Бишкек — Ош до Таш-Кумыра, далее через Кара-Жыгач/Аксы к Аркыту (~540 км, ~11 ч — hiking.kg; TripAdvisor — ~600 км, 8–9 ч). Из Джалал-Абада — ~210 км, ~4,5 ч (govori.tv); из Оша ~300 км. Из Аркыта — через северный КПП ~15 км по серпантину к парковке у основного озера. Сбор за тоннели трассы Бишкек — Ош: 50 сом (КР-номера) / 200 сом (иностранные), с 01.01.2024. Из Ташкента — ~400 км через КПП Учкурган (weproject, 2026).
A69: needcar | B69: Нужна ли машина | C69: Да: маршрутка/такси до Аркыта и машина (такси) от Аркыта до озера, либо 15 км пешком.
A70: self | B70: Самостоятельно / с гидом | C70: Да: пропуска не нужны — плата берётся на шлагбауме (форум eurasia.travel, 09.2025). Самостоятельно — маршрутка до Аркыта + такси/пешком; тропы к малым озёрам читаемые (hiking.kg).
A71: roadtype | B71: Тип дороги | C71: Асфальт до Таш-Кумыра; далее региональные дороги до Аркыта (в селе — без асфальта, govori.tv); от КПП — грунтовая служебная дорога-серпантин ~15 км к парковке (zewanderingfrogs, hiking.kg). В августе 2025 автор hiking.kg отмечал ремонт дороги — проходимость на сегодня не подтверждена. На YouTube есть ролик «дорога до Сары-Челека, едем на седане» — легковушкой проезжают в сухую погоду.
A72: traveltime | B72: Время в пути | C72: Бишкек — Сары-Челек: ~540 км / 11 ч (hiking.kg); Джалал-Абад — Аркыт: 210 км / ~4,5 ч (govori.tv) или ~6 ч на маршрутке; Ош — Аркыт: 7–8 ч на маршрутке. Аркыт — озеро: 15 км, ~40–60 мин на машине (editorial). Тропа к малым озёрам — 3 ч 15 мин.
A73: transfer | B73: Трансфер | C73: Аркыт — озеро: 150 сом/чел. шеринг или 1500 сом за машину туда-обратно (journalofnomads 2026); маршрутка Джалал-Абад — Аркыт 450 сом, Ош — Аркыт ~600 сом; Бишкек — Таш-Кумыр ~800 сом/место.
A74: p_sum | B74: Дорога: сводка | C74: База для Сары-Челека — село Аркыт: из Оша (07:30, 600 сом) и Джалал-Абада (09:00, 450 сом) туда ходит одна ежедневная маршрутка, из Бишкека — шеринг-такси до Таш-Кумыра (~800 сом) и пересадка на полуденную маршрутку до Аркыта (250 сом). Ночуйте 2–3 ночи в гостевом доме Аркыта (500–1000 сом/чел., Booking: Sabira, Kyzyl Alma, Aida — 24–40 $), до главного озера 15–17 км по служебной дороге — такси 1500 сом туда-обратно или 150 сом место. Вход для иностранцев 400 сом (по другим данным 150–200), машина 150 сом, наличными на КПП. Главный однодневный маршрут — тропа по 6 из 7 озёр (11 км, ~4 ч); купаться нельзя.
A75: #table:routes | B75: Подъезды — 4
A76: #keys | C76: rec | D76: title | E76: from | F76: route | G76: km | H76: time | I76: surface | J76: vehicle | K76: season | L76: last | M76: parking_d | N76: parking_price | O76: trail_d | P76: haz | Q76: src | R76: hub | S76: hub_lat | T76: hub_lon | U76: rkm | V76: parking_lat | W76: parking_lon | X76: trail_lat | Y76: trail_lon | Z76: road | AA76: has_rt
A77: #labels | B77: № / строки ниже | C77: Рекомендован (да/нет) | D77: Название варианта | E77: Откуда | F77: Маршрут | G77: Км | H77: Время | I77: Покрытие | J77: Машина | K77: Сезон | L77: Последние АЗС/магазины | M77: Парковка | N77: Парковка: цена | O77: Тропа от парковки | P77: Опасности | Q77: Источник | R77: Город-старт | S77: Старт: широта | T77: Старт: долгота | U77: Км по графу дорог | V77: Парковка: широта | W77: Парковка: долгота | X77: Тропа: широта | Y77: Тропа: долгота | Z77: Геометрия дороги (JSON, генерируется) | AA77: Есть маршрут на карте (да/нет)
B78: 1 | C78: да | D78: Из Оша / Джалал-Абада через Таш-Кумыр | E78: Ош (~300–330 км), Джалал-Абад (~210 км) | F78: Ош → Джалал-Абад → Кочкор-Ата → Таш-Кумыр → Кара-Жыгач → Аркыт | G78: Ош 330 / Джалал-Абад 210 | H78: Ош 6–8 ч, Джалал-Абад 4,5–6 ч | I78: Асфальт до Таш-Кумыра, далее региональная дорога, грунт в Аркыте и к озеру | J78: седан / кроссовер | K78: май — октябрь | L78: Таш-Кумыр — банкоматы, АЗС, базар | M78: Как выше | N78: 150 сом | O78: Как выше | P78: Как выше | Q78: https://www.journalofnomads.com/?p=23132 | R78: Ош | S78: 40.5283 | T78: 72.7985 | U78: 203 | Z78: [[40.529, 72.803], [40.529, 72.812], [40.583, 72.725], [40.665, 72.544], [40.682, 72.473], [40.698, 72.457], [40.756, 72.387], [40.777, 72.341], [40.777, 72.333], [40.768, 72.296], [40.785, 72.242], [40.781, 72.176], [40.789, 72.127], [40.818, 72.057], [40.814, 72.045], [40.838, 72.012], [40.863, 71.962], [40.88, 71.917], [40.888, 71.867], [40.929, 71.847], [40.942, 71.834], [40.966, 71.682], [40.979, 71.665], [40.999, 71.665], [41.041, 71.682], [41.082, 71.743], [41.098, 71.748], [41.14, 71.748], [41.247, 71.694], [41.271, 71.686], [41.296, 71.686], [41.35, 71.69], [41.395, 71.682], [41.441, 71.698], [41.486, 71.752], [41.593, 71.867], [41.63, 71.937], [41.643, 71.979]] | AA78: да
B79: 2 | C79: нет | D79: Из Бишкека через Таш-Кумыр | E79: Бишкек (≈540–600 км) | F79: Бишкек → трасса Бишкек — Ош (тоннель Тоо-Ашуу, Суусамыр, Токтогул) → Таш-Кумыр → на северо-запад через Кара-Жыгач / Аксы (Кербен) → Аркыт → КПП заповедника → 15–17 км серпантина к парковке у озера | G79: 540–600 | H79: 8–11 ч | I79: Асфальт до Таш-Кумыра; региональные дороги до Аркыта (участок Кербен — Кара-Жыгач асфальтируется: 15 км в плане 2025, 2 км готово на 07.2025); в Аркыте и от КПП — грунт, крутой и ухабистый серпантин | J79: седан (в сухую погоду), лучше кроссовер | K79: май — октябрь; зимой проезд от Аркыта не гарантирован | L79: Последние банкоматы и крупные АЗС — Таш-Кумыр / Кербен (Караван); в Аркыте один-два магазина, банкомата нет; мобильной связи в заповеднике нет (частично у Аркыта) | M79: Парковка у конца дороги на берегу главного озера (навесы, мангалы, туалеты); въезд машины — 150 сом на КПП | N79: 150 сом за машину (2025–2026) | O79: Парковка у главного озера — старт тропы к Кыла-Кёлю, Ири-Кёлю и др.; пешком из Аркыта — от КПП на северной окраине села (вход пешком 07:00–14:00) | P79: Крутая грунтовка, грязь после дождя, комары у воды; сбор за тоннели Бишкек — Ош 50/200 сом | Q79: https://www.journalofnomads.com/?p=23132 | R79: Бишкек | S79: 42.8746 | T79: 74.5698 | U79: 436 | V79: 41.874156 | W79: 71.974705 | X79: 41.7956 | Y79: 71.9598 | Z79: [[42.876, 74.536], [42.868, 74.478], [42.847, 74.243], [42.822, 74.103], [42.818, 73.938], [42.798, 73.872], [42.781, 73.88], [42.641, 73.905], [42.587, 73.888], [42.525, 73.855], [42.492, 73.859], [42.414, 73.839], [42.29, 73.847], [42.27, 73.843], [42.253, 73.826], [42.212, 73.727], [42.187, 73.624], [42.175, 73.463], [42.187, 73.232], [42.195, 73.191], [42.195, 73.121], [42.204, 73.084], [42.245, 73.018], [42.249, 72.981], [42.237, 72.968], [42.204, 72.972], [42.175, 72.948], [42.154, 72.841], [42.121, 72.795], [42.105, 72.791], [42.055, 72.816], [42.01, 72.824], [41.989, 72.849], [41.911, 72.907], [41.878, 72.981], [41.878, 73.018], [41.841, 73.187], [41.799, 73.228], [41.795, 73.241], [41.795, 73.298], [41.787, 73.323], [41.775, 73.335], [41.758, 73.335], [41.742, 73.319], [41.733, 73.294], [41.733, 73.249], [41.713, 73.216], [41.705, 73.166], [41.709, 73.117], [41.742, 73.034], [41.742, 73.01], [41.696, 72.898], [41.68, 72.915], [41.672, 72.907], [41.655, 72.799], [41.614, 72.663], [41.63, 72.634], [41.622, 72.572], [41.568, 72.506], [41.564, 72.49], [41.535, 72.449], [41.523, 72.42], [41.515, 72.362], [41.498, 72.317], [41.474, 72.275], [41.436, 72.234], [41.42, 72.23], [41.453, 72.214], [41.478, 72.23], [41.486, 72.251], [41.507, 72.263], [41.515, 72.238], [41.511, 72.214], [41.552, 72.185], [41.581, 72.148], [41.597, 72.115], [41.63, 72.082], [41.643, 72.02], [41.643, 71.979]] | AA79: да
B80: 3 | C80: нет | D80: Из Ташкента через Учкурган / Наманган | E80: Ташкент (~400 км) | F80: Ташкент → Наманган → КПП Учкурган → Ташкумыр/Кербен → Аркыт | G80: ≈400 | H80: 1 день | I80: Асфальт + региональные дороги | J80: седан | K80: май — октябрь | L80: Узбекская сторона / Кербен | P80: Пограничный переход | Q80: https://teletype.in/@poehali_uz/XBkNdmgNQt8 | R80: Ташкент | S80: 41.311 | T80: 69.279 | U80: 340 | Z80: [[41.321, 69.273], [41.284, 69.318], [41.255, 69.405], [41.239, 69.413], [41.181, 69.417], [41.16, 69.425], [41.098, 69.458], [41.049, 69.496], [41.036, 69.512], [40.987, 69.557], [40.937, 69.59], [40.925, 69.652], [40.925, 69.722], [40.937, 69.809], [40.987, 69.982], [40.995, 70.032], [41.016, 70.081], [41.032, 70.164], [41.074, 70.217], [41.086, 70.25], [41.111, 70.366], [41.144, 70.407], [41.168, 70.469], [41.119, 70.518], [41.094, 70.56], [41.028, 70.63], [41.024, 70.646], [40.999, 70.667], [40.946, 70.737], [40.929, 70.749], [40.888, 70.811], [40.772, 70.853], [40.739, 70.836], [40.752, 70.886], [40.801, 70.947], [40.88, 71.084], [40.933, 71.162], [40.987, 71.224], [41.016, 71.236], [41.123, 71.393], [41.218, 71.471], [41.243, 71.508], [41.247, 71.541], [41.296, 71.686], [41.35, 71.69], [41.395, 71.682], [41.441, 71.698], [41.486, 71.752], [41.593, 71.867], [41.63, 71.937], [41.643, 71.979]] | AA80: да
B81: 4 | C81: нет | D81: Конными/пешими треками (Афлатун, Кара-Суу, Беш-Арал) | E81: Афлатун / Кызыл-Кёль / Чаткальская долина | F81: Афлатун → Уялма → пер. Кульдамбес (2946 м) → Сары-Челек; или Кара-Суу → пер. Макмал (2654 м) → Сары-Челек | G81: 12–20 за этап | H81: 2–8 дней | I81: тропы | J81: пешком/верхом | K81: конец июня — сентябрь | O81: Аркыт / Афлатун | P81: Перевалы до ~2950 м | Q81: https://www.centralasia-travel.com/en/trekking/tien-shan/sari-chelek | R81: Кара-Суу | S81: 41.861139 | T81: 72.925051 | U81: 188 | Z81: [[41.878, 72.981], [41.878, 73.018], [41.841, 73.187], [41.799, 73.228], [41.795, 73.241], [41.795, 73.298], [41.787, 73.323], [41.775, 73.335], [41.758, 73.335], [41.742, 73.319], [41.733, 73.294], [41.733, 73.249], [41.713, 73.216], [41.705, 73.166], [41.709, 73.117], [41.742, 73.034], [41.742, 73.01], [41.696, 72.898], [41.68, 72.915], [41.672, 72.907], [41.655, 72.799], [41.614, 72.663], [41.63, 72.634], [41.622, 72.572], [41.568, 72.506], [41.564, 72.49], [41.535, 72.449], [41.523, 72.42], [41.515, 72.362], [41.498, 72.317], [41.474, 72.275], [41.436, 72.234], [41.42, 72.23], [41.453, 72.214], [41.478, 72.23], [41.486, 72.251], [41.507, 72.263], [41.515, 72.238], [41.511, 72.214], [41.552, 72.185], [41.581, 72.148], [41.597, 72.115], [41.63, 72.082], [41.643, 72.02], [41.643, 71.979]] | AA81: да
A83: #table:transport | B83: Транспорт и туры — 15
A84: #keys | C84: mode | D84: provider | E84: from | F84: details | G84: price | H84: year | I84: contact | J84: src
A85: #labels | B85: № / строки ниже | C85: Вид | D85: Перевозчик | E85: Откуда | F85: Подробно | G85: Цена | H85: Год цены | I85: Контакт | J85: Источник
B86: 1 | C86: маршрутка | D86: Ош → Аркыт | E86: Новый автовокзал Оша (ул. Касымбекова / Курманжан Датки) | F86: Ежедневно 07:30, 7–8 ч, через Джалал-Абад, Кочкор-Ату, Таш-Кумыр | G86: 600 сом | H86: 2026 | J86: https://www.journalofnomads.com/?p=23132
B87: 2 | C87: маршрутка | D87: Джалал-Абад → Аркыт | E87: Джалал-Абад | F87: Та же маршрутка, ~09:00, 6 ч | G87: 450 сом | H87: 2026 | J87: https://www.journalofnomads.com/?p=23132
B88: 3 | C88: маршрутка | D88: Таш-Кумыр → Аркыт | E88: Таш-Кумыр | F88: Около полудня, ~3 ч | G88: 250 сом | H88: 2026 | J88: https://www.journalofnomads.com/?p=23132
B89: 4 | C89: шеринг-такси | D89: Бишкек → Таш-Кумыр | E89: Бишкек (по journalofnomads — стоянка у Западного автовокзала; как автовокзал Западный закрыт с 10.2024 — уточнять) | F89: ~6 ч | G89: 800 сом/место; прямое шеринг-такси до Аркыта ~1200 сом (не подтверждено) | H89: 2025–2026 | J89: https://adventuresoflilnicki.com/sary-chelek-kyrgyzstan/
B90: 5 | C90: шеринг-такси | D90: Ош / Джалал-Абад → Аркыт | E90: Ош, Джалал-Абад | F90: Ош 6 ч, Джалал-Абад 5 ч | G90: Ош 1000 сом/чел.; Джалал-Абад ~800 сом/чел. | H90: 2026 | J90: https://www.journalofnomads.com/?p=23132
B91: 6 | C91: такси | D91: Частное такси | E91: Ош / Джалал-Абад → Аркыт | F91: Вся машина | G91: Ош 5000–6000 сом; Джалал-Абад 5000 сом | H91: 2026 | J91: https://www.journalofnomads.com/?p=23132
B92: 7 | C92: такси | D92: Аркыт → озеро (17 км) | E92: Аркыт | F92: Шеринг 150 сом в одну сторону; частное 1500 сом туда-обратно; в июне — сентябре маршрутка 3000 сом туда-обратно на всех (~250 сом/чел. при полной) | G92: 150–1500 сом | H92: 2026 | J92: https://www.journalofnomads.com/?p=23132
B93: 8 | C93: лодка | D93: Катера у главного озера | E93: Парковка | F93: Моторные лодки — торговаться; бывают неисправны | G93: ≈1000 сом/чел. за час | H93: 2026 | J93: https://www.journalofnomads.com/?p=23132
B94: 9 | C94: тур | D94: Nomad's Land «Magic lakes of Sary Chelek» | E94: Ош | F94: 6 дней, ~81 км верхом: Аркыт → Кара-Суу → Сары-Челек → Бакалы-Кёль → Аркыт; для начинающих | G94: 779 $ (1 чел.) … 372 $/чел. (6+) | H94: 2025–2026 | I94: nomadsland.travel | J94: https://nomadsland.travel/en/offers/private-tours/magic-lakes-sary-chelek
B95: 10 | C95: тур | D95: Central Asia Travel — трек к Сары-Челеку | E95: Ош / Бишкек | F95: 8 дней (Ош — Ош): Афлатун — Кульдамбес — Сары-Челек — Макмал — Кара-Суу — Кутурма — Кыла-Кёль; даты 2026: конец июня — июль | G95: 1130 $ (Ош — Ош), 1475 $ (Бишкек — Бишкек) | H95: 2026 | I95: centralasia-travel.com | J95: https://www.centralasia-travel.com/en/trekking/tien-shan/sari-chelek
B96: 11 | C96: тур | D96: Туры из Ташкента (poehali_uz) | E96: Ташкент | F96: 3 дня, коттеджи, питание, вход, гид; лошади и катер — доплата | G96: 2 390 000 сум | H96: 2025 | J96: https://teletype.in/@poehali_uz/XBkNdmgNQt8
B97: 12 | C97: лошадь | D97: CBT / гостевые дома Аркыта | E97: Аркыт | F97: Многодневные конные туры через туристические офисы | G97: не опубликовано | I97: Destination Jalal-Abad / CBT | J97: https://www.journalofnomads.com/?p=23132
B98: 13 | C98: другое | D98: Точка отправки южных маршрутов из Бишкека | E98: Бишкек | F98: С 28.10.2024 маршруты на Ош, Джалал-Абад, Баткен и Талас отправляются с западной окраины (участок у будущего ипподрома «Ак-Кула», рядом с постом ГАИ); туда идут автобусы №13, №40 и маршрутка №258 | H98: 2024 | J98: https://kaktus.media/doc/512072_izmeneny_otpravnye_tochki_mejdygorodnih_marshrytov_iz_bishkeka.html
B99: 14 | C99: другое | D99: Asman Airlines Бишкек — Кербен (дотационный рейс, аэропорт «Караван») | E99: Бишкек | F99: 2 раза в неделю (ср, пт) по данным 01.2026; в 09.2024 рейсы временно приостанавливались — проверять в приложении Asman | G99: 3600 сом | H99: 2026 | I99: приложение Asman Airlines | J99: https://economist.kg/transport/2026/01/26/asman-airlines-rasshiriaiet-siet-dotatsionnykh-rieisov-po-kyrghyzstanu/
B100: 15 | C100: маршрутка | D100: Аркыт → Ош (обратная) | E100: Аркыт | F100: Отправление рано утром, около 06:00 (данные 2017 г., уточнять у хозяев гостевого дома) | H100: 2017 | J100: https://worldheritagesite.org/community/jarek-pokrzywnicki/western-tien-shan
A103: #section | B103: Сезон и что взять
A104: when | B104: Когда ехать (подробно) | C104: Середина мая — сентябрь/начало октября; до середины мая дорога может быть закрыта снегом (central-asia.guide). Май — октябрь подходит для пеших и конных прогулок (journalofnomads). В октябре ночи ниже нуля (TripAdvisor).
A105: diff | B105: Сложность (подробно) | C105: Посещение основного озера — лёгкое (машина до парковки у берега). Тропа к малым озёрам и панораме — 7,1 км, 3 ч 15 мин, набор 760 м, сложность 4/5 по hiking.kg. Пешком от ворот до озера — 15 км с набором ~600 м (zewanderingfrogs).
A106: hours | B106: Часы работы | C106: Въезд через КПП (шлагбаум) заповедника на северном выезде из Аркыта; часы работы КПП официально не опубликованы. В 2026 г. запланирован автоматизированный КПП (time.kg, 08.06.2026). Вне сезона въезд ограничен погодой.
A107: daytime | B107: Лучшее время суток | C107: Раннее утро — зеркальная гладь, мягкий свет и меньше людей; на обратную дорогу по серпантину выезжай засветло (editorial).
A108: p_season | B108: Сезон (подробно) | C108: Май — июнь: зелень, дожди, грязь на грунтовке. Июль — сентябрь: тепло до +25 °C, пик посещений (бронировать жильё заранее в июле — августе), комары у воды. Октябрь: осенние краски ореховых и плодовых лесов. Ноябрь — апрель: доступ ограничен погодой, уточнять в CBT Jalal-Abad.
